Workbook
Name Pct_Cesiones: #REF!
Name SA_abs: #REF!
Name SA_comerc: #REF!
Name SA_conting: #REF!
Name SA_GG_BI: #REF!
Name SA_honorarios: #REF!
Name SA_licencias: #REF!
Name SA_m2_media: #REF!
Name SA_precio_m2: #REF!
Name SA_unidades: #REF!
Name Sup_Parcela_Bruta: #REF!
Name Sup_Parcela_Neta: #REF!

Sheet 00_ESTRATEGIA
A1: SELECCIONES ESTRATÉGICAS | D1: INDICADORES DE RENTABILIDAD
A2: Variable | B2: Selección | D2: Métrica | E2: Venta | F2: Alquiler
A3: Tipología | B3: Unifamiliar seg. | D3: TIR | E3: ='30_CASHFLOW'!B45 -> 0.1367759 | F3: ='30_CASHFLOW'!C45 -> 0.0086677881
A4: Escenario | B4: Base | D4: VAN | E4: ='30_CASHFLOW'!B46 -> 468930.73 | F4: ='30_CASHFLOW'!C46 -> -2949614.9
A5: Horizonte (alquiler) | B5: 15 | D5: Tasa descuento (VAN) | E5: 0.08 | F5: 0.06
A6: Año inicial | B6: 2028
A7: Parcela bruta (m2) | B7: 9290
A8: Sensibilidad financiera | B8: Base
A11: INDICADORES CON FINANCIACIÓN (Capa Financiera)
A12: TIR (anualizada) | B12: ='30_CASHFLOW'!B49 -> 0.17348834
A13: VAN @ Ke | B13: ='30_CASHFLOW'!B50 -> 157181.39
A14: Capital propio máximo | B14: ='30_CASHFLOW'!B51 -> 1570326
A15: Coste suelo | B15: ='10_CAPEX-INGRESOS-PAGOS'!$B$16 -> 1183546
A16: Coste extra | B16: =B14-B15 -> 386780.02
A17: Equity multiple (MOIC) | B17: ='30_CASHFLOW'!B52 -> 1.3803175

Sheet 01_MODELO
A2: CONFIGURACIÓN TÉCNICA
A3: Parámetro | B3: Unifamiliar seg. | C3: Unifamiliar conj. | D3: Plurifamiliar U2C | E3: Plurifamiliar U4C | F3: Unidades | H3: Parámetro | I3: ='00_ESTRATEGIA'!B3 -> Unifamiliar seg.
A4: Parcela | H4: =A4 -> Parcela
A5: Superficie parcela bruta | B5: ='00_ESTRATEGIA'!$B$7 -> 9290 | C5: ='00_ESTRATEGIA'!$B$7 -> 9290 | D5: ='00_ESTRATEGIA'!$B$7 -> 9290 | E5: ='00_ESTRATEGIA'!$B$7 -> 9290 | F5: m² | H5: =A5 -> Superficie parcela bruta | I5: {=_xlfn.SWITCH($I$3,$B$3,B5,$C$3,C5,$D$3,D5,$E$3,E5)} -> 9290
A6: % cesiones / afecciones | B6: 0 | C6: 0 | D6: 0 | E6: 0 | F6: % | H6: =A6 -> % cesiones / afecciones | I6: {=_xlfn.SWITCH($I$3,$B$3,B6,$C$3,C6,$D$3,D6,$E$3,E6)} -> 0
A7: Superficie parcela neta | B7: =B5*(1-B6) -> 9290 | C7: =C5*(1-C6) -> 9290 | D7: =D5*(1-D6) -> 9290 | E7: =E5*(1-E6) -> 9290 | F7: m² | H7: =A7 -> Superficie parcela neta | I7: {=_xlfn.SWITCH($I$3,$B$3,B7,$C$3,C7,$D$3,D7,$E$3,E7)} -> 9290
A8: Parámetros urbanísticos | H8: =A8 -> Parámetros urbanísticos
A9: Ordenanza aplicable | B9: U2 | C9: U2 | D9: U2C | E9: U4C | F9: — | H9: =A9 -> Ordenanza aplicable | I9: {=_xlfn.SWITCH($I$3,$B$3,B9,$C$3,C9,$D$3,D9,$E$3,E9)} -> U2
A10: Superficie ámbito | B10: =$B$7 -> 9290 | C10: =$B$7 -> 9290 | D10: =$B$7 -> 9290 | E10: =$B$7 -> 9290 | F10: m² | H10: =A10 -> Superficie ámbito | I10: {=_xlfn.SWITCH($I$3,$B$3,B10,$C$3,C10,$D$3,D10,$E$3,E10)} -> 9290
A11: Edificabilidad | B11: 0.45 | C11: 0.45 | D11: 0.45 | E11: 0.65 | F11: m²/m² | H11: =A11 -> Edificabilidad | I11: {=_xlfn.SWITCH($I$3,$B$3,B11,$C$3,C11,$D$3,D11,$E$3,E11)} -> 0.45
A12: Ocupación | B12: 0.25 | C12: 0.25 | D12: 0.2 | E12: 0.2 | F12: % | H12: =A12 -> Ocupación | I12: {=_xlfn.SWITCH($I$3,$B$3,B12,$C$3,C12,$D$3,D12,$E$3,E12)} -> 0.25
A13: Número máximo de plantas | B13: 2 | C13: 2 | D13: 3 | E13: 4 | F13: plantas | H13: =A13 -> Número máximo de plantas | I13: {=_xlfn.SWITCH($I$3,$B$3,B13,$C$3,C13,$D$3,D13,$E$3,E13)} -> 2
A14: Altura máxima | B14: 7 | C14: 7 | D14: 10 | E14: 13 | F14: m | H14: =A14 -> Altura máxima | I14: {=_xlfn.SWITCH($I$3,$B$3,B14,$C$3,C14,$D$3,D14,$E$3,E14)} -> 7
A15: Capacidad edificatoria | H15: =A15 -> Capacidad edificatoria | I15: =_xlfn.SWITCH($I$3,$B$3,B15,$C$3,C15,$D$3,D15,$E$3,E15) -> 0
A16: Techo máximo edificable | B16: =B10*B11 -> 4180.5 | C16: =C10*C11 -> 4180.5 | D16: =D10*D11 -> 4180.5 | E16: =E10*E11 -> 6038.5 | F16: m² | H16: =A16 -> Techo máximo edificable | I16: {=_xlfn.SWITCH($I$3,$B$3,B16,$C$3,C16,$D$3,D16,$E$3,E16)} -> 4180.5
A17: Huella máxima en planta | B17: =B10*B12 -> 2322.5 | C17: =C10*C12 -> 2322.5 | D17: =D10*D12 -> 1858 | E17: =E10*E12 -> 1858 | F17: m² | H17: =A17 -> Huella máxima en planta | I17: {=_xlfn.SWITCH($I$3,$B$3,B17,$C$3,C17,$D$3,D17,$E$3,E17)} -> 2322.5
A18: Eficiencia edificatoria | B18: 1 | C18: 1 | D18: 0.85 | E18: 0.85 | F18: % | H18: =A18 -> Eficiencia edificatoria | I18: {=_xlfn.SWITCH($I$3,$B$3,B18,$C$3,C18,$D$3,D18,$E$3,E18)} -> 1
A19: Definición del producto | H19: =A19 -> Definición del producto
A20: Parcela mínima | B20: 700 | C20: No aplica | D20: No aplica | E20: No aplica | F20: m² | H20: =A20 -> Parcela mínima | I20: {=_xlfn.SWITCH($I$3,$B$3,B20,$C$3,C20,$D$3,D20,$E$3,E20)} -> 700
A21: Parcela media | B21: =B10/B29 -> 714.61538 | C21: =C10/C29 -> 546.47059 | D21: No aplica | E21: No aplica | F21: m² | H21: =A21 -> Parcela media | I21: {=_xlfn.SWITCH($I$3,$B$3,B21,$C$3,C21,$D$3,D21,$E$3,E21)} -> 714.61538
A22: Huella por vivienda | B22: =B21*B12 -> 178.65385 | C22: =C21*C12 -> 136.61765 | D22: No aplica | E22: No aplica | F22: m² | H22: =A22 -> Huella por vivienda | I22: {=_xlfn.SWITCH($I$3,$B$3,B22,$C$3,C22,$D$3,D22,$E$3,E22)} -> 178.65385
A23: Parcela libre | B23: =B21-B22 -> 535.96154 | C23: =C21-C22 -> 409.85294 | D23: No aplica | E23: No aplica | F23: m² | H23: =A23 -> Parcela libre | I23: {=_xlfn.SWITCH($I$3,$B$3,B23,$C$3,C23,$D$3,D23,$E$3,E23)} -> 535.96154
A24: Tamaño mínimo vivienda | B24: 240 | C24: 240 | D24: 90 | E24: 90 | F24: m² | H24: =A24 -> Tamaño mínimo vivienda | I24: {=_xlfn.SWITCH($I$3,$B$3,B24,$C$3,C24,$D$3,D24,$E$3,E24)} -> 240
A25: Tamaño máximo vivienda | B25: =B16/B29 -> 321.57692 | C25: =C16/C29 -> 245.91176 | D25: =D24 -> 90 | E25: =E24 -> 90 | F25: m² | H25: =A25 -> Tamaño máximo vivienda | I25: {=_xlfn.SWITCH($I$3,$B$3,B25,$C$3,C25,$D$3,D25,$E$3,E25)} -> 321.57692
A26: Tamaño elegido vivienda | B26: =B24 -> 240 | C26: =C24 -> 240 | D26: =D24 -> 90 | E26: =E24 -> 90 | F26: m² | H26: =A26 -> Tamaño elegido vivienda | I26: {=_xlfn.SWITCH($I$3,$B$3,B26,$C$3,C26,$D$3,D26,$E$3,E26)} -> 240
A27: Resultado físico del proyecto | H27: =A27 -> Resultado físico del proyecto
A28: Superficie construida media | B28: =B26 -> 240 | C28: =C26 -> 240 | D28: =D26 -> 90 | E28: =E26 -> 90 | F28: m² | H28: =A28 -> Superficie construida media | I28: {=_xlfn.SWITCH($I$3,$B$3,B28,$C$3,C28,$D$3,D28,$E$3,E28)} -> 240
A29: Número estimado de unidades | B29: =INT(IF(B20<>"No aplica",INT(B10/B20),B16*B18/B24)) -> 13 | C29: =INT(IF(C20<>"No aplica",INT(C10/C20),C16*C18/C24)) -> 17 | D29: =INT(IF(D20<>"No aplica",INT(D10/D20),D16*D18/D24)) -> 39 | E29: =INT(IF(E20<>"No aplica",INT(E10/E20),E16*E18/E24)) -> 57 | F29: unidades | H29: =A29 -> Número estimado de unidades | I29: {=_xlfn.SWITCH($I$3,$B$3,B29,$C$3,C29,$D$3,D29,$E$3,E29)} -> 13
A30: Huella en planta | B30: =B28/B13 -> 120 | C30: =C28/C13 -> 120 | D30: =D29*D28/D13 -> 1170 | E30: =E29*E28/E13 -> 1282.5 | F30: m² | H30: =A30 -> Huella en planta | I30: {=_xlfn.SWITCH($I$3,$B$3,B30,$C$3,C30,$D$3,D30,$E$3,E30)} -> 120
A31: Variables temporales | H31: =A31 -> Variables temporales
A32: Año inicio proyecto | B32: 0 | C32: 0 | D32: 0 | E32: 0 | F32: año | H32: =A32 -> Año inicio proyecto | I32: {=_xlfn.SWITCH($I$3,$B$3,B32,$C$3,C32,$D$3,D32,$E$3,E32)} -> 0
A33: Fase de diseño | B33: {=5*(1+_xlfn.SWITCH('02_ESCENARIOS'!$G$2,'02_ESCENARIOS'!$B$2,'02_ESCENARIOS'!$B$17,'02_ESCENARIOS'!$C$2,'02_ESCENARIOS'!$C$17,'02_ESCENARIOS'!$D$2,'02_ESCENARIOS'!$D$17))} -> 5 | C33: {=5*(1+_xlfn.SWITCH('02_ESCENARIOS'!$G$2,'02_ESCENARIOS'!$B$2,'02_ESCENARIOS'!$B$17,'02_ESCENARIOS'!$C$2,'02_ESCENARIOS'!$C$17,'02_ESCENARIOS'!$D$2,'02_ESCENARIOS'!$D$17))} -> 5 | D33: {=5*(1+_xlfn.SWITCH('02_ESCENARIOS'!$G$2,'02_ESCENARIOS'!$B$2,'02_ESCENARIOS'!$B$17,'02_ESCENARIOS'!$C$2,'02_ESCENARIOS'!$C$17,'02_ESCENARIOS'!$D$2,'02_ESCENARIOS'!$D$17))} -> 5 | E33: {=5*(1+_xlfn.SWITCH('02_ESCENARIOS'!$G$2,'02_ESCENARIOS'!$B$2,'02_ESCENARIOS'!$B$17,'02_ESCENARIOS'!$C$2,'02_ESCENARIOS'!$C$17,'02_ESCENARIOS'!$D$2,'02_ESCENARIOS'!$D$17))} -> 5 | F33: meses | H33: =A33 -> Fase de diseño | I33: {=_xlfn.SWITCH($I$3,$B$3,B33,$C$3,C33,$D$3,D33,$E$3,E33)} -> 5
A34: Fase de licitaciones y permisos | B34: {=6*(1+_xlfn.SWITCH('02_ESCENARIOS'!$G$2,'02_ESCENARIOS'!$B$2,'02_ESCENARIOS'!$B$17,'02_ESCENARIOS'!$C$2,'02_ESCENARIOS'!$C$17,'02_ESCENARIOS'!$D$2,'02_ESCENARIOS'!$D$17))} -> 6 | C34: {=6*(1+_xlfn.SWITCH('02_ESCENARIOS'!$G$2,'02_ESCENARIOS'!$B$2,'02_ESCENARIOS'!$B$17,'02_ESCENARIOS'!$C$2,'02_ESCENARIOS'!$C$17,'02_ESCENARIOS'!$D$2,'02_ESCENARIOS'!$D$17))} -> 6 | D34: {=6*(1+_xlfn.SWITCH('02_ESCENARIOS'!$G$2,'02_ESCENARIOS'!$B$2,'02_ESCENARIOS'!$B$17,'02_ESCENARIOS'!$C$2,'02_ESCENARIOS'!$C$17,'02_ESCENARIOS'!$D$2,'02_ESCENARIOS'!$D$17))} -> 6 | E34: {=6*(1+_xlfn.SWITCH('02_ESCENARIOS'!$G$2,'02_ESCENARIOS'!$B$2,'02_ESCENARIOS'!$B$17,'02_ESCENARIOS'!$C$2,'02_ESCENARIOS'!$C$17,'02_ESCENARIOS'!$D$2,'02_ESCENARIOS'!$D$17))} -> 6 | F34: meses | H34: =A34 -> Fase de licitaciones y permisos | I34: {=_xlfn.SWITCH($I$3,$B$3,B34,$C$3,C34,$D$3,D34,$E$3,E34)} -> 6
A35: Inicio obra | B35: =B32+(B33+B34) -> 11 | C35: =C32+(C33+C34) -> 11 | D35: =D32+(D33+D34) -> 11 | E35: =E32+(E33+E34) -> 11 | F35: mes | H35: =A35 -> Inicio obra | I35: {=_xlfn.SWITCH($I$3,$B$3,B35,$C$3,C35,$D$3,D35,$E$3,E35)} -> 11
A36: Duración obra (meses) | B36: {=24*(1+_xlfn.SWITCH('02_ESCENARIOS'!$G$2,'02_ESCENARIOS'!B2,'02_ESCENARIOS'!B17,'02_ESCENARIOS'!C2,'02_ESCENARIOS'!C17,'02_ESCENARIOS'!D2,'02_ESCENARIOS'!D17))} -> 24 | C36: {=24*(1+_xlfn.SWITCH('02_ESCENARIOS'!$G$2,'02_ESCENARIOS'!B2,'02_ESCENARIOS'!B17,'02_ESCENARIOS'!C2,'02_ESCENARIOS'!C17,'02_ESCENARIOS'!D2,'02_ESCENARIOS'!D17))} -> 24 | D36: {=25*(1+_xlfn.SWITCH('02_ESCENARIOS'!$G$2,'02_ESCENARIOS'!B2,'02_ESCENARIOS'!B17,'02_ESCENARIOS'!C2,'02_ESCENARIOS'!C17,'02_ESCENARIOS'!D2,'02_ESCENARIOS'!D17))} -> 25 | E36: {=27*(1+_xlfn.SWITCH('02_ESCENARIOS'!$G$2,'02_ESCENARIOS'!B2,'02_ESCENARIOS'!B17,'02_ESCENARIOS'!C2,'02_ESCENARIOS'!C17,'02_ESCENARIOS'!D2,'02_ESCENARIOS'!D17))} -> 27 | F36: meses | H36: =A36 -> Duración obra (meses) | I36: {=_xlfn.SWITCH($I$3,$B$3,B36,$C$3,C36,$D$3,D36,$E$3,E36)} -> 24
A37: Fin obra | B37: =B35+B36 -> 35 | C37: =C35+C36 -> 35 | D37: =D35+D36 -> 36 | E37: =E35+E36 -> 38 | F37: mes | H37: =A37 -> Fin obra | I37: {=_xlfn.SWITCH($I$3,$B$3,B37,$C$3,C37,$D$3,D37,$E$3,E37)} -> 35
A38: Variables de coste | H38: =A38 -> Variables de coste | I38: =_xlfn.SWITCH($I$3,$B$3,B38,$C$3,C38,$D$3,D38,$E$3,E38) -> 0
A39: Coste ejecución material | B39: 1323 | C39: =B39 -> 1323 | D39: =C39 -> 1323 | E39: =D39 -> 1323 | F39: €/m² | H39: =A39 -> Coste ejecución material | I39: {=_xlfn.SWITCH($I$3,$B$3,B39,$C$3,C39,$D$3,D39,$E$3,E39)} -> 1323
A40: Factor tipología | B40: 1.12 | C40: 1.08 | D40: 0.92 | E40: 0.97 | F40: — | H40: =A40 -> Factor tipología | I40: {=_xlfn.SWITCH($I$3,$B$3,B40,$C$3,C40,$D$3,D40,$E$3,E40)} -> 1.12
A41: Gastos generales + BI | B41: {=20%+_xlfn.SWITCH('00_ESTRATEGIA'!$B$4,'02_ESCENARIOS'!$B$2,'02_ESCENARIOS'!$B4,'02_ESCENARIOS'!$C$2,'02_ESCENARIOS'!$C4,'02_ESCENARIOS'!$D$2,'02_ESCENARIOS'!$D4)} -> 0.2 | C41: =B41 -> 0.2 | D41: =C41 -> 0.2 | E41: =D41 -> 0.2 | F41: % | H41: =A41 -> Gastos generales + BI | I41: {=_xlfn.SWITCH($I$3,$B$3,B41,$C$3,C41,$D$3,D41,$E$3,E41)} -> 0.2
A42: Contingencia | B42: {=7.5%+_xlfn.SWITCH('00_ESTRATEGIA'!$B$4,'02_ESCENARIOS'!$B$2,'02_ESCENARIOS'!$B5,'02_ESCENARIOS'!$C$2,'02_ESCENARIOS'!$C5,'02_ESCENARIOS'!$D$2,'02_ESCENARIOS'!$D5)} -> 0.075 | C42: {=7%+_xlfn.SWITCH('00_ESTRATEGIA'!$B$4,'02_ESCENARIOS'!$B$2,'02_ESCENARIOS'!$B5,'02_ESCENARIOS'!$C$2,'02_ESCENARIOS'!$C5,'02_ESCENARIOS'!$D$2,'02_ESCENARIOS'!$D5)} -> 0.07 | D42: {=6%+_xlfn.SWITCH('00_ESTRATEGIA'!$B$4,'02_ESCENARIOS'!$B$2,'02_ESCENARIOS'!$B5,'02_ESCENARIOS'!$C$2,'02_ESCENARIOS'!$C5,'02_ESCENARIOS'!$D$2,'02_ESCENARIOS'!$D5)} -> 0.06 | E42: {=6%+_xlfn.SWITCH('00_ESTRATEGIA'!$B$4,'02_ESCENARIOS'!$B$2,'02_ESCENARIOS'!$B5,'02_ESCENARIOS'!$C$2,'02_ESCENARIOS'!$C5,'02_ESCENARIOS'!$D$2,'02_ESCENARIOS'!$D5)} -> 0.06 | F42: % | H42: =A42 -> Contingencia | I42: {=_xlfn.SWITCH($I$3,$B$3,B42,$C$3,C42,$D$3,D42,$E$3,E42)} -> 0.075
A43: Licencias y tasas | B43: {=4.5%+_xlfn.SWITCH('00_ESTRATEGIA'!$B$4,'02_ESCENARIOS'!$B$2,'02_ESCENARIOS'!$B6,'02_ESCENARIOS'!$C$2,'02_ESCENARIOS'!$C6,'02_ESCENARIOS'!$D$2,'02_ESCENARIOS'!$D6)} -> 0.045 | C43: =B43 -> 0.045 | D43: =C43 -> 0.045 | E43: =D43 -> 0.045 | F43: % | H43: =A43 -> Licencias y tasas | I43: {=_xlfn.SWITCH($I$3,$B$3,B43,$C$3,C43,$D$3,D43,$E$3,E43)} -> 0.045
A44: Honorarios técnicos | B44: {=8%+_xlfn.SWITCH('00_ESTRATEGIA'!$B$4,'02_ESCENARIOS'!$B$2,'02_ESCENARIOS'!$B7,'02_ESCENARIOS'!$C$2,'02_ESCENARIOS'!$C7,'02_ESCENARIOS'!$D$2,'02_ESCENARIOS'!$D7)} -> 0.08 | C44: {=8%+_xlfn.SWITCH('00_ESTRATEGIA'!$B$4,'02_ESCENARIOS'!$B$2,'02_ESCENARIOS'!$B7,'02_ESCENARIOS'!$C$2,'02_ESCENARIOS'!$C7,'02_ESCENARIOS'!$D$2,'02_ESCENARIOS'!$D7)} -> 0.08 | D44: {=9%+_xlfn.SWITCH('00_ESTRATEGIA'!$B$4,'02_ESCENARIOS'!$B$2,'02_ESCENARIOS'!$B7,'02_ESCENARIOS'!$C$2,'02_ESCENARIOS'!$C7,'02_ESCENARIOS'!$D$2,'02_ESCENARIOS'!$D7)} -> 0.09 | E44: {=9%+_xlfn.SWITCH('00_ESTRATEGIA'!$B$4,'02_ESCENARIOS'!$B$2,'02_ESCENARIOS'!$B7,'02_ESCENARIOS'!$C$2,'02_ESCENARIOS'!$C7,'02_ESCENARIOS'!$D$2,'02_ESCENARIOS'!$D7)} -> 0.09 | F44: % | H44: =A44 -> Honorarios técnicos | I44: {=_xlfn.SWITCH($I$3,$B$3,B44,$C$3,C44,$D$3,D44,$E$3,E44)} -> 0.08
A46: ESCENARIOS DE EXPLOTACIÓN
A47: Parámetro | B47: Unifamiliar seg. | C47: Unifamiliar conj. | D47: Plurifamiliar U2C | E47: Plurifamiliar U4C | F47: Unidades | H47: Parámetro | I47: =I3 -> Unifamiliar seg.
A48: VENTA | H48: =A48 -> VENTA
A49: Vivienda | H49: =A49 -> Vivienda
A50: Precio venta ML | B50: 603759 | C50: 603759 | D50: 314318 | E50: 314318 | F50: € | H50: =A50 -> Precio venta ML | I50: {=_xlfn.SWITCH($I$3,$B$3,B50,$C$3,C50,$D$3,D50,$E$3,E50)} -> 603759
A51: Superficie construida | B51: 240 | C51: 240 | D51: 90 | E51: 90 | F51: m² | H51: =A51 -> Superficie construida | I51: {=_xlfn.SWITCH($I$3,$B$3,B51,$C$3,C51,$D$3,D51,$E$3,E51)} -> 240
A52: Precio corregido por perfil comprador | B52: 1.1 | C52: 1.05 | D52: 1 | E52: 1 | F52: - | H52: =A52 -> Precio corregido por perfil comprador | I52: {=_xlfn.SWITCH($I$3,$B$3,B52,$C$3,C52,$D$3,D52,$E$3,E52)} -> 1.1
A53: Precio medio por unidad | B53: =B50*B52 -> 664134.9 | C53: =C50*C52 -> 633946.95 | D53: =D50*D52 -> 314318 | E53: =E50*E52 -> 314318 | F53: € | H53: =A53 -> Precio medio por unidad | I53: {=_xlfn.SWITCH($I$3,$B$3,B53,$C$3,C53,$D$3,D53,$E$3,E53)} -> 664134.9
A54: Parcela | H54: =A54 -> Parcela | I54: {=_xlfn.SWITCH($I$3,$B$3,B54,$C$3,C54,$D$3,D54,$E$3,E54)} -> 0
A55: Superficie parcela | B55: ='01_MODELO'!B21 -> 714.61538 | C55: ='01_MODELO'!C21 -> 546.47059 | D55: No aplica | E55: No aplica | F55: m² | H55: =A55 -> Superficie parcela | I55: {=_xlfn.SWITCH($I$3,$B$3,B55,$C$3,C55,$D$3,D55,$E$3,E55)} -> 714.61538
A56: Diferencia con parcela 533,33 | B56: =B55-533.33 -> 181.28538 | C56: =C55-533.33 -> 13.140588 | D56: No aplica | E56: No aplica | F56: m² | H56: =A56 -> Diferencia con parcela 533,33 | I56: {=_xlfn.SWITCH($I$3,$B$3,B56,$C$3,C56,$D$3,D56,$E$3,E56)} -> 181.28538
A57: Precio suelo | B57: ='10_CAPEX-INGRESOS-PAGOS'!B15*2 -> 254.8 | C57: ='10_CAPEX-INGRESOS-PAGOS'!C15*2 -> 254.8 | D57: No aplica | E57: No aplica | F57: €/m² | H57: =A57 -> Precio suelo | I57: {=_xlfn.SWITCH($I$3,$B$3,B57,$C$3,C57,$D$3,D57,$E$3,E57)} -> 254.8
A58: Valor parcela | B58: =B56*B57 -> 46191.516 | C58: =C56*C57 -> 3348.2219 | D58: No aplica | E58: No aplica | F58: € | H58: =A58 -> Valor parcela | I58: {=_xlfn.SWITCH($I$3,$B$3,B58,$C$3,C58,$D$3,D58,$E$3,E58)} -> 46191.516
A59: Precio Total Unidad | H59: =A59 -> Precio Total Unidad | I59: {=_xlfn.SWITCH($I$3,$B$3,B59,$C$3,C59,$D$3,D59,$E$3,E59)} -> 0
A60: Precio total por unidad calculado | B60: =B53+B58 -> 710326.42 | C60: =C53+C58 -> 637295.17 | D60: =D50 -> 314318 | E60: =E50 -> 314318 | F60: € | H60: =A60 -> Precio total por unidad calculado | I60: {=_xlfn.SWITCH($I$3,$B$3,B60,$C$3,C60,$D$3,D60,$E$3,E60)} -> 710326.42
A61: Precio equivalente €/m² construido | B61: =B60/B51 -> 2959.6934 | C61: =C60/C51 -> 2655.3965 | D61: =D60/D51 -> 3492.4222 | E61: =E60/E51 -> 3492.4222 | F61: €/m² | H61: =A61 -> Precio equivalente €/m² construido | I61: {=_xlfn.SWITCH($I$3,$B$3,B61,$C$3,C61,$D$3,D61,$E$3,E61)} -> 2959.6934
A62: Ingreso Bruto | B62: =B60*B29 -> 9234243.4 | C62: =C60*C29 -> 10834018 | D62: =D60*D29 -> 12258402 | E62: =E60*E29 -> 17916126 | F62: € | H62: =A62 -> Ingreso Bruto | I62: {=_xlfn.SWITCH($I$3,$B$3,B62,$C$3,C62,$D$3,D62,$E$3,E62)} -> 9234243.4
A63: Comercialización | B63: {=3%+_xlfn.SWITCH('00_ESTRATEGIA'!$B$4,'02_ESCENARIOS'!$B$2,'02_ESCENARIOS'!$B$9,'02_ESCENARIOS'!$C$2,'02_ESCENARIOS'!$C$9,'02_ESCENARIOS'!$D$2,'02_ESCENARIOS'!$D$9)} -> 0.03 | C63: {=3%+_xlfn.SWITCH('00_ESTRATEGIA'!$B$4,'02_ESCENARIOS'!$B$2,'02_ESCENARIOS'!$B$9,'02_ESCENARIOS'!$C$2,'02_ESCENARIOS'!$C$9,'02_ESCENARIOS'!$D$2,'02_ESCENARIOS'!$D$9)} -> 0.03 | D63: {=4%+_xlfn.SWITCH('00_ESTRATEGIA'!$B$4,'02_ESCENARIOS'!$B$2,'02_ESCENARIOS'!$B$9,'02_ESCENARIOS'!$C$2,'02_ESCENARIOS'!$C$9,'02_ESCENARIOS'!$D$2,'02_ESCENARIOS'!$D$9)} -> 0.04 | E63: {=4%+_xlfn.SWITCH('00_ESTRATEGIA'!$B$4,'02_ESCENARIOS'!$B$2,'02_ESCENARIOS'!$B$9,'02_ESCENARIOS'!$C$2,'02_ESCENARIOS'!$C$9,'02_ESCENARIOS'!$D$2,'02_ESCENARIOS'!$D$9)} -> 0.04 | F63: % | H63: =A63 -> Comercialización | I63: {=_xlfn.SWITCH($I$3,$B$3,B63,$C$3,C63,$D$3,D63,$E$3,E63)} -> 0.03
A64: Ritmo absorción | B64: {=1.25*_xlfn.SWITCH('00_ESTRATEGIA'!$B$4,'02_ESCENARIOS'!$B$2,'02_ESCENARIOS'!$B$10,'02_ESCENARIOS'!$C$2,'02_ESCENARIOS'!$C$10,'02_ESCENARIOS'!$D$2,'02_ESCENARIOS'!$D$10)} -> 1.25 | C64: {=1.25*_xlfn.SWITCH('00_ESTRATEGIA'!$B$4,'02_ESCENARIOS'!$B$2,'02_ESCENARIOS'!$B$10,'02_ESCENARIOS'!$C$2,'02_ESCENARIOS'!$C$10,'02_ESCENARIOS'!$D$2,'02_ESCENARIOS'!$D$10)} -> 1.25 | D64: {=4*_xlfn.SWITCH('00_ESTRATEGIA'!$B$4,'02_ESCENARIOS'!$B$2,'02_ESCENARIOS'!$B$10,'02_ESCENARIOS'!$C$2,'02_ESCENARIOS'!$C$10,'02_ESCENARIOS'!$D$2,'02_ESCENARIOS'!$D$10)} -> 4 | E64: {=4*_xlfn.SWITCH('00_ESTRATEGIA'!$B$4,'02_ESCENARIOS'!$B$2,'02_ESCENARIOS'!$B$10,'02_ESCENARIOS'!$C$2,'02_ESCENARIOS'!$C$10,'02_ESCENARIOS'!$D$2,'02_ESCENARIOS'!$D$10)} -> 4 | F64: uds/mes | H64: =A64 -> Ritmo absorción | I64: {=_xlfn.SWITCH($I$3,$B$3,B64,$C$3,C64,$D$3,D64,$E$3,E64)} -> 1.25
A65: Duración comercialización | B65: 12 | C65: 12 | D65: 12 | E65: 12 | F65: meses | H65: =A65 -> Duración comercialización | I65: {=_xlfn.SWITCH($I$3,$B$3,B65,$C$3,C65,$D$3,D65,$E$3,E65)} -> 12
A66: Inicio ventas | B66: ='01_MODELO'!B37-B65 -> 23 | C66: ='01_MODELO'!C37-C65 -> 23 | D66: ='01_MODELO'!D37-D65 -> 24 | E66: ='01_MODELO'!E37-E65 -> 26 | F66: mes | H66: =A66 -> Inicio ventas | I66: {=_xlfn.SWITCH($I$3,$B$3,B66,$C$3,C66,$D$3,D66,$E$3,E66)} -> 23
A67: Duración estimada | B67: =B29/B64 -> 10.4 | C67: =C29/C64 -> 13.6 | D67: =D29/D64 -> 9.75 | E67: =E29/E64 -> 14.25 | F67: meses | H67: =A67 -> Duración estimada | I67: {=_xlfn.SWITCH($I$3,$B$3,B67,$C$3,C67,$D$3,D67,$E$3,E67)} -> 10.4
A68: ALQUILER | H68: =A68 -> ALQUILER
A69: Renta mensual estimada | B69: 1543 | C69: 1543 | D69: 1039 | E69: 1039 | F69: € | H69: =A69 -> Renta mensual estimada | I69: {=_xlfn.SWITCH($I$3,$B$3,B69,$C$3,C69,$D$3,D69,$E$3,E69)} -> 1543
A70: Precio corregido por perfil comprador | B70: 1.1 | C70: 1.05 | D70: 1 | E70: 1 | F70: - | H70: =A70 -> Precio corregido por perfil comprador | I70: {=_xlfn.SWITCH($I$3,$B$3,B70,$C$3,C70,$D$3,D70,$E$3,E70)} -> 1.1
A71: Ajuste por parcela | B71: =B58*B69/B50 -> 118.0496 | C71: =C58*C69/C50 -> 8.5569016 | D71: 0 | E71: 0 | F71: € | H71: =A71 -> Ajuste por parcela | I71: {=_xlfn.SWITCH($I$3,$B$3,B71,$C$3,C71,$D$3,D71,$E$3,E71)} -> 118.0496
A72: Renta mensual final | B72: =B69*B70+B71 -> 1815.3496 | C72: =C69*C70+C71 -> 1628.7069 | D72: =D69*D70+D71 -> 1039 | E72: =E69*E70+E71 -> 1039 | F72: € | H72: =A72 -> Renta mensual final | I72: {=_xlfn.SWITCH($I$3,$B$3,B72,$C$3,C72,$D$3,D72,$E$3,E72)} -> 1815.3496
A73: Ingreso bruto potencial | B73: =B72*B29*12 -> 283194.54 | C73: =C72*C29*12 -> 332256.21 | D73: =D72*D29*12 -> 486252 | E73: =E72*E29*12 -> 710676 | F73: € | H73: =A73 -> Ingreso bruto potencial | I73: {=_xlfn.SWITCH($I$3,$B$3,B73,$C$3,C73,$D$3,D73,$E$3,E73)} -> 283194.54
A74: Ocupación estabilizada | B74: {=93%+_xlfn.SWITCH('00_ESTRATEGIA'!$B$4,'02_ESCENARIOS'!$B$2,'02_ESCENARIOS'!$B$12,'02_ESCENARIOS'!$C$2,'02_ESCENARIOS'!$C$12,'02_ESCENARIOS'!$D$2,'02_ESCENARIOS'!$D$12)} -> 0.93 | C74: {=93%+_xlfn.SWITCH('00_ESTRATEGIA'!$B$4,'02_ESCENARIOS'!$B$2,'02_ESCENARIOS'!$B$12,'02_ESCENARIOS'!$C$2,'02_ESCENARIOS'!$C$12,'02_ESCENARIOS'!$D$2,'02_ESCENARIOS'!$D$12)} -> 0.93 | D74: {=93%+_xlfn.SWITCH('00_ESTRATEGIA'!$B$4,'02_ESCENARIOS'!$B$2,'02_ESCENARIOS'!$B$12,'02_ESCENARIOS'!$C$2,'02_ESCENARIOS'!$C$12,'02_ESCENARIOS'!$D$2,'02_ESCENARIOS'!$D$12)} -> 0.93 | E74: {=93%+_xlfn.SWITCH('00_ESTRATEGIA'!$B$4,'02_ESCENARIOS'!$B$2,'02_ESCENARIOS'!$B$12,'02_ESCENARIOS'!$C$2,'02_ESCENARIOS'!$C$12,'02_ESCENARIOS'!$D$2,'02_ESCENARIOS'!$D$12)} -> 0.93 | F74: % | H74: =A74 -> Ocupación estabilizada | I74: {=_xlfn.SWITCH($I$3,$B$3,B74,$C$3,C74,$D$3,D74,$E$3,E74)} -> 0.93
A75: Gastos explotación | B75: {=28%+_xlfn.SWITCH('00_ESTRATEGIA'!$B$4,'02_ESCENARIOS'!$B$2,'02_ESCENARIOS'!$B13,'02_ESCENARIOS'!$C$2,'02_ESCENARIOS'!$C13,'02_ESCENARIOS'!$D$2,'02_ESCENARIOS'!$D13)} -> 0.28 | C75: {=28%+_xlfn.SWITCH('00_ESTRATEGIA'!$B$4,'02_ESCENARIOS'!$B$2,'02_ESCENARIOS'!$B13,'02_ESCENARIOS'!$C$2,'02_ESCENARIOS'!$C13,'02_ESCENARIOS'!$D$2,'02_ESCENARIOS'!$D13)} -> 0.28 | D75: {=28%+_xlfn.SWITCH('00_ESTRATEGIA'!$B$4,'02_ESCENARIOS'!$B$2,'02_ESCENARIOS'!$B13,'02_ESCENARIOS'!$C$2,'02_ESCENARIOS'!$C13,'02_ESCENARIOS'!$D$2,'02_ESCENARIOS'!$D13)} -> 0.28 | E75: {=28%+_xlfn.SWITCH('00_ESTRATEGIA'!$B$4,'02_ESCENARIOS'!$B$2,'02_ESCENARIOS'!$B13,'02_ESCENARIOS'!$C$2,'02_ESCENARIOS'!$C13,'02_ESCENARIOS'!$D$2,'02_ESCENARIOS'!$D13)} -> 0.28 | F75: %/renta | H75: =A75 -> Gastos explotación | I75: {=_xlfn.SWITCH($I$3,$B$3,B75,$C$3,C75,$D$3,D75,$E$3,E75)} -> 0.28
A76: Yield mercado | B76: =6%+'02_ESCENARIOS'!$G15 -> 0.06 | C76: =6%+'02_ESCENARIOS'!$G15 -> 0.06 | D76: =6%+'02_ESCENARIOS'!$G15 -> 0.06 | E76: =6%+'02_ESCENARIOS'!$G15 -> 0.06 | F76: % | H76: =A76 -> Yield mercado | I76: {=_xlfn.SWITCH($I$3,$B$3,B76,$C$3,C76,$D$3,D76,$E$3,E76)} -> 0.06
A77: Crecimiento anual en rentas | B77: =1.5%+'02_ESCENARIOS'!$G16 -> 0.015 | C77: =B77 -> 0.015 | D77: =C77 -> 0.015 | E77: =D77 -> 0.015 | F77: % | H77: =A77 -> Crecimiento anual en rentas | I77: {=_xlfn.SWITCH($I$3,$B$3,B77,$C$3,C77,$D$3,D77,$E$3,E77)} -> 0.015
A78: Inicio ingresos | B78: ='01_MODELO'!B37 -> 35 | C78: ='01_MODELO'!C37 -> 35 | D78: ='01_MODELO'!D37 -> 36 | E78: ='01_MODELO'!E37 -> 38 | F78: mes | H78: =A78 -> Inicio ingresos | I78: {=_xlfn.SWITCH($I$3,$B$3,B78,$C$3,C78,$D$3,D78,$E$3,E78)} -> 35

Sheet 02_ESCENARIOS
A1: ESCENARIOS ECONÓMICO-FINANCIEROS
A2: Variable | B2: Conservador | C2: Base | D2: Optimista | F2: Selección | G2: ='00_ESTRATEGIA'!B4 -> Base
A3: Variables de construcción | F3: =A3 -> Variables de construcción
A4: GG + BI | B4: 0.01 | C4: 0 | D4: -0.01 | F4: =A4 -> GG + BI | G4: {=_xlfn.SWITCH($G$2,$B$2,B4,$C$2,C4,$D$2,D4)} -> 0
A5: Contingencia | B5: 0.02 | C5: 0 | D5: -0.02 | F5: =A5 -> Contingencia | G5: {=_xlfn.SWITCH($G$2,$B$2,B5,$C$2,C5,$D$2,D5)} -> 0
A6: Licencias y tasas | B6: 0.005 | C6: 0 | D6: -0.005 | F6: =A6 -> Licencias y tasas | G6: {=_xlfn.SWITCH($G$2,$B$2,B6,$C$2,C6,$D$2,D6)} -> 0
A7: Honorarios | B7: 0.01 | C7: 0 | D7: -0.01 | F7: =A7 -> Honorarios | G7: {=_xlfn.SWITCH($G$2,$B$2,B7,$C$2,C7,$D$2,D7)} -> 0
A8: Variables de venta | F8: =A8 -> Variables de venta
A9: Delta comercialización (pp) | B9: 0.005 | C9: 0 | D9: -0.005 | F9: =A9 -> Delta comercialización (pp) | G9: {=_xlfn.SWITCH($G$2,$B$2,B9,$C$2,C9,$D$2,D9)} -> 0
A10: Ritmo de absorción (multiplicador) | B10: 0.8 | C10: 1 | D10: 1.2 | F10: =A10 -> Ritmo de absorción (multiplicador) | G10: {=_xlfn.SWITCH($G$2,$B$2,B10,$C$2,C10,$D$2,D10)} -> 1
A11: Variables de alquiler | F11: =A11 -> Variables de alquiler
A12: Ocupación estabilizada | B12: -0.03 | C12: 0 | D12: 0.03 | F12: =A12 -> Ocupación estabilizada | G12: {=_xlfn.SWITCH($G$2,$B$2,B12,$C$2,C12,$D$2,D12)} -> 0
A13: Gastos explotación OPEX | B13: 0.04 | C13: 0 | D13: -0.04 | F13: =A13 -> Gastos explotación OPEX | G13: {=_xlfn.SWITCH($G$2,$B$2,B13,$C$2,C13,$D$2,D13)} -> 0
A14: Crecimiento anual rentas | B14: -0.005 | C14: 0 | D14: 0.005 | F14: =A14 -> Crecimiento anual rentas | G14: {=_xlfn.SWITCH($G$2,$B$2,B14,$C$2,C14,$D$2,D14)} -> 0
A15: Yield / cap rate salida | B15: 0.005 | C15: 0 | D15: -0.005 | F15: =A15 -> Yield / cap rate salida | G15: {=_xlfn.SWITCH($G$2,$B$2,B15,$C$2,C15,$D$2,D15)} -> 0
A16: Variables de temporales | F16: =A16 -> Variables de temporales
A17: Factor temporal (obra, licitaciones,diseño) | B17: 0.2 | C17: 0 | D17: -0.1 | F17: =A17 -> Factor temporal (obra, licitaciones,diseño) | G17: {=_xlfn.SWITCH($G$2,$B$2,B17,$C$2,C17,$D$2,D17)} -> 0
A19: SENSIBILIDAD FINANCIERA (independiente del escenario)
A20: Variable | B20: Adverso | C20: Base | D20: Favorable | F20: Seleccion | G20: ='00_ESTRATEGIA'!B8 -> Base
A21: Delta coste de la deuda (Euribor) | B21: 0.015 | C21: 0 | D21: -0.015 | F21: =A21 -> Delta coste de la deuda (Euribor) | G21: {=_xlfn.SWITCH($G$20,$B$20,B21,$C$20,C21,$D$20,D21)} -> 0

Sheet 10_CAPEX-INGRESOS-PAGOS
A1: CAPEX
A2: Variable | B2: Unifamiliar seg. | C2: Unifamiliar conj. | D2: Plurifamiliar U2C | E2: Plurifamiliar U4C | G2: Selección | H2: ='00_ESTRATEGIA'!B3 -> Unifamiliar seg.
A3: Número de viviendas | B3: ='01_MODELO'!B29 -> 13 | C3: ='01_MODELO'!C29 -> 17 | D3: ='01_MODELO'!D29 -> 39 | E3: ='01_MODELO'!E29 -> 57 | G3: =A3 -> Número de viviendas | H3: {=_xlfn.SWITCH($H$2,$B$2,B3,$C$2,C3,$D$2,D3,$E$2,E3)} -> 13
A4: Superficie por vivienda (m²) | B4: ='01_MODELO'!B26 -> 240 | C4: ='01_MODELO'!C26 -> 240 | D4: ='01_MODELO'!D26 -> 90 | E4: ='01_MODELO'!E26 -> 90 | G4: =A4 -> Superficie por vivienda (m²) | H4: {=_xlfn.SWITCH($H$2,$B$2,B4,$C$2,C4,$D$2,D4,$E$2,E4)} -> 240
A5: Superficie total (m²) | B5: =B3*B4 -> 3120 | C5: =C3*C4 -> 4080 | D5: ='01_MODELO'!D16 -> 4180.5 | E5: ='01_MODELO'!E16 -> 6038.5 | G5: =A5 -> Superficie total (m²) | H5: {=_xlfn.SWITCH($H$2,$B$2,B5,$C$2,C5,$D$2,D5,$E$2,E5)} -> 3120
A6: Cem unitario (€/m²) | B6: ='01_MODELO'!B39*'01_MODELO'!B40 -> 1481.76 | C6: ='01_MODELO'!C39*'01_MODELO'!C40 -> 1428.84 | D6: ='01_MODELO'!D39*'01_MODELO'!D40 -> 1217.16 | E6: ='01_MODELO'!E39*'01_MODELO'!E40 -> 1283.31 | G6: =A6 -> Cem unitario (€/m²) | H6: {=_xlfn.SWITCH($H$2,$B$2,B6,$C$2,C6,$D$2,D6,$E$2,E6)} -> 1481.76
A7: PEM Total (€) | B7: =B6*B5 -> 4623091.2 | C7: =C6*C5 -> 5829667.2 | D7: =D6*D5 -> 5088337.4 | E7: =E6*E5 -> 7749267.4 | G7: =A7 -> PEM Total (€) | H7: {=_xlfn.SWITCH($H$2,$B$2,B7,$C$2,C7,$D$2,D7,$E$2,E7)} -> 4623091.2
A8: GG+BI (€) | B8: =B$7*'01_MODELO'!B41 -> 924618.24 | C8: =C$7*'01_MODELO'!C41 -> 1165933.4 | D8: =D$7*'01_MODELO'!D41 -> 1017667.5 | E8: =E$7*'01_MODELO'!E41 -> 1549853.5 | G8: =A8 -> GG+BI (€) | H8: {=_xlfn.SWITCH($H$2,$B$2,B8,$C$2,C8,$D$2,D8,$E$2,E8)} -> 924618.24
A9: Licencias (€) | B9: =B$7*'01_MODELO'!B43 -> 208039.1 | C9: =C$7*'01_MODELO'!C43 -> 262335.02 | D9: =D$7*'01_MODELO'!D43 -> 228975.18 | E9: =E$7*'01_MODELO'!E43 -> 348717.03 | G9: =A9 -> Licencias (€) | H9: {=_xlfn.SWITCH($H$2,$B$2,B9,$C$2,C9,$D$2,D9,$E$2,E9)} -> 208039.1
A10: Contingencia (€) | B10: =B$7*'01_MODELO'!B42 -> 346731.84 | C10: =C$7*'01_MODELO'!C42 -> 408076.7 | D10: =D$7*'01_MODELO'!D42 -> 305300.24 | E10: =E$7*'01_MODELO'!E42 -> 464956.05 | G10: =A10 -> Contingencia (€) | H10: {=_xlfn.SWITCH($H$2,$B$2,B10,$C$2,C10,$D$2,D10,$E$2,E10)} -> 346731.84
A11: Honorarios (€) | B11: =B$7*'01_MODELO'!B44 -> 369847.3 | C11: =C$7*'01_MODELO'!C44 -> 466373.38 | D11: =D$7*'01_MODELO'!D44 -> 457950.36 | E11: =E$7*'01_MODELO'!E44 -> 697434.07 | G11: =A11 -> Honorarios (€) | H11: {=_xlfn.SWITCH($H$2,$B$2,B11,$C$2,C11,$D$2,D11,$E$2,E11)} -> 369847.3
A12: Coste total construcción (€) | B12: =SUM(B7:B11) -> 6472327.7 | C12: =SUM(C7:C11) -> 8132385.7 | D12: =SUM(D7:D11) -> 7098230.6 | E12: =SUM(E7:E11) -> 10810228 | G12: =A12 -> Coste total construcción (€) | H12: {=_xlfn.SWITCH($H$2,$B$2,B12,$C$2,C12,$D$2,D12,$E$2,E12)} -> 6472327.7
A13: Coste total (€/m²) | B13: =B12/B5 -> 2074.464 | C13: =C12/C5 -> 1993.2318 | D13: =D12/D5 -> 1697.9382 | E13: =E12/E5 -> 1790.2175 | G13: =A13 -> Coste total (€/m²) | H13: {=_xlfn.SWITCH($H$2,$B$2,B13,$C$2,C13,$D$2,D13,$E$2,E13)} -> 2074.464
A14: Coste total por vivienda (€) | B14: =B12/B3 -> 497871.36 | C14: =C12/C3 -> 478375.63 | D14: =D12/D3 -> 182005.91 | E14: =E12/E3 -> 189653.12 | G14: =A14 -> Coste total por vivienda (€) | H14: {=_xlfn.SWITCH($H$2,$B$2,B14,$C$2,C14,$D$2,D14,$E$2,E14)} -> 497871.36
A15: Precio suelo (€/m²) | B15: 127.4 | C15: 127.4 | D15: 127.4 | E15: 127.4 | G15: =A15 -> Precio suelo (€/m²) | H15: {=_xlfn.SWITCH($H$2,$B$2,B15,$C$2,C15,$D$2,D15,$E$2,E15)} -> 127.4
A16: Coste parcela total (€) | B16: ='01_MODELO'!$B$5*'10_CAPEX-INGRESOS-PAGOS'!B15 -> 1183546 | C16: ='01_MODELO'!$B$5*'10_CAPEX-INGRESOS-PAGOS'!C15 -> 1183546 | D16: ='01_MODELO'!$B$5*'10_CAPEX-INGRESOS-PAGOS'!D15 -> 1183546 | E16: ='01_MODELO'!$B$5*'10_CAPEX-INGRESOS-PAGOS'!E15 -> 1183546 | G16: =A16 -> Coste parcela total (€) | H16: {=_xlfn.SWITCH($H$2,$B$2,B16,$C$2,C16,$D$2,D16,$E$2,E16)} -> 1183546
A17: Coste suelo por vivienda (€) | B17: =B16/B3 -> 91042 | C17: =C16/C3 -> 69620.353 | D17: =D16/D3 -> 30347.333 | E17: =E16/E3 -> 20763.965 | G17: =A17 -> Coste suelo por vivienda (€) | H17: {=_xlfn.SWITCH($H$2,$B$2,B17,$C$2,C17,$D$2,D17,$E$2,E17)} -> 91042
A18: Coste total + suelo (€) | B18: =B12+B16 -> 7655873.7 | C18: =C12+C16 -> 9315931.7 | D18: =D12+D16 -> 8281776.6 | E18: =E12+E16 -> 11993774 | G18: =A18 -> Coste total + suelo (€) | H18: {=_xlfn.SWITCH($H$2,$B$2,B18,$C$2,C18,$D$2,D18,$E$2,E18)} -> 7655873.7
A19: Coste total + suelo por vivienda (€) | B19: =B18/B3 -> 588913.36 | C19: =C18/C3 -> 547995.98 | D19: =D18/D3 -> 212353.25 | E19: =E18/E3 -> 210417.09 | G19: =A19 -> Coste total + suelo por vivienda (€) | H19: {=_xlfn.SWITCH($H$2,$B$2,B19,$C$2,C19,$D$2,D19,$E$2,E19)} -> 588913.36
A20: Coste total + suelo (€/m²) | B20: =B18/B5 -> 2453.8057 | C20: =C18/C5 -> 2283.3166 | D20: =D18/D5 -> 1981.0493 | E20: =E18/E5 -> 1986.2175 | G20: =A20 -> Coste total + suelo (€/m²) | H20: {=_xlfn.SWITCH($H$2,$B$2,B20,$C$2,C20,$D$2,D20,$E$2,E20)} -> 2453.8057
A22: INGRESOS
A23: Variable | B23: Unifamiliar seg. | C23: Unifamiliar conj. | D23: Plurifamiliar U2C | E23: Plurifamiliar U4C | G23: Selección | H23: ='00_ESTRATEGIA'!B3 -> Unifamiliar seg.
A24: Número viviendas (N) | B24: ='01_MODELO'!B29 -> 13 | C24: ='01_MODELO'!C29 -> 17 | D24: ='01_MODELO'!D29 -> 39 | E24: ='01_MODELO'!E29 -> 57 | G24: =A24 -> Número viviendas (N) | H24: {=_xlfn.SWITCH($H$23,$B$23,B24,$C$23,C24,$D$23,D24,$E$23,E24)} -> 13
A25: VENTA | G25: =A25 -> VENTA
A26: Superficie media (m2) | B26: ='01_MODELO'!B26 -> 240 | C26: ='01_MODELO'!C26 -> 240 | D26: ='01_MODELO'!D26 -> 90 | E26: ='01_MODELO'!E26 -> 90 | G26: =A26 -> Superficie media (m2) | H26: {=_xlfn.SWITCH($H$23,$B$23,B26,$C$23,C26,$D$23,D26,$E$23,E26)} -> 240
A27: Precio medio por unidad (€) | B27: 715000 | C27: 640000 | D27: 315000 | E27: 315000 | G27: =A27 -> Precio medio por unidad (€) | H27: {=_xlfn.SWITCH($H$23,$B$23,B27,$C$23,C27,$D$23,D27,$E$23,E27)} -> 715000
A28: Ingresos brutos totales (€) | B28: =B24*B27 -> 9295000 | C28: =C24*C27 -> 10880000 | D28: =D24*D27 -> 12285000 | E28: =E24*E27 -> 17955000 | G28: =A28 -> Ingresos brutos totales (€) | H28: {=_xlfn.SWITCH($H$23,$B$23,B28,$C$23,C28,$D$23,D28,$E$23,E28)} -> 9295000
A29: Comercialización (%) | B29: ='01_MODELO'!B63 -> 0.03 | C29: ='01_MODELO'!C63 -> 0.03 | D29: ='01_MODELO'!D63 -> 0.04 | E29: ='01_MODELO'!E63 -> 0.04 | G29: =A29 -> Comercialización (%) | H29: {=_xlfn.SWITCH($H$23,$B$23,B29,$C$23,C29,$D$23,D29,$E$23,E29)} -> 0.03
A30: Coste comercialización (€) | B30: =B28*B29 -> 278850 | C30: =C28*C29 -> 326400 | D30: =D28*D29 -> 491400 | E30: =E28*E29 -> 718200 | G30: =A30 -> Coste comercialización (€) | H30: {=_xlfn.SWITCH($H$23,$B$23,B30,$C$23,C30,$D$23,D30,$E$23,E30)} -> 278850
A31: Ingresos netos promotor (€) | B31: =B28-B30 -> 9016150 | C31: =C28-C30 -> 10553600 | D31: =D28-D30 -> 11793600 | E31: =E28-E30 -> 17236800 | G31: =A31 -> Ingresos netos promotor (€) | H31: {=_xlfn.SWITCH($H$23,$B$23,B31,$C$23,C31,$D$23,D31,$E$23,E31)} -> 9016150
A32: Ventas anuales | B32: =MIN(B24,12*'01_MODELO'!B64) -> 13 | C32: =MIN(C24,12*'01_MODELO'!C64) -> 15 | D32: =MIN(D24,12*'01_MODELO'!D64) -> 39 | E32: =MIN(E24,12*'01_MODELO'!E64) -> 48 | G32: =A32 -> Ventas anuales | H32: {=_xlfn.SWITCH($H$23,$B$23,B32,$C$23,C32,$D$23,D32,$E$23,E32)} -> 13
A33: ALQUILER | G33: =A33 -> ALQUILER
A34: Renta mensual por unidad (€) | B34: ='01_MODELO'!B72 -> 1815.3496 | C34: ='01_MODELO'!C72 -> 1628.7069 | D34: ='01_MODELO'!D72 -> 1039 | E34: ='01_MODELO'!E72 -> 1039 | G34: =A34 -> Renta mensual por unidad (€) | H34: {=_xlfn.SWITCH($H$23,$B$23,B34,$C$23,C34,$D$23,D34,$E$23,E34)} -> 1815.3496
A35: Ingreso bruto anual (€) | B35: =B24*B34*12 -> 283194.54 | C35: =C24*C34*12 -> 332256.21 | D35: =D24*D34*12 -> 486252 | E35: =E24*E34*12 -> 710676 | G35: =A35 -> Ingreso bruto anual (€) | H35: {=_xlfn.SWITCH($H$23,$B$23,B35,$C$23,C35,$D$23,D35,$E$23,E35)} -> 283194.54
A36: Ocupación estabilizada (%) | B36: ='01_MODELO'!B74 -> 0.93 | C36: ='01_MODELO'!C74 -> 0.93 | D36: ='01_MODELO'!D74 -> 0.93 | E36: ='01_MODELO'!E74 -> 0.93 | G36: =A36 -> Ocupación estabilizada (%) | H36: {=_xlfn.SWITCH($H$23,$B$23,B36,$C$23,C36,$D$23,D36,$E$23,E36)} -> 0.93
A37: Ingreso efectivo (€) | B37: =B35*B36 -> 263370.92 | C37: =C35*C36 -> 308998.27 | D37: =D35*D36 -> 452214.36 | E37: =E35*E36 -> 660928.68 | G37: =A37 -> Ingreso efectivo (€) | H37: {=_xlfn.SWITCH($H$23,$B$23,B37,$C$23,C37,$D$23,D37,$E$23,E37)} -> 263370.92
A38: Gastos explotación (% renta) | B38: ='01_MODELO'!B75 -> 0.28 | C38: ='01_MODELO'!C75 -> 0.28 | D38: ='01_MODELO'!D75 -> 0.28 | E38: ='01_MODELO'!E75 -> 0.28 | G38: =A38 -> Gastos explotación (% renta) | H38: {=_xlfn.SWITCH($H$23,$B$23,B38,$C$23,C38,$D$23,D38,$E$23,E38)} -> 0.28
A39: NOI anual (€) | B39: =B37*(1-B38) -> 189627.06 | C39: =C37*(1-C38) -> 222478.76 | D39: =D37*(1-D38) -> 325594.34 | E39: =E37*(1-E38) -> 475868.65 | G39: =A39 -> NOI anual (€) | H39: {=_xlfn.SWITCH($H$23,$B$23,B39,$C$23,C39,$D$23,D39,$E$23,E39)} -> 189627.06
A40: Yield mercado (%) | B40: ='01_MODELO'!B76 -> 0.06 | C40: ='01_MODELO'!C76 -> 0.06 | D40: ='01_MODELO'!D76 -> 0.06 | E40: ='01_MODELO'!E76 -> 0.06 | G40: =A40 -> Yield mercado (%) | H40: {=_xlfn.SWITCH($H$23,$B$23,B40,$C$23,C40,$D$23,D40,$E$23,E40)} -> 0.06
A41: Valor capitalizado (€) | B41: =B39/B40 -> 3160451 | C41: =C39/C40 -> 3707979.3 | D41: =D39/D40 -> 5426572.3 | E41: =E39/E40 -> 7931144.2 | G41: =A41 -> Valor capitalizado (€) | H41: {=_xlfn.SWITCH($H$23,$B$23,B41,$C$23,C41,$D$23,D41,$E$23,E41)} -> 3160451
A43: PAGOS
A44: Tipología | B44: Unifamiliar Seg. | C44: Unifamiliar Conj. | D44: Plurifamiliar U2C | E44: Plurifamiliar U4C | G44: Selección | H44: ='00_ESTRATEGIA'!B3 -> Unifamiliar seg.
A45: % Reserva (mes t) | B45: 0.05 | C45: 0.05 | D45: 0.05 | E45: 0.05 | G45: =A45 -> % Reserva (mes t) | H45: {=_xlfn.SWITCH($H$23,$B$23,B45,$C$23,C45,$D$23,D45,$E$23,E45)} -> 0.05
A46: % Contrato (mes t+2) | B46: 0.1 | C46: 0.1 | D46: 0.1 | E46: 0.1 | G46: =A46 -> % Contrato (mes t+2) | H46: {=_xlfn.SWITCH($H$23,$B$23,B46,$C$23,C46,$D$23,D46,$E$23,E46)} -> 0.1
A47: % Aplazado lineal (t+2 → fin obra) | B47: 0.1 | C47: 0.1 | D47: 0.1 | E47: 0.1 | G47: =A47 -> % Aplazado lineal (t+2 → fin obra) | H47: {=_xlfn.SWITCH($H$23,$B$23,B47,$C$23,C47,$D$23,D47,$E$23,E47)} -> 0.1
A48: % Escritura (fin obra) | B48: 0.75 | C48: 0.75 | D48: 0.75 | E48: 0.75 | G48: =A48 -> % Escritura (fin obra) | H48: {=_xlfn.SWITCH($H$23,$B$23,B48,$C$23,C48,$D$23,D48,$E$23,E48)} -> 0.75
A49: Total | B49: =SUM(B45:B48) -> 1 | C49: =SUM(C45:C48) -> 1 | D49: =SUM(D45:D48) -> 1 | E49: =SUM(E45:E48) -> 1 | G49: =A49 -> Total | H49: {=_xlfn.SWITCH($H$23,$B$23,B49,$C$23,C49,$D$23,D49,$E$23,E49)} -> 1
A50: % Escritura post fin obra (sin lineal) | B50: =1-B45-B46 -> 0.85 | C50: =1-C45-C46 -> 0.85 | D50: =1-D45-D46 -> 0.85 | E50: =1-E45-E46 -> 0.85 | G50: =A50 -> % Escritura post fin obra (sin lineal) | H50: {=_xlfn.SWITCH($H$23,$B$23,B50,$C$23,C50,$D$23,D50,$E$23,E50)} -> 0.85

Sheet 20_FINANCIACION
A1: VARIABLES DE FINANCIACIÓN
A2: Variable | B2: Base | C2: Unidad | E2: Base sin sensibilidad
A3: PARÁMETROS COMUNES (build-up de Tipo de interés y Ke)
A4: Euríbor 12m de referencia | B4: =E4+'02_ESCENARIOS'!G21 -> 0.0275 | C4: % | E4: 0.0275
A5: Diferencial bancario | B5: 0.0275 | C5: %
A6: Tasa libre de riesgo (Bono España 10Y) | B6: 0.03114 | C6: %
A7: Equity Risk Premium España | B7: 0.058 | C7: %
A8: Prima de tamaño (small developer) | B8: 0.02 | C8: %
A9: Prima específica del proyecto | B9: =2%-0.41% -> 0.0159 | C9: %
A10: PARÁMETROS USADOS EN 32_CASHFLOW (levered)
A11: Loan to Cost (LTC) | B11: 0.65 | C11: % | E11: ='00_ESTRATEGIA'!B14 -> 1570326
A12: Tipo de interés nominal | B12: =B4+B5 -> 0.055 | C12: %
A13: Mes formalización préstamo | B13: ='01_MODELO'!I35 -> 11 | C13: mes
A14: Mes inicio amortización por ventas | B14: ='01_MODELO'!I37 -> 35 | C14: mes
A15: % de cada venta a cancelación | B15: 0.85 | C15: %
A16: Tipo IS aplicable | B16: 0.25 | C16: %
A17: Coste de capital propio (Ke) | B17: =B6+B7+B8+B9 -> 0.12504 | C17: %
A18: PARÁMETROS USADOS EN 33_CASHFLOW (partner)
A19: % partner sobre ejecución | B19: 0.5 | C19: %
A20: Hurdle rate (preferred return) anual | B20: 0.08 | C20: %
A21: Split sobre exceso — Promotor | B21: 0.7 | C21: %
A22: Split sobre exceso — Partner | B22: 0.3 | C22: %
A23: Mes de entrada del partner | B23: ='01_MODELO'!I35 -> 11 | C23: mes
A24: Comisión de apertura (% sobre nominal aprobado) | B24: 0.0075 | C24: %
A25: Comisión de no disponibilidad (% anual sobre saldo no dispuesto) | B25: 0.005 | C25: %

Sheet 30_CASHFLOW
A1: CASHFLOW MENSUAL
A2: Tipología: | B2: ='00_ESTRATEGIA'!B3 -> Unifamiliar seg. | D2: Escenario: | E2: ='00_ESTRATEGIA'!B4 -> Base
A3: Concepto / Mes | B3: 0 | C3: 1 | D3: 2 | E3: 3 | F3: 4 | G3: 5 | H3: 6 | I3: 7 | J3: 8 | K3: 9 | L3: 10 | M3: 11 | N3: 12 | O3: 13 | P3: 14 | Q3: 15 | R3: 16 | S3: 17 | T3: 18 | U3: 19 | V3: 20 | W3: 21 | X3: 22 | Y3: 23 | Z3: 24 | AA3: 25 | AB3: 26 | AC3: 27 | AD3: 28 | AE3: 29 | AF3: 30 | AG3: 31 | AH3: 32 | AI3: 33 | AJ3: 34 | AK3: 35 | AL3: 36 | AM3: 37 | AN3: 38 | AO3: 39 | AP3: 40 | AQ3: 41 | AR3: 42 | AS3: 43 | AT3: 44 | AU3: 45 | AV3: 46 | AW3: 47 | AX3: 48 | AY3: 49 | AZ3: 50 | BA3: 51 | BB3: 52 | BC3: 53 | BD3: 54 | BE3: 55 | BF3: 56 | BG3: 57 | BH3: 58 | BI3: 59 | BJ3: 60 | BK3: 61 | BL3: 62 | BM3: 63 | BN3: 64 | BO3: 65 | BP3: 66 | BQ3: 67 | BR3: 68 | BS3: 69 | BT3: 70 | BU3: 71 | BV3: 72 | BW3: 73 | BX3: 74 | BY3: 75 | BZ3: 76 | CA3: 77 | CB3: 78 | CC3: 79 | CD3: 80 | CE3: 81 | CF3: 82 | CG3: 83 | CH3: 84 | CI3: 85 | CJ3: 86 | CK3: 87 | CL3: 88 | CM3: 89 | CN3: 90 | CO3: 91 | CP3: 92 | CQ3: 93 | CR3: 94 | CS3: 95 | CT3: 96 | CU3: 97 | CV3: 98 | CW3: 99 | CX3: 100 | CY3: 101 | CZ3: 102 | DA3: 103 | DB3: 104 | DC3: 105 | DD3: 106 | DE3: 107 | DF3: 108 | DG3: 109 | DH3: 110 | DI3: 111 | DJ3: 112 | DK3: 113 | DL3: 114 | DM3: 115 | DN3: 116 | DO3: 117 | DP3: 118 | DQ3: 119 | DR3: 120 | DS3: 121 | DT3: 122 | DU3: 123 | DV3: 124 | DW3: 125 | DX3: 126 | DY3: 127 | DZ3: 128 | EA3: 129 | EB3: 130 | EC3: 131 | ED3: 132 | EE3: 133 | EF3: 134 | EG3: 135 | EH3: 136 | EI3: 137 | EJ3: 138 | EK3: 139 | EL3: 140 | EM3: 141 | EN3: 142 | EO3: 143 | EP3: 144 | EQ3: 145 | ER3: 146 | ES3: 147 | ET3: 148 | EU3: 149 | EV3: 150 | EW3: 151 | EX3: 152 | EY3: 153 | EZ3: 154 | FA3: 155 | FB3: 156 | FC3: 157 | FD3: 158 | FE3: 159 | FF3: 160 | FG3: 161 | FH3: 162 | FI3: 163 | FJ3: 164 | FK3: 165 | FL3: 166 | FM3: 167 | FN3: 168 | FO3: 169 | FP3: 170 | FQ3: 171 | FR3: 172 | FS3: 173 | FT3: 174 | FU3: 175 | FV3: 176 | FW3: 177 | FX3: 178 | FY3: 179 | FZ3: 180
A4: Año | B4: Y0 | C4: Y0 | D4: Y0 | E4: Y0 | F4: Y0 | G4: Y0 | H4: Y0 | I4: Y0 | J4: Y0 | K4: Y0 | L4: Y0 | M4: Y0 | N4: Y1 | O4: Y1 | P4: Y1 | Q4: Y1 | R4: Y1 | S4: Y1 | T4: Y1 | U4: Y1 | V4: Y1 | W4: Y1 | X4: Y1 | Y4: Y1 | Z4: Y2 | AA4: Y2 | AB4: Y2 | AC4: Y2 | AD4: Y2 | AE4: Y2 | AF4: Y2 | AG4: Y2 | AH4: Y2 | AI4: Y2 | AJ4: Y2 | AK4: Y2 | AL4: Y3 | AM4: Y3 | AN4: Y3 | AO4: Y3 | AP4: Y3 | AQ4: Y3 | AR4: Y3 | AS4: Y3 | AT4: Y3 | AU4: Y3 | AV4: Y3 | AW4: Y3 | AX4: Y4 | AY4: Y4 | AZ4: Y4 | BA4: Y4 | BB4: Y4 | BC4: Y4 | BD4: Y4 | BE4: Y4 | BF4: Y4 | BG4: Y4 | BH4: Y4 | BI4: Y4 | BJ4: Y5 | BK4: Y5 | BL4: Y5 | BM4: Y5 | BN4: Y5 | BO4: Y5 | BP4: Y5 | BQ4: Y5 | BR4: Y5 | BS4: Y5 | BT4: Y5 | BU4: Y5 | BV4: Y6 | BW4: Y6 | BX4: Y6 | BY4: Y6 | BZ4: Y6 | CA4: Y6 | CB4: Y6 | CC4: Y6 | CD4: Y6 | CE4: Y6 | CF4: Y6 | CG4: Y6 | CH4: Y7 | CI4: Y7 | CJ4: Y7 | CK4: Y7 | CL4: Y7 | CM4: Y7 | CN4: Y7 | CO4: Y7 | CP4: Y7 | CQ4: Y7 | CR4: Y7 | CS4: Y7 | CT4: Y8 | CU4: Y8 | CV4: Y8 | CW4: Y8 | CX4: Y8 | CY4: Y8 | CZ4: Y8 | DA4: Y8 | DB4: Y8 | DC4: Y8 | DD4: Y8 | DE4: Y8 | DF4: Y9 | DG4: Y9 | DH4: Y9 | DI4: Y9 | DJ4: Y9 | DK4: Y9 | DL4: Y9 | DM4: Y9 | DN4: Y9 | DO4: Y9 | DP4: Y9 | DQ4: Y9 | DR4: Y10 | DS4: Y10 | DT4: Y10 | DU4: Y10 | DV4: Y10 | DW4: Y10 | DX4: Y10 | DY4: Y10 | DZ4: Y10 | EA4: Y10 | EB4: Y10 | EC4: Y10 | ED4: Y11 | EE4: Y11 | EF4: Y11 | EG4: Y11 | EH4: Y11 | EI4: Y11 | EJ4: Y11 | EK4: Y11 | EL4: Y11 | EM4: Y11 | EN4: Y11 | EO4: Y11 | EP4: Y12 | EQ4: Y12 | ER4: Y12 | ES4: Y12 | ET4: Y12 | EU4: Y12 | EV4: Y12 | EW4: Y12 | EX4: Y12 | EY4: Y12 | EZ4: Y12 | FA4: Y12 | FB4: Y13 | FC4: Y13 | FD4: Y13 | FE4: Y13 | FF4: Y13 | FG4: Y13 | FH4: Y13 | FI4: Y13 | FJ4: Y13 | FK4: Y13 | FL4: Y13 | FM4: Y13 | FN4: Y14 | FO4: Y14 | FP4: Y14 | FQ4: Y14 | FR4: Y14 | FS4: Y14 | FT4: Y14 | FU4: Y14 | FV4: Y14 | FW4: Y14 | FX4: Y14 | FY4: Y14 | FZ4: Y15
A5: CAPEX | B5: M0 | C5: M1 | D5: M2 | E5: M3 | F5: M4 | G5: M5 | H5: M6 | I5: M7 | J5: M8 | K5: M9 | L5: M10 | M5: M11 | N5: M12 | O5: M13 | P5: M14 | Q5: M15 | R5: M16
A6: Suelo | B6: =IF(B$3=0,-'10_CAPEX-INGRESOS-PAGOS'!$H$16,0) -> -1183546 | C6: =IF(C$3=0,-'10_CAPEX-INGRESOS-PAGOS'!$H$16,0) -> 0 | D6: =IF(D$3=0,-'10_CAPEX-INGRESOS-PAGOS'!$H$16,0) -> 0 | E6: =IF(E$3=0,-'10_CAPEX-INGRESOS-PAGOS'!$H$16,0) -> 0 | F6: =IF(F$3=0,-'10_CAPEX-INGRESOS-PAGOS'!$H$16,0) -> 0 | G6: =IF(G$3=0,-'10_CAPEX-INGRESOS-PAGOS'!$H$16,0) -> 0 | H6: =IF(H$3=0,-'10_CAPEX-INGRESOS-PAGOS'!$H$16,0) -> 0 | I6: =IF(I$3=0,-'10_CAPEX-INGRESOS-PAGOS'!$H$16,0) -> 0 | ... FZ6: =IF(FZ$3=0,-'10_CAPEX-INGRESOS-PAGOS'!$H$16,0) -> 0
A7: Construcción | B7: =-'10_CAPEX-INGRESOS-PAGOS'!$H$12*MAX(0,MIN(B$3+1,'01_MODELO'!$I$37)-MAX(B$3,'01_MODELO'!$I$35))/('01_MODELO'!$I$37-'01_MODELO'!$I$35) -> 0 | C7: =-'10_CAPEX-INGRESOS-PAGOS'!$H$12*MAX(0,MIN(C$3+1,'01_MODELO'!$I$37)-MAX(C$3,'01_MODELO'!$I$35))/('01_MODELO'!$I$37-'01_MODELO'!$I$35) -> 0 | D7: =-'10_CAPEX-INGRESOS-PAGOS'!$H$12*MAX(0,MIN(D$3+1,'01_MODELO'!$I$37)-MAX(D$3,'01_MODELO'!$I$35))/('01_MODELO'!$I$37-'01_MODELO'!$I$35) -> 0 | E7: =-'10_CAPEX-INGRESOS-PAGOS'!$H$12*MAX(0,MIN(E$3+1,'01_MODELO'!$I$37)-MAX(E$3,'01_MODELO'!$I$35))/('01_MODELO'!$I$37-'01_MODELO'!$I$35) -> 0 | F7: =-'10_CAPEX-INGRESOS-PAGOS'!$H$12*MAX(0,MIN(F$3+1,'01_MODELO'!$I$37)-MAX(F$3,'01_MODELO'!$I$35))/('01_MODELO'!$I$37-'01_MODELO'!$I$35) -> 0 | G7: =-'10_CAPEX-INGRESOS-PAGOS'!$H$12*MAX(0,MIN(G$3+1,'01_MODELO'!$I$37)-MAX(G$3,'01_MODELO'!$I$35))/('01_MODELO'!$I$37-'01_MODELO'!$I$35) -> 0 | H7: =-'10_CAPEX-INGRESOS-PAGOS'!$H$12*MAX(0,MIN(H$3+1,'01_MODELO'!$I$37)-MAX(H$3,'01_MODELO'!$I$35))/('01_MODELO'!$I$37-'01_MODELO'!$I$35) -> 0 | I7: =-'10_CAPEX-INGRESOS-PAGOS'!$H$12*MAX(0,MIN(I$3+1,'01_MODELO'!$I$37)-MAX(I$3,'01_MODELO'!$I$35))/('01_MODELO'!$I$37-'01_MODELO'!$I$35) -> 0 | ... FZ7: =-'10_CAPEX-INGRESOS-PAGOS'!$H$12*MAX(0,MIN(FZ$3+1,'01_MODELO'!$I$37)-MAX(FZ$3,'01_MODELO'!$I$35))/('01_MODELO'!$I$37-'01_MODELO'!$I$35) -> 0
A8: CAPEX Total | B8: =SUM(B6,B7) -> -1183546 | C8: =SUM(C6,C7) -> 0 | D8: =SUM(D6,D7) -> 0 | E8: =SUM(E6,E7) -> 0 | F8: =SUM(F6,F7) -> 0 | G8: =SUM(G6,G7) -> 0 | H8: =SUM(H6,H7) -> 0 | I8: =SUM(I6,I7) -> 0 | ... FZ8: =SUM(FZ6,FZ7) -> 0
A9: Ingresos Venta
A10: Unidades vendidas | B10: =IF(B$3<'01_MODELO'!$I$66,0,MAX(0,MIN('01_MODELO'!$I$64,'10_CAPEX-INGRESOS-PAGOS'!$H$3-IF(COLUMN()=COLUMN($B$10),0,SUM($B$10:INDEX($10:$10,COLUMN()-1)))))) -> 0 | C10: =IF(C$3<'01_MODELO'!$I$66,0,MAX(0,MIN('01_MODELO'!$I$64,'10_CAPEX-INGRESOS-PAGOS'!$H$3-IF(COLUMN()=COLUMN($B$10),0,SUM($B$10:INDEX($10:$10,COLUMN()-1)))))) -> 0 | D10: =IF(D$3<'01_MODELO'!$I$66,0,MAX(0,MIN('01_MODELO'!$I$64,'10_CAPEX-INGRESOS-PAGOS'!$H$3-IF(COLUMN()=COLUMN($B$10),0,SUM($B$10:INDEX($10:$10,COLUMN()-1)))))) -> 0 | E10: =IF(E$3<'01_MODELO'!$I$66,0,MAX(0,MIN('01_MODELO'!$I$64,'10_CAPEX-INGRESOS-PAGOS'!$H$3-IF(COLUMN()=COLUMN($B$10),0,SUM($B$10:INDEX($10:$10,COLUMN()-1)))))) -> 0 | F10: =IF(F$3<'01_MODELO'!$I$66,0,MAX(0,MIN('01_MODELO'!$I$64,'10_CAPEX-INGRESOS-PAGOS'!$H$3-IF(COLUMN()=COLUMN($B$10),0,SUM($B$10:INDEX($10:$10,COLUMN()-1)))))) -> 0 | G10: =IF(G$3<'01_MODELO'!$I$66,0,MAX(0,MIN('01_MODELO'!$I$64,'10_CAPEX-INGRESOS-PAGOS'!$H$3-IF(COLUMN()=COLUMN($B$10),0,SUM($B$10:INDEX($10:$10,COLUMN()-1)))))) -> 0 | H10: =IF(H$3<'01_MODELO'!$I$66,0,MAX(0,MIN('01_MODELO'!$I$64,'10_CAPEX-INGRESOS-PAGOS'!$H$3-IF(COLUMN()=COLUMN($B$10),0,SUM($B$10:INDEX($10:$10,COLUMN()-1)))))) -> 0 | I10: =IF(I$3<'01_MODELO'!$I$66,0,MAX(0,MIN('01_MODELO'!$I$64,'10_CAPEX-INGRESOS-PAGOS'!$H$3-IF(COLUMN()=COLUMN($B$10),0,SUM($B$10:INDEX($10:$10,COLUMN()-1)))))) -> 0 | ... FZ10: =IF(FZ$3<'01_MODELO'!$I$66,0,MAX(0,MIN('01_MODELO'!$I$64,'10_CAPEX-INGRESOS-PAGOS'!$H$3-IF(COLUMN()=COLUMN($B$10),0,SUM($B$10:INDEX($10:$10,COLUMN()-1)))))) -> 0
A11: % ventas | B11: =B10/'10_CAPEX-INGRESOS-PAGOS'!$H$3 -> 0 | C11: =C10/'10_CAPEX-INGRESOS-PAGOS'!$H$3 -> 0 | D11: =D10/'10_CAPEX-INGRESOS-PAGOS'!$H$3 -> 0 | E11: =E10/'10_CAPEX-INGRESOS-PAGOS'!$H$3 -> 0 | F11: =F10/'10_CAPEX-INGRESOS-PAGOS'!$H$3 -> 0 | G11: =G10/'10_CAPEX-INGRESOS-PAGOS'!$H$3 -> 0 | H11: =H10/'10_CAPEX-INGRESOS-PAGOS'!$H$3 -> 0 | I11: =I10/'10_CAPEX-INGRESOS-PAGOS'!$H$3 -> 0 | ... FZ11: =FZ10/'10_CAPEX-INGRESOS-PAGOS'!$H$3 -> 0
A12: Cobro reserva | B12: =B$10*'10_CAPEX-INGRESOS-PAGOS'!$H$27*'10_CAPEX-INGRESOS-PAGOS'!$H$45 -> 0 | C12: =C$10*'10_CAPEX-INGRESOS-PAGOS'!$H$27*'10_CAPEX-INGRESOS-PAGOS'!$H$45 -> 0 | D12: =D$10*'10_CAPEX-INGRESOS-PAGOS'!$H$27*'10_CAPEX-INGRESOS-PAGOS'!$H$45 -> 0 | E12: =E$10*'10_CAPEX-INGRESOS-PAGOS'!$H$27*'10_CAPEX-INGRESOS-PAGOS'!$H$45 -> 0 | F12: =F$10*'10_CAPEX-INGRESOS-PAGOS'!$H$27*'10_CAPEX-INGRESOS-PAGOS'!$H$45 -> 0 | G12: =G$10*'10_CAPEX-INGRESOS-PAGOS'!$H$27*'10_CAPEX-INGRESOS-PAGOS'!$H$45 -> 0 | H12: =H$10*'10_CAPEX-INGRESOS-PAGOS'!$H$27*'10_CAPEX-INGRESOS-PAGOS'!$H$45 -> 0 | I12: =I$10*'10_CAPEX-INGRESOS-PAGOS'!$H$27*'10_CAPEX-INGRESOS-PAGOS'!$H$45 -> 0 | ... FZ12: =FZ$10*'10_CAPEX-INGRESOS-PAGOS'!$H$27*'10_CAPEX-INGRESOS-PAGOS'!$H$45 -> 0
A13: Cobro contrato | B13: =IF(B$3>=2,INDEX($B$10:$FZ$10,1,MATCH(B$3-2,$B$3:$FZ$3,0))*'10_CAPEX-INGRESOS-PAGOS'!$H$27*'10_CAPEX-INGRESOS-PAGOS'!$H$46,0) -> 0 | C13: =IF(C$3>=2,INDEX($B$10:$FZ$10,1,MATCH(C$3-2,$B$3:$FZ$3,0))*'10_CAPEX-INGRESOS-PAGOS'!$H$27*'10_CAPEX-INGRESOS-PAGOS'!$H$46,0) -> 0 | D13: =IF(D$3>=2,INDEX($B$10:$FZ$10,1,MATCH(D$3-2,$B$3:$FZ$3,0))*'10_CAPEX-INGRESOS-PAGOS'!$H$27*'10_CAPEX-INGRESOS-PAGOS'!$H$46,0) -> 0 | E13: =IF(E$3>=2,INDEX($B$10:$FZ$10,1,MATCH(E$3-2,$B$3:$FZ$3,0))*'10_CAPEX-INGRESOS-PAGOS'!$H$27*'10_CAPEX-INGRESOS-PAGOS'!$H$46,0) -> 0 | F13: =IF(F$3>=2,INDEX($B$10:$FZ$10,1,MATCH(F$3-2,$B$3:$FZ$3,0))*'10_CAPEX-INGRESOS-PAGOS'!$H$27*'10_CAPEX-INGRESOS-PAGOS'!$H$46,0) -> 0 | G13: =IF(G$3>=2,INDEX($B$10:$FZ$10,1,MATCH(G$3-2,$B$3:$FZ$3,0))*'10_CAPEX-INGRESOS-PAGOS'!$H$27*'10_CAPEX-INGRESOS-PAGOS'!$H$46,0) -> 0 | H13: =IF(H$3>=2,INDEX($B$10:$FZ$10,1,MATCH(H$3-2,$B$3:$FZ$3,0))*'10_CAPEX-INGRESOS-PAGOS'!$H$27*'10_CAPEX-INGRESOS-PAGOS'!$H$46,0) -> 0 | I13: =IF(I$3>=2,INDEX($B$10:$FZ$10,1,MATCH(I$3-2,$B$3:$FZ$3,0))*'10_CAPEX-INGRESOS-PAGOS'!$H$27*'10_CAPEX-INGRESOS-PAGOS'!$H$46,0) -> 0 | ... FZ13: =IF(FZ$3>=2,INDEX($B$10:$FZ$10,1,MATCH(FZ$3-2,$B$3:$FZ$3,0))*'10_CAPEX-INGRESOS-PAGOS'!$H$27*'10_CAPEX-INGRESOS-PAGOS'!$H$46,0) -> 0
A14: Cobro aplazado lineal | B14: =IF(AND(B$3>=ROUNDUP('01_MODELO'!$I$66+2,0),B$3<=ROUNDUP('01_MODELO'!$I$37,0)),(SUMPRODUCT($B$10:$FZ$10,--($B$3:$FZ$3<ROUNDUP('01_MODELO'!$I$37,0)))*'10_CAPEX-INGRESOS-PAGOS'!$H$27)*'10_CAPEX-INGRESOS-PAGOS'!$H$47/(ROUNDUP('01_MODELO'!$I$37,0)-ROUNDUP('01_MODELO'!$I$66+2,0)+1),0) -> 0 | C14: =IF(AND(C$3>=ROUNDUP('01_MODELO'!$I$66+2,0),C$3<=ROUNDUP('01_MODELO'!$I$37,0)),(SUMPRODUCT($B$10:$FZ$10,--($B$3:$FZ$3<ROUNDUP('01_MODELO'!$I$37,0)))*'10_CAPEX-INGRESOS-PAGOS'!$H$27)*'10_CAPEX-INGRESOS-PAGOS'!$H$47/(ROUNDUP('01_MODELO'!$I$37,0)-ROUNDUP('01_MODELO'!$I$66+2,0)+1),0) -> 0 | D14: =IF(AND(D$3>=ROUNDUP('01_MODELO'!$I$66+2,0),D$3<=ROUNDUP('01_MODELO'!$I$37,0)),(SUMPRODUCT($B$10:$FZ$10,--($B$3:$FZ$3<ROUNDUP('01_MODELO'!$I$37,0)))*'10_CAPEX-INGRESOS-PAGOS'!$H$27)*'10_CAPEX-INGRESOS-PAGOS'!$H$47/(ROUNDUP('01_MODELO'!$I$37,0)-ROUNDUP('01_MODELO'!$I$66+2,0)+1),0) -> 0 | E14: =IF(AND(E$3>=ROUNDUP('01_MODELO'!$I$66+2,0),E$3<=ROUNDUP('01_MODELO'!$I$37,0)),(SUMPRODUCT($B$10:$FZ$10,--($B$3:$FZ$3<ROUNDUP('01_MODELO'!$I$37,0)))*'10_CAPEX-INGRESOS-PAGOS'!$H$27)*'10_CAPEX-INGRESOS-PAGOS'!$H$47/(ROUNDUP('01_MODELO'!$I$37,0)-ROUNDUP('01_MODELO'!$I$66+2,0)+1),0) -> 0 | F14: =IF(AND(F$3>=ROUNDUP('01_MODELO'!$I$66+2,0),F$3<=ROUNDUP('01_MODELO'!$I$37,0)),(SUMPRODUCT($B$10:$FZ$10,--($B$3:$FZ$3<ROUNDUP('01_MODELO'!$I$37,0)))*'10_CAPEX-INGRESOS-PAGOS'!$H$27)*'10_CAPEX-INGRESOS-PAGOS'!$H$47/(ROUNDUP('01_MODELO'!$I$37,0)-ROUNDUP('01_MODELO'!$I$66+2,0)+1),0) -> 0 | G14: =IF(AND(G$3>=ROUNDUP('01_MODELO'!$I$66+2,0),G$3<=ROUNDUP('01_MODELO'!$I$37,0)),(SUMPRODUCT($B$10:$FZ$10,--($B$3:$FZ$3<ROUNDUP('01_MODELO'!$I$37,0)))*'10_CAPEX-INGRESOS-PAGOS'!$H$27)*'10_CAPEX-INGRESOS-PAGOS'!$H$47/(ROUNDUP('01_MODELO'!$I$37,0)-ROUNDUP('01_MODELO'!$I$66+2,0)+1),0) -> 0 | H14: =IF(AND(H$3>=ROUNDUP('01_MODELO'!$I$66+2,0),H$3<=ROUNDUP('01_MODELO'!$I$37,0)),(SUMPRODUCT($B$10:$FZ$10,--($B$3:$FZ$3<ROUNDUP('01_MODELO'!$I$37,0)))*'10_CAPEX-INGRESOS-PAGOS'!$H$27)*'10_CAPEX-INGRESOS-PAGOS'!$H$47/(ROUNDUP('01_MODELO'!$I$37,0)-ROUNDUP('01_MODELO'!$I$66+2,0)+1),0) -> 0 | I14: =IF(AND(I$3>=ROUNDUP('01_MODELO'!$I$66+2,0),I$3<=ROUNDUP('01_MODELO'!$I$37,0)),(SUMPRODUCT($B$10:$FZ$10,--($B$3:$FZ$3<ROUNDUP('01_MODELO'!$I$37,0)))*'10_CAPEX-INGRESOS-PAGOS'!$H$27)*'10_CAPEX-INGRESOS-PAGOS'!$H$47/(ROUNDUP('01_MODELO'!$I$37,0)-ROUNDUP('01_MODELO'!$I$66+2,0)+1),0) -> 0 | ... FZ14: =IF(AND(FZ$3>=ROUNDUP('01_MODELO'!$I$66+2,0),FZ$3<=ROUNDUP('01_MODELO'!$I$37,0)),(SUMPRODUCT($B$10:$FZ$10,--($B$3:$FZ$3<ROUNDUP('01_MODELO'!$I$37,0)))*'10_CAPEX-INGRESOS-PAGOS'!$H$27)*'10_CAPEX-INGRESOS-PAGOS'!$H$47/(ROUNDUP('01_MODELO'!$I$37,0)-ROUNDUP('01_MODELO'!$I$66+2,0)+1),0) -> 0
A15: Escritura fin de obra | B15: =IF(B$3=ROUNDUP('01_MODELO'!$I$37,0),(SUMPRODUCT($B$10:$FZ$10,--($B$3:$FZ$3<ROUNDUP('01_MODELO'!$I$37,0)))*'10_CAPEX-INGRESOS-PAGOS'!$H$27)*'10_CAPEX-INGRESOS-PAGOS'!$H$48,0) -> 0 | C15: =IF(C$3=ROUNDUP('01_MODELO'!$I$37,0),(SUMPRODUCT($B$10:$FZ$10,--($B$3:$FZ$3<ROUNDUP('01_MODELO'!$I$37,0)))*'10_CAPEX-INGRESOS-PAGOS'!$H$27)*'10_CAPEX-INGRESOS-PAGOS'!$H$48,0) -> 0 | D15: =IF(D$3=ROUNDUP('01_MODELO'!$I$37,0),(SUMPRODUCT($B$10:$FZ$10,--($B$3:$FZ$3<ROUNDUP('01_MODELO'!$I$37,0)))*'10_CAPEX-INGRESOS-PAGOS'!$H$27)*'10_CAPEX-INGRESOS-PAGOS'!$H$48,0) -> 0 | E15: =IF(E$3=ROUNDUP('01_MODELO'!$I$37,0),(SUMPRODUCT($B$10:$FZ$10,--($B$3:$FZ$3<ROUNDUP('01_MODELO'!$I$37,0)))*'10_CAPEX-INGRESOS-PAGOS'!$H$27)*'10_CAPEX-INGRESOS-PAGOS'!$H$48,0) -> 0 | F15: =IF(F$3=ROUNDUP('01_MODELO'!$I$37,0),(SUMPRODUCT($B$10:$FZ$10,--($B$3:$FZ$3<ROUNDUP('01_MODELO'!$I$37,0)))*'10_CAPEX-INGRESOS-PAGOS'!$H$27)*'10_CAPEX-INGRESOS-PAGOS'!$H$48,0) -> 0 | G15: =IF(G$3=ROUNDUP('01_MODELO'!$I$37,0),(SUMPRODUCT($B$10:$FZ$10,--($B$3:$FZ$3<ROUNDUP('01_MODELO'!$I$37,0)))*'10_CAPEX-INGRESOS-PAGOS'!$H$27)*'10_CAPEX-INGRESOS-PAGOS'!$H$48,0) -> 0 | H15: =IF(H$3=ROUNDUP('01_MODELO'!$I$37,0),(SUMPRODUCT($B$10:$FZ$10,--($B$3:$FZ$3<ROUNDUP('01_MODELO'!$I$37,0)))*'10_CAPEX-INGRESOS-PAGOS'!$H$27)*'10_CAPEX-INGRESOS-PAGOS'!$H$48,0) -> 0 | I15: =IF(I$3=ROUNDUP('01_MODELO'!$I$37,0),(SUMPRODUCT($B$10:$FZ$10,--($B$3:$FZ$3<ROUNDUP('01_MODELO'!$I$37,0)))*'10_CAPEX-INGRESOS-PAGOS'!$H$27)*'10_CAPEX-INGRESOS-PAGOS'!$H$48,0) -> 0 | ... FZ15: =IF(FZ$3=ROUNDUP('01_MODELO'!$I$37,0),(SUMPRODUCT($B$10:$FZ$10,--($B$3:$FZ$3<ROUNDUP('01_MODELO'!$I$37,0)))*'10_CAPEX-INGRESOS-PAGOS'!$H$27)*'10_CAPEX-INGRESOS-PAGOS'!$H$48,0) -> 0
A16: Escritura post fin de obra | B16: =SUMPRODUCT($B$10:$FZ$10*'10_CAPEX-INGRESOS-PAGOS'!$H$27*'10_CAPEX-INGRESOS-PAGOS'!$H$50*--($B$3:$FZ$3>=ROUNDUP('01_MODELO'!$I$37,0))*--($B$3:$FZ$3+2=B$3)) -> 0 | C16: =SUMPRODUCT($B$10:$FZ$10*'10_CAPEX-INGRESOS-PAGOS'!$H$27*'10_CAPEX-INGRESOS-PAGOS'!$H$50*--($B$3:$FZ$3>=ROUNDUP('01_MODELO'!$I$37,0))*--($B$3:$FZ$3+2=C$3)) -> 0 | D16: =SUMPRODUCT($B$10:$FZ$10*'10_CAPEX-INGRESOS-PAGOS'!$H$27*'10_CAPEX-INGRESOS-PAGOS'!$H$50*--($B$3:$FZ$3>=ROUNDUP('01_MODELO'!$I$37,0))*--($B$3:$FZ$3+2=D$3)) -> 0 | E16: =SUMPRODUCT($B$10:$FZ$10*'10_CAPEX-INGRESOS-PAGOS'!$H$27*'10_CAPEX-INGRESOS-PAGOS'!$H$50*--($B$3:$FZ$3>=ROUNDUP('01_MODELO'!$I$37,0))*--($B$3:$FZ$3+2=E$3)) -> 0 | F16: =SUMPRODUCT($B$10:$FZ$10*'10_CAPEX-INGRESOS-PAGOS'!$H$27*'10_CAPEX-INGRESOS-PAGOS'!$H$50*--($B$3:$FZ$3>=ROUNDUP('01_MODELO'!$I$37,0))*--($B$3:$FZ$3+2=F$3)) -> 0 | G16: =SUMPRODUCT($B$10:$FZ$10*'10_CAPEX-INGRESOS-PAGOS'!$H$27*'10_CAPEX-INGRESOS-PAGOS'!$H$50*--($B$3:$FZ$3>=ROUNDUP('01_MODELO'!$I$37,0))*--($B$3:$FZ$3+2=G$3)) -> 0 | H16: =SUMPRODUCT($B$10:$FZ$10*'10_CAPEX-INGRESOS-PAGOS'!$H$27*'10_CAPEX-INGRESOS-PAGOS'!$H$50*--($B$3:$FZ$3>=ROUNDUP('01_MODELO'!$I$37,0))*--($B$3:$FZ$3+2=H$3)) -> 0 | I16: =SUMPRODUCT($B$10:$FZ$10*'10_CAPEX-INGRESOS-PAGOS'!$H$27*'10_CAPEX-INGRESOS-PAGOS'!$H$50*--($B$3:$FZ$3>=ROUNDUP('01_MODELO'!$I$37,0))*--($B$3:$FZ$3+2=I$3)) -> 0 | ... FZ16: =SUMPRODUCT($B$10:$FZ$10*'10_CAPEX-INGRESOS-PAGOS'!$H$27*'10_CAPEX-INGRESOS-PAGOS'!$H$50*--($B$3:$FZ$3>=ROUNDUP('01_MODELO'!$I$37,0))*--($B$3:$FZ$3+2=FZ$3)) -> 0
A17: Total cobro ventas (bruto) | B17: =SUM(B$12:B$16) -> 0 | C17: =SUM(C$12:C$16) -> 0 | D17: =SUM(D$12:D$16) -> 0 | E17: =SUM(E$12:E$16) -> 0 | F17: =SUM(F$12:F$16) -> 0 | G17: =SUM(G$12:G$16) -> 0 | H17: =SUM(H$12:H$16) -> 0 | I17: =SUM(I$12:I$16) -> 0 | ... FZ17: =SUM(FZ$12:FZ$16) -> 0
A18: Coste comercialización | B18: =B$10*'10_CAPEX-INGRESOS-PAGOS'!$H$27*'10_CAPEX-INGRESOS-PAGOS'!$H$29 -> 0 | C18: =C$10*'10_CAPEX-INGRESOS-PAGOS'!$H$27*'10_CAPEX-INGRESOS-PAGOS'!$H$29 -> 0 | D18: =D$10*'10_CAPEX-INGRESOS-PAGOS'!$H$27*'10_CAPEX-INGRESOS-PAGOS'!$H$29 -> 0 | E18: =E$10*'10_CAPEX-INGRESOS-PAGOS'!$H$27*'10_CAPEX-INGRESOS-PAGOS'!$H$29 -> 0 | F18: =F$10*'10_CAPEX-INGRESOS-PAGOS'!$H$27*'10_CAPEX-INGRESOS-PAGOS'!$H$29 -> 0 | G18: =G$10*'10_CAPEX-INGRESOS-PAGOS'!$H$27*'10_CAPEX-INGRESOS-PAGOS'!$H$29 -> 0 | H18: =H$10*'10_CAPEX-INGRESOS-PAGOS'!$H$27*'10_CAPEX-INGRESOS-PAGOS'!$H$29 -> 0 | I18: =I$10*'10_CAPEX-INGRESOS-PAGOS'!$H$27*'10_CAPEX-INGRESOS-PAGOS'!$H$29 -> 0 | ... FZ18: =FZ$10*'10_CAPEX-INGRESOS-PAGOS'!$H$27*'10_CAPEX-INGRESOS-PAGOS'!$H$29 -> 0
A19: Ingresos netos venta | B19: =B$17-B$18 -> 0 | C19: =C$17-C$18 -> 0 | D19: =D$17-D$18 -> 0 | E19: =E$17-E$18 -> 0 | F19: =F$17-F$18 -> 0 | G19: =G$17-G$18 -> 0 | H19: =H$17-H$18 -> 0 | I19: =I$17-I$18 -> 0 | ... FZ19: =FZ$17-FZ$18 -> 0
A20: Flujo neto venta + CAPEX | B20: =B$8+B$19 -> -1183546 | C20: =C$8+C$19 -> 0 | D20: =D$8+D$19 -> 0 | E20: =E$8+E$19 -> 0 | F20: =F$8+F$19 -> 0 | G20: =G$8+G$19 -> 0 | H20: =H$8+H$19 -> 0 | I20: =I$8+I$19 -> 0 | ... FZ20: =FZ$8+FZ$19 -> 0
A21: Alquiler
A22: Ingresos alquiler | B22: =IF(B$3>='01_MODELO'!$I$78,IF(B$3<='00_ESTRATEGIA'!$B$5*12,'10_CAPEX-INGRESOS-PAGOS'!$H$35/12*(1+B$3/12*'01_MODELO'!$I$77),0),0) -> 0 | C22: =IF(C$3>='01_MODELO'!$I$78,IF(C$3<='00_ESTRATEGIA'!$B$5*12,'10_CAPEX-INGRESOS-PAGOS'!$H$35/12*(1+C$3/12*'01_MODELO'!$I$77),0),0) -> 0 | D22: =IF(D$3>='01_MODELO'!$I$78,IF(D$3<='00_ESTRATEGIA'!$B$5*12,'10_CAPEX-INGRESOS-PAGOS'!$H$35/12*(1+D$3/12*'01_MODELO'!$I$77),0),0) -> 0 | E22: =IF(E$3>='01_MODELO'!$I$78,IF(E$3<='00_ESTRATEGIA'!$B$5*12,'10_CAPEX-INGRESOS-PAGOS'!$H$35/12*(1+E$3/12*'01_MODELO'!$I$77),0),0) -> 0 | F22: =IF(F$3>='01_MODELO'!$I$78,IF(F$3<='00_ESTRATEGIA'!$B$5*12,'10_CAPEX-INGRESOS-PAGOS'!$H$35/12*(1+F$3/12*'01_MODELO'!$I$77),0),0) -> 0 | G22: =IF(G$3>='01_MODELO'!$I$78,IF(G$3<='00_ESTRATEGIA'!$B$5*12,'10_CAPEX-INGRESOS-PAGOS'!$H$35/12*(1+G$3/12*'01_MODELO'!$I$77),0),0) -> 0 | H22: =IF(H$3>='01_MODELO'!$I$78,IF(H$3<='00_ESTRATEGIA'!$B$5*12,'10_CAPEX-INGRESOS-PAGOS'!$H$35/12*(1+H$3/12*'01_MODELO'!$I$77),0),0) -> 0 | I22: =IF(I$3>='01_MODELO'!$I$78,IF(I$3<='00_ESTRATEGIA'!$B$5*12,'10_CAPEX-INGRESOS-PAGOS'!$H$35/12*(1+I$3/12*'01_MODELO'!$I$77),0),0) -> 0 | ... FZ22: =IF(FZ$3>='01_MODELO'!$I$78,IF(FZ$3<='00_ESTRATEGIA'!$B$5*12,'10_CAPEX-INGRESOS-PAGOS'!$H$35/12*(1+FZ$3/12*'01_MODELO'!$I$77),0),0) -> 28909.442
A23: OPEX | B23: =B$22*'01_MODELO'!$I$75 -> 0 | C23: =C$22*'01_MODELO'!$I$75 -> 0 | D23: =D$22*'01_MODELO'!$I$75 -> 0 | E23: =E$22*'01_MODELO'!$I$75 -> 0 | F23: =F$22*'01_MODELO'!$I$75 -> 0 | G23: =G$22*'01_MODELO'!$I$75 -> 0 | H23: =H$22*'01_MODELO'!$I$75 -> 0 | I23: =I$22*'01_MODELO'!$I$75 -> 0 | ... FZ23: =FZ$22*'01_MODELO'!$I$75 -> 8094.6439
A24: NOI | B24: =B$22-B$23 -> 0 | C24: =C$22-C$23 -> 0 | D24: =D$22-D$23 -> 0 | E24: =E$22-E$23 -> 0 | F24: =F$22-F$23 -> 0 | G24: =G$22-G$23 -> 0 | H24: =H$22-H$23 -> 0 | I24: =I$22-I$23 -> 0 | ... FZ24: =FZ$22-FZ$23 -> 20814.799
A25: Valor terminal | B25: =IF(B$3='00_ESTRATEGIA'!$B$5*12,(B$24*12*(1+'01_MODELO'!$I$77))/('01_MODELO'!$I$76-'01_MODELO'!$I$77),0) -> 0 | C25: =IF(C$3='00_ESTRATEGIA'!$B$5*12,(C$24*12*(1+'01_MODELO'!$I$77))/('01_MODELO'!$I$76-'01_MODELO'!$I$77),0) -> 0 | D25: =IF(D$3='00_ESTRATEGIA'!$B$5*12,(D$24*12*(1+'01_MODELO'!$I$77))/('01_MODELO'!$I$76-'01_MODELO'!$I$77),0) -> 0 | E25: =IF(E$3='00_ESTRATEGIA'!$B$5*12,(E$24*12*(1+'01_MODELO'!$I$77))/('01_MODELO'!$I$76-'01_MODELO'!$I$77),0) -> 0 | F25: =IF(F$3='00_ESTRATEGIA'!$B$5*12,(F$24*12*(1+'01_MODELO'!$I$77))/('01_MODELO'!$I$76-'01_MODELO'!$I$77),0) -> 0 | G25: =IF(G$3='00_ESTRATEGIA'!$B$5*12,(G$24*12*(1+'01_MODELO'!$I$77))/('01_MODELO'!$I$76-'01_MODELO'!$I$77),0) -> 0 | H25: =IF(H$3='00_ESTRATEGIA'!$B$5*12,(H$24*12*(1+'01_MODELO'!$I$77))/('01_MODELO'!$I$76-'01_MODELO'!$I$77),0) -> 0 | I25: =IF(I$3='00_ESTRATEGIA'!$B$5*12,(I$24*12*(1+'01_MODELO'!$I$77))/('01_MODELO'!$I$76-'01_MODELO'!$I$77),0) -> 0 | ... FZ25: =IF(FZ$3='00_ESTRATEGIA'!$B$5*12,(FZ$24*12*(1+'01_MODELO'!$I$77))/('01_MODELO'!$I$76-'01_MODELO'!$I$77),0) -> 5633872.1
A26: Flujo neto alquiler + CAPEX | B26: =B$8+B$24+B$25 -> -1183546 | C26: =C$8+C$24+C$25 -> 0 | D26: =D$8+D$24+D$25 -> 0 | E26: =E$8+E$24+E$25 -> 0 | F26: =F$8+F$24+F$25 -> 0 | G26: =G$8+G$24+G$25 -> 0 | H26: =H$8+H$24+H$25 -> 0 | I26: =I$8+I$24+I$25 -> 0 | ... FZ26: =FZ$8+FZ$24+FZ$25 -> 5654686.9
A27: Financiación
A28: Equity aportado | B28: =MAX(0,-(B20+B29+B37+B38)) -> 1183546 | C28: =MAX(0,-(C20+C29+C37+C38)) -> 0 | D28: =MAX(0,-(D20+D29+D37+D38)) -> 0 | E28: =MAX(0,-(E20+E29+E37+E38)) -> 0 | F28: =MAX(0,-(F20+F29+F37+F38)) -> 0 | G28: =MAX(0,-(G20+G29+G37+G38)) -> 0 | H28: =MAX(0,-(H20+H29+H37+H38)) -> 0 | I28: =MAX(0,-(I20+I29+I37+I38)) -> 0 | ... FZ28: =MAX(0,-(FZ20+FZ29+FZ37+FZ38)) -> 0
A29: Deuda dispuesta | B29: =IF(AND(B$3>='20_FINANCIACION'!$B$13,B$3<'20_FINANCIACION'!$B$14),MAX(0,MIN(-'30_CASHFLOW'!B7,'20_FINANCIACION'!$B$11*ABS(SUM('30_CASHFLOW'!$B$7:$FZ$7)) - 0)),0) -> 0 | C29: =IF(AND(C$3>='20_FINANCIACION'!$B$13,C$3<'20_FINANCIACION'!$B$14),MAX(0,MIN(-'30_CASHFLOW'!C7,'20_FINANCIACION'!$B$11*ABS(SUM('30_CASHFLOW'!$B$7:$FZ$7)) - SUM($B$29:B29))),0) -> 0 | D29: =IF(AND(D$3>='20_FINANCIACION'!$B$13,D$3<'20_FINANCIACION'!$B$14),MAX(0,MIN(-'30_CASHFLOW'!D7,'20_FINANCIACION'!$B$11*ABS(SUM('30_CASHFLOW'!$B$7:$FZ$7)) - SUM($B$29:C29))),0) -> 0 | E29: =IF(AND(E$3>='20_FINANCIACION'!$B$13,E$3<'20_FINANCIACION'!$B$14),MAX(0,MIN(-'30_CASHFLOW'!E7,'20_FINANCIACION'!$B$11*ABS(SUM('30_CASHFLOW'!$B$7:$FZ$7)) - SUM($B$29:D29))),0) -> 0 | F29: =IF(AND(F$3>='20_FINANCIACION'!$B$13,F$3<'20_FINANCIACION'!$B$14),MAX(0,MIN(-'30_CASHFLOW'!F7,'20_FINANCIACION'!$B$11*ABS(SUM('30_CASHFLOW'!$B$7:$FZ$7)) - SUM($B$29:E29))),0) -> 0 | G29: =IF(AND(G$3>='20_FINANCIACION'!$B$13,G$3<'20_FINANCIACION'!$B$14),MAX(0,MIN(-'30_CASHFLOW'!G7,'20_FINANCIACION'!$B$11*ABS(SUM('30_CASHFLOW'!$B$7:$FZ$7)) - SUM($B$29:F29))),0) -> 0 | H29: =IF(AND(H$3>='20_FINANCIACION'!$B$13,H$3<'20_FINANCIACION'!$B$14),MAX(0,MIN(-'30_CASHFLOW'!H7,'20_FINANCIACION'!$B$11*ABS(SUM('30_CASHFLOW'!$B$7:$FZ$7)) - SUM($B$29:G29))),0) -> 0 | I29: =IF(AND(I$3>='20_FINANCIACION'!$B$13,I$3<'20_FINANCIACION'!$B$14),MAX(0,MIN(-'30_CASHFLOW'!I7,'20_FINANCIACION'!$B$11*ABS(SUM('30_CASHFLOW'!$B$7:$FZ$7)) - SUM($B$29:H29))),0) -> 0 | J29: =IF(AND(J$3>='20_FINANCIACION'!$B$13,J$3<'20_FINANCIACION'!$B$14),MAX(0,MIN(-'30_CASHFLOW'!J7,'20_FINANCIACION'!$B$11*ABS(SUM('30_CASHFLOW'!$B$7:$FZ$7)) - SUM($B$29:I29))),0) -> 0 | ... FZ29: =IF(AND(FZ$3>='20_FINANCIACION'!$B$13,FZ$3<'20_FINANCIACION'!$B$14),MAX(0,MIN(-'30_CASHFLOW'!FZ7,'20_FINANCIACION'!$B$11*ABS(SUM('30_CASHFLOW'!$B$7:$FZ$7)) - SUM($B$29:FY29))),0) -> 0
A30: Total entradas financiación | B30: =B28+B29 -> 1183546 | C30: =C28+C29 -> 0 | D30: =D28+D29 -> 0 | E30: =E28+E29 -> 0 | F30: =F28+F29 -> 0 | G30: =G28+G29 -> 0 | H30: =H28+H29 -> 0 | I30: =I28+I29 -> 0 | ... FZ30: =FZ28+FZ29 -> 0
A31: Servicio de la deuda
A32: Intereses devengados | B32: =(B29/2)*'20_FINANCIACION'!$B$12/12 -> 0 | C32: =(B40+C29/2)*'20_FINANCIACION'!$B$12/12 -> 0 | D32: =(C40+D29/2)*'20_FINANCIACION'!$B$12/12 -> 0 | E32: =(D40+E29/2)*'20_FINANCIACION'!$B$12/12 -> 0 | F32: =(E40+F29/2)*'20_FINANCIACION'!$B$12/12 -> 0 | G32: =(F40+G29/2)*'20_FINANCIACION'!$B$12/12 -> 0 | H32: =(G40+H29/2)*'20_FINANCIACION'!$B$12/12 -> 0 | I32: =(H40+I29/2)*'20_FINANCIACION'!$B$12/12 -> 0 | J32: =(I40+J29/2)*'20_FINANCIACION'!$B$12/12 -> 0 | ... FZ32: =(FY40+FZ29/2)*'20_FINANCIACION'!$B$12/12 -> 0
A33: Intereses capitalizados (no cash) | B33: =IF(B$3<'20_FINANCIACION'!$B$14,B32,0) -> 0 | C33: =IF(C$3<'20_FINANCIACION'!$B$14,C32,0) -> 0 | D33: =IF(D$3<'20_FINANCIACION'!$B$14,D32,0) -> 0 | E33: =IF(E$3<'20_FINANCIACION'!$B$14,E32,0) -> 0 | F33: =IF(F$3<'20_FINANCIACION'!$B$14,F32,0) -> 0 | G33: =IF(G$3<'20_FINANCIACION'!$B$14,G32,0) -> 0 | H33: =IF(H$3<'20_FINANCIACION'!$B$14,H32,0) -> 0 | I33: =IF(I$3<'20_FINANCIACION'!$B$14,I32,0) -> 0 | ... FZ33: =IF(FZ$3<'20_FINANCIACION'!$B$14,FZ32,0) -> 0
A34: Intereses pagados (cash) | B34: =B32-B33 -> 0 | C34: =C32-C33 -> 0 | D34: =D32-D33 -> 0 | E34: =E32-E33 -> 0 | F34: =F32-F33 -> 0 | G34: =G32-G33 -> 0 | H34: =H32-H33 -> 0 | I34: =I32-I33 -> 0 | ... FZ34: =FZ32-FZ33 -> 0
A35: Amortización por ventas | B35: =IF(B$3>='20_FINANCIACION'!$B$14,MIN('20_FINANCIACION'!$B$15*MAX(0,'30_CASHFLOW'!B19),0+B29+B33),0) -> 0 | C35: =IF(C$3>='20_FINANCIACION'!$B$14,MIN('20_FINANCIACION'!$B$15*MAX(0,'30_CASHFLOW'!C19),B40+C29+C33),0) -> 0 | D35: =IF(D$3>='20_FINANCIACION'!$B$14,MIN('20_FINANCIACION'!$B$15*MAX(0,'30_CASHFLOW'!D19),C40+D29+D33),0) -> 0 | E35: =IF(E$3>='20_FINANCIACION'!$B$14,MIN('20_FINANCIACION'!$B$15*MAX(0,'30_CASHFLOW'!E19),D40+E29+E33),0) -> 0 | F35: =IF(F$3>='20_FINANCIACION'!$B$14,MIN('20_FINANCIACION'!$B$15*MAX(0,'30_CASHFLOW'!F19),E40+F29+F33),0) -> 0 | G35: =IF(G$3>='20_FINANCIACION'!$B$14,MIN('20_FINANCIACION'!$B$15*MAX(0,'30_CASHFLOW'!G19),F40+G29+G33),0) -> 0 | H35: =IF(H$3>='20_FINANCIACION'!$B$14,MIN('20_FINANCIACION'!$B$15*MAX(0,'30_CASHFLOW'!H19),G40+H29+H33),0) -> 0 | I35: =IF(I$3>='20_FINANCIACION'!$B$14,MIN('20_FINANCIACION'!$B$15*MAX(0,'30_CASHFLOW'!I19),H40+I29+I33),0) -> 0 | J35: =IF(J$3>='20_FINANCIACION'!$B$14,MIN('20_FINANCIACION'!$B$15*MAX(0,'30_CASHFLOW'!J19),I40+J29+J33),0) -> 0 | ... FZ35: =IF(FZ$3>='20_FINANCIACION'!$B$14,MIN('20_FINANCIACION'!$B$15*MAX(0,'30_CASHFLOW'!FZ19),FY40+FZ29+FZ33),0) -> 0
A36: Comisiones (apertura + no disponibilidad) | B36: =-IF(B$3='20_FINANCIACION'!$B$13,'20_FINANCIACION'!$B$24*'20_FINANCIACION'!$B$11*ABS(SUM('30_CASHFLOW'!$B$7:$FZ$7)),0)-IF(AND(B$3>='20_FINANCIACION'!$B$13,B$3<'20_FINANCIACION'!$B$14),'20_FINANCIACION'!$B$25/12*MAX(0,'20_FINANCIACION'!$B$11*ABS(SUM('30_CASHFLOW'!$B$7:$FZ$7))-0),0) -> 0 | C36: =-IF(C$3='20_FINANCIACION'!$B$13,'20_FINANCIACION'!$B$24*'20_FINANCIACION'!$B$11*ABS(SUM('30_CASHFLOW'!$B$7:$FZ$7)),0)-IF(AND(C$3>='20_FINANCIACION'!$B$13,C$3<'20_FINANCIACION'!$B$14),'20_FINANCIACION'!$B$25/12*MAX(0,'20_FINANCIACION'!$B$11*ABS(SUM('30_CASHFLOW'!$B$7:$FZ$7))-SUM($B$29:B29)),0) -> 0 | D36: =-IF(D$3='20_FINANCIACION'!$B$13,'20_FINANCIACION'!$B$24*'20_FINANCIACION'!$B$11*ABS(SUM('30_CASHFLOW'!$B$7:$FZ$7)),0)-IF(AND(D$3>='20_FINANCIACION'!$B$13,D$3<'20_FINANCIACION'!$B$14),'20_FINANCIACION'!$B$25/12*MAX(0,'20_FINANCIACION'!$B$11*ABS(SUM('30_CASHFLOW'!$B$7:$FZ$7))-SUM($B$29:C29)),0) -> 0 | E36: =-IF(E$3='20_FINANCIACION'!$B$13,'20_FINANCIACION'!$B$24*'20_FINANCIACION'!$B$11*ABS(SUM('30_CASHFLOW'!$B$7:$FZ$7)),0)-IF(AND(E$3>='20_FINANCIACION'!$B$13,E$3<'20_FINANCIACION'!$B$14),'20_FINANCIACION'!$B$25/12*MAX(0,'20_FINANCIACION'!$B$11*ABS(SUM('30_CASHFLOW'!$B$7:$FZ$7))-SUM($B$29:D29)),0) -> 0 | F36: =-IF(F$3='20_FINANCIACION'!$B$13,'20_FINANCIACION'!$B$24*'20_FINANCIACION'!$B$11*ABS(SUM('30_CASHFLOW'!$B$7:$FZ$7)),0)-IF(AND(F$3>='20_FINANCIACION'!$B$13,F$3<'20_FINANCIACION'!$B$14),'20_FINANCIACION'!$B$25/12*MAX(0,'20_FINANCIACION'!$B$11*ABS(SUM('30_CASHFLOW'!$B$7:$FZ$7))-SUM($B$29:E29)),0) -> 0 | G36: =-IF(G$3='20_FINANCIACION'!$B$13,'20_FINANCIACION'!$B$24*'20_FINANCIACION'!$B$11*ABS(SUM('30_CASHFLOW'!$B$7:$FZ$7)),0)-IF(AND(G$3>='20_FINANCIACION'!$B$13,G$3<'20_FINANCIACION'!$B$14),'20_FINANCIACION'!$B$25/12*MAX(0,'20_FINANCIACION'!$B$11*ABS(SUM('30_CASHFLOW'!$B$7:$FZ$7))-SUM($B$29:F29)),0) -> 0 | H36: =-IF(H$3='20_FINANCIACION'!$B$13,'20_FINANCIACION'!$B$24*'20_FINANCIACION'!$B$11*ABS(SUM('30_CASHFLOW'!$B$7:$FZ$7)),0)-IF(AND(H$3>='20_FINANCIACION'!$B$13,H$3<'20_FINANCIACION'!$B$14),'20_FINANCIACION'!$B$25/12*MAX(0,'20_FINANCIACION'!$B$11*ABS(SUM('30_CASHFLOW'!$B$7:$FZ$7))-SUM($B$29:G29)),0) -> 0 | I36: =-IF(I$3='20_FINANCIACION'!$B$13,'20_FINANCIACION'!$B$24*'20_FINANCIACION'!$B$11*ABS(SUM('30_CASHFLOW'!$B$7:$FZ$7)),0)-IF(AND(I$3>='20_FINANCIACION'!$B$13,I$3<'20_FINANCIACION'!$B$14),'20_FINANCIACION'!$B$25/12*MAX(0,'20_FINANCIACION'!$B$11*ABS(SUM('30_CASHFLOW'!$B$7:$FZ$7))-SUM($B$29:H29)),0) -> 0 | J36: =-IF(J$3='20_FINANCIACION'!$B$13,'20_FINANCIACION'!$B$24*'20_FINANCIACION'!$B$11*ABS(SUM('30_CASHFLOW'!$B$7:$FZ$7)),0)-IF(AND(J$3>='20_FINANCIACION'!$B$13,J$3<'20_FINANCIACION'!$B$14),'20_FINANCIACION'!$B$25/12*MAX(0,'20_FINANCIACION'!$B$11*ABS(SUM('30_CASHFLOW'!$B$7:$FZ$7))-SUM($B$29:I29)),0) -> 0 | ... FZ36: =-IF(FZ$3='20_FINANCIACION'!$B$13,'20_FINANCIACION'!$B$24*'20_FINANCIACION'!$B$11*ABS(SUM('30_CASHFLOW'!$B$7:$FZ$7)),0)-IF(AND(FZ$3>='20_FINANCIACION'!$B$13,FZ$3<'20_FINANCIACION'!$B$14),'20_FINANCIACION'!$B$25/12*MAX(0,'20_FINANCIACION'!$B$11*ABS(SUM('30_CASHFLOW'!$B$7:$FZ$7))-SUM($B$29:FY29)),0) -> 0
A37: Servicio total de la deuda (cash) | B37: =-B34-B35+B36 -> 0 | C37: =-C34-C35+C36 -> 0 | D37: =-D34-D35+D36 -> 0 | E37: =-E34-E35+E36 -> 0 | F37: =-F34-F35+F36 -> 0 | G37: =-G34-G35+G36 -> 0 | H37: =-H34-H35+H36 -> 0 | I37: =-I34-I35+I36 -> 0 | ... FZ37: =-FZ34-FZ35+FZ36 -> 0
A38: IS pagado (cash) | B38: =-IF(B$3=ROUNDUP('01_MODELO'!$I$37,0), MAX(0, (SUM('30_CASHFLOW'!$19:$19) + SUM('30_CASHFLOW'!$8:$8) - SUM($32:$32))) * '20_FINANCIACION'!$B$16, 0) -> 0 | C38: =-IF(C$3=ROUNDUP('01_MODELO'!$I$37,0), MAX(0, (SUM('30_CASHFLOW'!$19:$19) + SUM('30_CASHFLOW'!$8:$8) - SUM($32:$32))) * '20_FINANCIACION'!$B$16, 0) -> 0 | D38: =-IF(D$3=ROUNDUP('01_MODELO'!$I$37,0), MAX(0, (SUM('30_CASHFLOW'!$19:$19) + SUM('30_CASHFLOW'!$8:$8) - SUM($32:$32))) * '20_FINANCIACION'!$B$16, 0) -> 0 | E38: =-IF(E$3=ROUNDUP('01_MODELO'!$I$37,0), MAX(0, (SUM('30_CASHFLOW'!$19:$19) + SUM('30_CASHFLOW'!$8:$8) - SUM($32:$32))) * '20_FINANCIACION'!$B$16, 0) -> 0 | F38: =-IF(F$3=ROUNDUP('01_MODELO'!$I$37,0), MAX(0, (SUM('30_CASHFLOW'!$19:$19) + SUM('30_CASHFLOW'!$8:$8) - SUM($32:$32))) * '20_FINANCIACION'!$B$16, 0) -> 0 | G38: =-IF(G$3=ROUNDUP('01_MODELO'!$I$37,0), MAX(0, (SUM('30_CASHFLOW'!$19:$19) + SUM('30_CASHFLOW'!$8:$8) - SUM($32:$32))) * '20_FINANCIACION'!$B$16, 0) -> 0 | H38: =-IF(H$3=ROUNDUP('01_MODELO'!$I$37,0), MAX(0, (SUM('30_CASHFLOW'!$19:$19) + SUM('30_CASHFLOW'!$8:$8) - SUM($32:$32))) * '20_FINANCIACION'!$B$16, 0) -> 0 | I38: =-IF(I$3=ROUNDUP('01_MODELO'!$I$37,0), MAX(0, (SUM('30_CASHFLOW'!$19:$19) + SUM('30_CASHFLOW'!$8:$8) - SUM($32:$32))) * '20_FINANCIACION'!$B$16, 0) -> 0 | ... FZ38: =-IF(FZ$3=ROUNDUP('01_MODELO'!$I$37,0), MAX(0, (SUM('30_CASHFLOW'!$19:$19) + SUM('30_CASHFLOW'!$8:$8) - SUM($32:$32))) * '20_FINANCIACION'!$B$16, 0) -> 0
A39: Cashflow del accionista | B39: =B20+B29+B37+B38 -> -1183546 | C39: =C20+C29+C37+C38 -> 0 | D39: =D20+D29+D37+D38 -> 0 | E39: =E20+E29+E37+E38 -> 0 | F39: =F20+F29+F37+F38 -> 0 | G39: =G20+G29+G37+G38 -> 0 | H39: =H20+H29+H37+H38 -> 0 | I39: =I20+I29+I37+I38 -> 0 | ... FZ39: =FZ20+FZ29+FZ37+FZ38 -> 0
A40: Saldo vivo del préstamo (memoria) | B40: =B29+B33-B35 -> 0 | C40: =B40+C29+C33-C35 -> 0 | D40: =C40+D29+D33-D35 -> 0 | E40: =D40+E29+E33-E35 -> 0 | F40: =E40+F29+F33-F35 -> 0 | G40: =F40+G29+G33-G35 -> 0 | H40: =G40+H29+H33-H35 -> 0 | I40: =H40+I29+I33-I35 -> 0 | J40: =I40+J29+J33-J35 -> 0 | ... FZ40: =FY40+FZ29+FZ33-FZ35 -> 0
A41: FCF accionista acumulado (memoria) | B41: =B39 -> -1183546 | C41: =B41+C39 -> -1183546 | D41: =C41+D39 -> -1183546 | E41: =D41+E39 -> -1183546 | F41: =E41+F39 -> -1183546 | G41: =F41+G39 -> -1183546 | H41: =G41+H39 -> -1183546 | I41: =H41+I39 -> -1183546 | J41: =I41+J39 -> -1183546 | ... FZ41: =FY41+FZ39 -> 715285.95
A43: INDICADORES
A44: Sin financiación | B44: Venta | C44: Alquiler
A45: TIR (anualizada) | B45: =IFERROR((1+IRR(B20:FZ20,0.05))^12-1,IFERROR((1+IRR(B20:FZ20,-0.5))^12-1,IFERROR((1+IRR(B20:FZ20,-0.9))^12-1,IFERROR((1+MIRR(B20:FZ20,B47/12,B47/12))^12-1,0)))) -> 0.1367759 | C45: =IFERROR((1+IRR(B26:FZ26,0.05))^12-1,IFERROR((1+IRR(B26:FZ26,-0.5))^12-1,IFERROR((1+IRR(B26:FZ26,-0.9))^12-1,IFERROR((1+MIRR(B26:FZ26,C47/12,C47/12))^12-1,0)))) -> 0.0086677881
A46: VAN | B46: =NPV((1+B47)^(1/12)-1,C20:FZ20)+B20 -> 468930.73 | C46: =NPV((1+C47)^(1/12)-1,C26:FZ26)+B26 -> -2949614.9
A47: Tasa de descuento (anual) | B47: ='00_ESTRATEGIA'!E5 -> 0.08 | C47: ='00_ESTRATEGIA'!F5 -> 0.06
A48: Indicadores con financiación | B48: Valor
A49: TIR equity (anualizada) | B49: =IFERROR((1+IRR(B39:BI39,0.05))^12-1,IFERROR((1+IRR(B39:BI39,-0.3))^12-1,IFERROR((1+IRR(B39:BI39,-0.7))^12-1,IFERROR((1+IRR(B39:BI39,-0.95))^12-1,0)))) -> 0.17348834
A50: VAN equity @ Ke | B50: =NPV((1+'20_FINANCIACION'!$B$17)^(1/12)-1,C39:BI39)+B39 -> 157181.39
A51: Capital propio máximo desembolsado | B51: =-MIN(B41:BI41) -> 1570326
A52: Equity multiple (MOIC) | B52: =IFERROR((SUMIF(B39:BI39,">0")) / -SUMIF(B39:BI39,"<0"),0) -> 1.3803175

Sheet 31_P&L
A1: CUENTA DE RESULTADOS MENSUAL
A2: Tipología: | B2: ='00_ESTRATEGIA'!B3 -> Unifamiliar seg. | D2: Escenario: | E2: ='00_ESTRATEGIA'!B4 -> Base
A3: Mes | B3: 0 | C3: 1 | D3: 2 | E3: 3 | F3: 4 | G3: 5 | H3: 6 | I3: 7 | J3: 8 | K3: 9 | L3: 10 | M3: 11 | N3: 12 | O3: 13 | P3: 14 | Q3: 15 | R3: 16 | S3: 17 | T3: 18 | U3: 19 | V3: 20 | W3: 21 | X3: 22 | Y3: 23 | Z3: 24 | AA3: 25 | AB3: 26 | AC3: 27 | AD3: 28 | AE3: 29 | AF3: 30 | AG3: 31 | AH3: 32 | AI3: 33 | AJ3: 34 | AK3: 35 | AL3: 36 | AM3: 37 | AN3: 38 | AO3: 39 | AP3: 40 | AQ3: 41 | AR3: 42 | AS3: 43 | AT3: 44 | AU3: 45 | AV3: 46 | AW3: 47 | AX3: 48 | AY3: 49 | AZ3: 50 | BA3: 51 | BB3: 52 | BC3: 53 | BD3: 54 | BE3: 55 | BF3: 56 | BG3: 57 | BH3: 58 | BI3: 59
A4: Año | B4: Y0 | C4: Y0 | D4: Y0 | E4: Y0 | F4: Y0 | G4: Y0 | H4: Y0 | I4: Y0 | J4: Y0 | K4: Y0 | L4: Y0 | M4: Y0 | N4: Y1 | O4: Y1 | P4: Y1 | Q4: Y1 | R4: Y1 | S4: Y1 | T4: Y1 | U4: Y1 | V4: Y1 | W4: Y1 | X4: Y1 | Y4: Y1 | Z4: Y2 | AA4: Y2 | AB4: Y2 | AC4: Y2 | AD4: Y2 | AE4: Y2 | AF4: Y2 | AG4: Y2 | AH4: Y2 | AI4: Y2 | AJ4: Y2 | AK4: Y2 | AL4: Y3 | AM4: Y3 | AN4: Y3 | AO4: Y3 | AP4: Y3 | AQ4: Y3 | AR4: Y3 | AS4: Y3 | AT4: Y3 | AU4: Y3 | AV4: Y3 | AW4: Y3 | AX4: Y4 | AY4: Y4 | AZ4: Y4 | BA4: Y4 | BB4: Y4 | BC4: Y4 | BD4: Y4 | BE4: Y4 | BF4: Y4 | BG4: Y4 | BH4: Y4 | BI4: Y4
A5: INGRESOS
A6: Ingresos reconocidos por escritura / entrega | B6: =IFERROR('30_CASHFLOW'!B15/'10_CAPEX-INGRESOS-PAGOS'!$H$48,0)+IFERROR('30_CASHFLOW'!B16/'10_CAPEX-INGRESOS-PAGOS'!$H$50,0) -> 0 | C6: =IFERROR('30_CASHFLOW'!C15/'10_CAPEX-INGRESOS-PAGOS'!$H$48,0)+IFERROR('30_CASHFLOW'!C16/'10_CAPEX-INGRESOS-PAGOS'!$H$50,0) -> 0 | D6: =IFERROR('30_CASHFLOW'!D15/'10_CAPEX-INGRESOS-PAGOS'!$H$48,0)+IFERROR('30_CASHFLOW'!D16/'10_CAPEX-INGRESOS-PAGOS'!$H$50,0) -> 0 | E6: =IFERROR('30_CASHFLOW'!E15/'10_CAPEX-INGRESOS-PAGOS'!$H$48,0)+IFERROR('30_CASHFLOW'!E16/'10_CAPEX-INGRESOS-PAGOS'!$H$50,0) -> 0 | F6: =IFERROR('30_CASHFLOW'!F15/'10_CAPEX-INGRESOS-PAGOS'!$H$48,0)+IFERROR('30_CASHFLOW'!F16/'10_CAPEX-INGRESOS-PAGOS'!$H$50,0) -> 0 | G6: =IFERROR('30_CASHFLOW'!G15/'10_CAPEX-INGRESOS-PAGOS'!$H$48,0)+IFERROR('30_CASHFLOW'!G16/'10_CAPEX-INGRESOS-PAGOS'!$H$50,0) -> 0 | H6: =IFERROR('30_CASHFLOW'!H15/'10_CAPEX-INGRESOS-PAGOS'!$H$48,0)+IFERROR('30_CASHFLOW'!H16/'10_CAPEX-INGRESOS-PAGOS'!$H$50,0) -> 0 | I6: =IFERROR('30_CASHFLOW'!I15/'10_CAPEX-INGRESOS-PAGOS'!$H$48,0)+IFERROR('30_CASHFLOW'!I16/'10_CAPEX-INGRESOS-PAGOS'!$H$50,0) -> 0 | ... BI6: =IFERROR('30_CASHFLOW'!BI15/'10_CAPEX-INGRESOS-PAGOS'!$H$48,0)+IFERROR('30_CASHFLOW'!BI16/'10_CAPEX-INGRESOS-PAGOS'!$H$50,0) -> 0
A7: TOTAL INGRESOS | B7: =SUM(B6:B6) -> 0 | C7: =SUM(C6:C6) -> 0 | D7: =SUM(D6:D6) -> 0 | E7: =SUM(E6:E6) -> 0 | F7: =SUM(F6:F6) -> 0 | G7: =SUM(G6:G6) -> 0 | H7: =SUM(H6:H6) -> 0 | I7: =SUM(I6:I6) -> 0 | ... BI7: =SUM(BI6:BI6) -> 0
A9: COSTES OPERATIVOS
A10: Coste de ventas — suelo | B10: =ABS(SUM('30_CASHFLOW'!$B$6:$FZ$6))*IFERROR(B7/'10_CAPEX-INGRESOS-PAGOS'!$H$28,0) -> 0 | C10: =ABS(SUM('30_CASHFLOW'!$B$6:$FZ$6))*IFERROR(C7/'10_CAPEX-INGRESOS-PAGOS'!$H$28,0) -> 0 | D10: =ABS(SUM('30_CASHFLOW'!$B$6:$FZ$6))*IFERROR(D7/'10_CAPEX-INGRESOS-PAGOS'!$H$28,0) -> 0 | E10: =ABS(SUM('30_CASHFLOW'!$B$6:$FZ$6))*IFERROR(E7/'10_CAPEX-INGRESOS-PAGOS'!$H$28,0) -> 0 | F10: =ABS(SUM('30_CASHFLOW'!$B$6:$FZ$6))*IFERROR(F7/'10_CAPEX-INGRESOS-PAGOS'!$H$28,0) -> 0 | G10: =ABS(SUM('30_CASHFLOW'!$B$6:$FZ$6))*IFERROR(G7/'10_CAPEX-INGRESOS-PAGOS'!$H$28,0) -> 0 | H10: =ABS(SUM('30_CASHFLOW'!$B$6:$FZ$6))*IFERROR(H7/'10_CAPEX-INGRESOS-PAGOS'!$H$28,0) -> 0 | I10: =ABS(SUM('30_CASHFLOW'!$B$6:$FZ$6))*IFERROR(I7/'10_CAPEX-INGRESOS-PAGOS'!$H$28,0) -> 0 | ... BI10: =ABS(SUM('30_CASHFLOW'!$B$6:$FZ$6))*IFERROR(BI7/'10_CAPEX-INGRESOS-PAGOS'!$H$28,0) -> 0
A11: Coste de ventas — construcción | B11: =ABS(SUM('30_CASHFLOW'!$B$7:$FZ$7))*IFERROR(B$7/'10_CAPEX-INGRESOS-PAGOS'!$H$28,0) -> 0 | C11: =ABS(SUM('30_CASHFLOW'!$B$7:$FZ$7))*IFERROR(C$7/'10_CAPEX-INGRESOS-PAGOS'!$H$28,0) -> 0 | D11: =ABS(SUM('30_CASHFLOW'!$B$7:$FZ$7))*IFERROR(D$7/'10_CAPEX-INGRESOS-PAGOS'!$H$28,0) -> 0 | E11: =ABS(SUM('30_CASHFLOW'!$B$7:$FZ$7))*IFERROR(E$7/'10_CAPEX-INGRESOS-PAGOS'!$H$28,0) -> 0 | F11: =ABS(SUM('30_CASHFLOW'!$B$7:$FZ$7))*IFERROR(F$7/'10_CAPEX-INGRESOS-PAGOS'!$H$28,0) -> 0 | G11: =ABS(SUM('30_CASHFLOW'!$B$7:$FZ$7))*IFERROR(G$7/'10_CAPEX-INGRESOS-PAGOS'!$H$28,0) -> 0 | H11: =ABS(SUM('30_CASHFLOW'!$B$7:$FZ$7))*IFERROR(H$7/'10_CAPEX-INGRESOS-PAGOS'!$H$28,0) -> 0 | I11: =ABS(SUM('30_CASHFLOW'!$B$7:$FZ$7))*IFERROR(I$7/'10_CAPEX-INGRESOS-PAGOS'!$H$28,0) -> 0 | ... BI11: =ABS(SUM('30_CASHFLOW'!$B$7:$FZ$7))*IFERROR(BI$7/'10_CAPEX-INGRESOS-PAGOS'!$H$28,0) -> 0
A12: Coste de ventas — intereses capitalizados | B12: =SUM('30_CASHFLOW'!$B$33:$FZ$33)*IFERROR(B$7/'10_CAPEX-INGRESOS-PAGOS'!$H$28,0) -> 0 | C12: =SUM('30_CASHFLOW'!$B$33:$FZ$33)*IFERROR(C$7/'10_CAPEX-INGRESOS-PAGOS'!$H$28,0) -> 0 | D12: =SUM('30_CASHFLOW'!$B$33:$FZ$33)*IFERROR(D$7/'10_CAPEX-INGRESOS-PAGOS'!$H$28,0) -> 0 | E12: =SUM('30_CASHFLOW'!$B$33:$FZ$33)*IFERROR(E$7/'10_CAPEX-INGRESOS-PAGOS'!$H$28,0) -> 0 | F12: =SUM('30_CASHFLOW'!$B$33:$FZ$33)*IFERROR(F$7/'10_CAPEX-INGRESOS-PAGOS'!$H$28,0) -> 0 | G12: =SUM('30_CASHFLOW'!$B$33:$FZ$33)*IFERROR(G$7/'10_CAPEX-INGRESOS-PAGOS'!$H$28,0) -> 0 | H12: =SUM('30_CASHFLOW'!$B$33:$FZ$33)*IFERROR(H$7/'10_CAPEX-INGRESOS-PAGOS'!$H$28,0) -> 0 | I12: =SUM('30_CASHFLOW'!$B$33:$FZ$33)*IFERROR(I$7/'10_CAPEX-INGRESOS-PAGOS'!$H$28,0) -> 0 | ... BI12: =SUM('30_CASHFLOW'!$B$33:$FZ$33)*IFERROR(BI$7/'10_CAPEX-INGRESOS-PAGOS'!$H$28,0) -> 0
A13: Coste comercialización | B13: =ABS('30_CASHFLOW'!B18) -> 0 | C13: =ABS('30_CASHFLOW'!C18) -> 0 | D13: =ABS('30_CASHFLOW'!D18) -> 0 | E13: =ABS('30_CASHFLOW'!E18) -> 0 | F13: =ABS('30_CASHFLOW'!F18) -> 0 | G13: =ABS('30_CASHFLOW'!G18) -> 0 | H13: =ABS('30_CASHFLOW'!H18) -> 0 | I13: =ABS('30_CASHFLOW'!I18) -> 0 | ... BI13: =ABS('30_CASHFLOW'!BI18) -> 0
A14: TOTAL COSTES OPERATIVOS | B14: =SUM(B10:B13) -> 0 | C14: =SUM(C10:C13) -> 0 | D14: =SUM(D10:D13) -> 0 | E14: =SUM(E10:E13) -> 0 | F14: =SUM(F10:F13) -> 0 | G14: =SUM(G10:G13) -> 0 | H14: =SUM(H10:H13) -> 0 | I14: =SUM(I10:I13) -> 0 | ... BI14: =SUM(BI10:BI13) -> 0
A16: EBITDA | B16: =B7-B14 -> 0 | C16: =C7-C14 -> 0 | D16: =D7-D14 -> 0 | E16: =E7-E14 -> 0 | F16: =F7-F14 -> 0 | G16: =G7-G14 -> 0 | H16: =H7-H14 -> 0 | I16: =I7-I14 -> 0 | ... BI16: =BI7-BI14 -> 0
A18: RESULTADO FINANCIERO
A19: Intereses no capitalizados / pagados | B19: =ABS('30_CASHFLOW'!B34) -> 0 | C19: =ABS('30_CASHFLOW'!C34) -> 0 | D19: =ABS('30_CASHFLOW'!D34) -> 0 | E19: =ABS('30_CASHFLOW'!E34) -> 0 | F19: =ABS('30_CASHFLOW'!F34) -> 0 | G19: =ABS('30_CASHFLOW'!G34) -> 0 | H19: =ABS('30_CASHFLOW'!H34) -> 0 | I19: =ABS('30_CASHFLOW'!I34) -> 0 | ... BI19: =ABS('30_CASHFLOW'!BI34) -> 0
A20: Comisiones financieras | B20: =ABS('30_CASHFLOW'!B36) -> 0 | C20: =ABS('30_CASHFLOW'!C36) -> 0 | D20: =ABS('30_CASHFLOW'!D36) -> 0 | E20: =ABS('30_CASHFLOW'!E36) -> 0 | F20: =ABS('30_CASHFLOW'!F36) -> 0 | G20: =ABS('30_CASHFLOW'!G36) -> 0 | H20: =ABS('30_CASHFLOW'!H36) -> 0 | I20: =ABS('30_CASHFLOW'!I36) -> 0 | ... BI20: =ABS('30_CASHFLOW'!BI36) -> 0
A21: TOTAL GASTO FINANCIERO | B21: =SUM(B19:B20) -> 0 | C21: =SUM(C19:C20) -> 0 | D21: =SUM(D19:D20) -> 0 | E21: =SUM(E19:E20) -> 0 | F21: =SUM(F19:F20) -> 0 | G21: =SUM(G19:G20) -> 0 | H21: =SUM(H19:H20) -> 0 | I21: =SUM(I19:I20) -> 0 | ... BI21: =SUM(BI19:BI20) -> 0
A23: RESULTADO ANTES DE IMPUESTOS | B23: =B16-B21 -> 0 | C23: =C16-C21 -> 0 | D23: =D16-D21 -> 0 | E23: =E16-E21 -> 0 | F23: =F16-F21 -> 0 | G23: =G16-G21 -> 0 | H23: =H16-H21 -> 0 | I23: =I16-I21 -> 0 | ... BI23: =BI16-BI21 -> 0
A24: Impuesto sobre sociedades | B24: =ABS('30_CASHFLOW'!B38) -> 0 | C24: =ABS('30_CASHFLOW'!C38) -> 0 | D24: =ABS('30_CASHFLOW'!D38) -> 0 | E24: =ABS('30_CASHFLOW'!E38) -> 0 | F24: =ABS('30_CASHFLOW'!F38) -> 0 | G24: =ABS('30_CASHFLOW'!G38) -> 0 | H24: =ABS('30_CASHFLOW'!H38) -> 0 | I24: =ABS('30_CASHFLOW'!I38) -> 0 | ... BI24: =ABS('30_CASHFLOW'!BI38) -> 0
A25: RESULTADO NETO | B25: =B23-B24 -> 0 | C25: =C23-C24 -> 0 | D25: =D23-D24 -> 0 | E25: =E23-E24 -> 0 | F25: =F23-F24 -> 0 | G25: =G23-G24 -> 0 | H25: =H23-H24 -> 0 | I25: =I23-I24 -> 0 | ... BI25: =BI23-BI24 -> 0
A26: RESULTADO NETO ACUMULADO | B26: =SUM($B$25:B25) -> 0 | C26: =SUM($B$25:C25) -> 0 | D26: =SUM($B$25:D25) -> 0 | E26: =SUM($B$25:E25) -> 0 | F26: =SUM($B$25:F25) -> 0 | G26: =SUM($B$25:G25) -> 0 | H26: =SUM($B$25:H25) -> 0 | I26: =SUM($B$25:I25) -> 0 | ... BI26: =SUM($B$25:BI25) -> 715285.95
A28: Checks
A29: Margen EBITDA | B29: =IFERROR(B16/B7,0) -> 0 | C29: =IFERROR(C16/C7,0) -> 0 | D29: =IFERROR(D16/D7,0) -> 0 | E29: =IFERROR(E16/E7,0) -> 0 | F29: =IFERROR(F16/F7,0) -> 0 | G29: =IFERROR(G16/G7,0) -> 0 | H29: =IFERROR(H16/H7,0) -> 0 | I29: =IFERROR(I16/I7,0) -> 0 | ... BI29: =IFERROR(BI16/BI7,0) -> 0
A30: Margen neto | B30: =IFERROR(B25/B7,0) -> 0 | C30: =IFERROR(C25/C7,0) -> 0 | D30: =IFERROR(D25/D7,0) -> 0 | E30: =IFERROR(E25/E7,0) -> 0 | F30: =IFERROR(F25/F7,0) -> 0 | G30: =IFERROR(G25/G7,0) -> 0 | H30: =IFERROR(H25/H7,0) -> 0 | I30: =IFERROR(I25/I7,0) -> 0 | ... BI30: =IFERROR(BI25/BI7,0) -> 0
A31: Control: flujo venta + CAPEX | B31: ='30_CASHFLOW'!B20 -> -1183546 | C31: ='30_CASHFLOW'!C20 -> 0 | D31: ='30_CASHFLOW'!D20 -> 0 | E31: ='30_CASHFLOW'!E20 -> 0 | F31: ='30_CASHFLOW'!F20 -> 0 | G31: ='30_CASHFLOW'!G20 -> 0 | H31: ='30_CASHFLOW'!H20 -> 0 | I31: ='30_CASHFLOW'!I20 -> 0 | ... BI31: ='30_CASHFLOW'!BI20 -> 0
A32: Control: CAPEX total mensual | B32: =ABS('30_CASHFLOW'!B8) -> 1183546 | C32: =ABS('30_CASHFLOW'!C8) -> 0 | D32: =ABS('30_CASHFLOW'!D8) -> 0 | E32: =ABS('30_CASHFLOW'!E8) -> 0 | F32: =ABS('30_CASHFLOW'!F8) -> 0 | G32: =ABS('30_CASHFLOW'!G8) -> 0 | H32: =ABS('30_CASHFLOW'!H8) -> 0 | I32: =ABS('30_CASHFLOW'!I8) -> 0 | ... BI32: =ABS('30_CASHFLOW'!BI8) -> 0

Sheet 32_BALANCE
A1: BALANCE MENSUAL
A2: Tipología: | B2: ='00_ESTRATEGIA'!B3 -> Unifamiliar seg. | D2: Escenario: | E2: ='00_ESTRATEGIA'!B4 -> Base
A4: Mes | B4: 0 | C4: 1 | D4: 2 | E4: 3 | F4: 4 | G4: 5 | H4: 6 | I4: 7 | J4: 8 | K4: 9 | L4: 10 | M4: 11 | N4: 12 | O4: 13 | P4: 14 | Q4: 15 | R4: 16 | S4: 17 | T4: 18 | U4: 19 | V4: 20 | W4: 21 | X4: 22 | Y4: 23 | Z4: 24 | AA4: 25 | AB4: 26 | AC4: 27 | AD4: 28 | AE4: 29 | AF4: 30 | AG4: 31 | AH4: 32 | AI4: 33 | AJ4: 34 | AK4: 35 | AL4: 36 | AM4: 37 | AN4: 38 | AO4: 39 | AP4: 40 | AQ4: 41 | AR4: 42 | AS4: 43 | AT4: 44 | AU4: 45 | AV4: 46 | AW4: 47 | AX4: 48 | AY4: 49 | AZ4: 50 | BA4: 51 | BB4: 52 | BC4: 53 | BD4: 54 | BE4: 55 | BF4: 56 | BG4: 57 | BH4: 58 | BI4: 59
A5: Año | B5: Y0 | C5: Y0 | D5: Y0 | E5: Y0 | F5: Y0 | G5: Y0 | H5: Y0 | I5: Y0 | J5: Y0 | K5: Y0 | L5: Y0 | M5: Y0 | N5: Y1 | O5: Y1 | P5: Y1 | Q5: Y1 | R5: Y1 | S5: Y1 | T5: Y1 | U5: Y1 | V5: Y1 | W5: Y1 | X5: Y1 | Y5: Y1 | Z5: Y2 | AA5: Y2 | AB5: Y2 | AC5: Y2 | AD5: Y2 | AE5: Y2 | AF5: Y2 | AG5: Y2 | AH5: Y2 | AI5: Y2 | AJ5: Y2 | AK5: Y2 | AL5: Y3 | AM5: Y3 | AN5: Y3 | AO5: Y3 | AP5: Y3 | AQ5: Y3 | AR5: Y3 | AS5: Y3 | AT5: Y3 | AU5: Y3 | AV5: Y3 | AW5: Y3 | AX5: Y4 | AY5: Y4 | AZ5: Y4 | BA5: Y4 | BB5: Y4 | BC5: Y4 | BD5: Y4 | BE5: Y4 | BF5: Y4 | BG5: Y4 | BH5: Y4 | BI5: Y4
A6: Periodo | B6: M0 | C6: M1 | D6: M2 | E6: M3 | F6: M4 | G6: M5 | H6: M6 | I6: M7 | J6: M8 | K6: M9 | L6: M10 | M6: M11 | N6: M12 | O6: M13 | P6: M14 | Q6: M15 | R6: M16 | S6: M17 | T6: M18 | U6: M19 | V6: M20 | W6: M21 | X6: M22 | Y6: M23 | Z6: M24 | AA6: M25 | AB6: M26 | AC6: M27 | AD6: M28 | AE6: M29 | AF6: M30 | AG6: M31 | AH6: M32 | AI6: M33 | AJ6: M34 | AK6: M35 | AL6: M36 | AM6: M37 | AN6: M38 | AO6: M39 | AP6: M40 | AQ6: M41 | AR6: M42 | AS6: M43 | AT6: M44 | AU6: M45 | AV6: M46 | AW6: M47 | AX6: M48 | AY6: M49 | AZ6: M50 | BA6: M51 | BB6: M52 | BC6: M53 | BD6: M54 | BE6: M55 | BF6: M56 | BG6: M57 | BH6: M58 | BI6: M59
A8: ACTIVO
A9: Activo No Corriente
A10: Inmovilizado / Inversiones LP | B10: =0 -> 0 | C10: =0 -> 0 | D10: =0 -> 0 | E10: =0 -> 0 | F10: =0 -> 0 | G10: =0 -> 0 | H10: =0 -> 0 | I10: =0 -> 0 | ... BI10: =0 -> 0
A11: Total Activo No Corriente | B11: =SUM(B10:B10) -> 0 | C11: =SUM(C10:C10) -> 0 | D11: =SUM(D10:D10) -> 0 | E11: =SUM(E10:E10) -> 0 | F11: =SUM(F10:F10) -> 0 | G11: =SUM(G10:G10) -> 0 | H11: =SUM(H10:H10) -> 0 | I11: =SUM(I10:I10) -> 0 | ... BI11: =SUM(BI10:BI10) -> 0
A13: Activo Corriente
A14: Existencias suelo | B14: =MAX(0,ABS(SUM('30_CASHFLOW'!$B$6:B$6))-SUM('31_P&L'!$B$10:B$10)) -> 1183546 | C14: =MAX(0,ABS(SUM('30_CASHFLOW'!$B$6:C$6))-SUM('31_P&L'!$B$10:C$10)) -> 1183546 | D14: =MAX(0,ABS(SUM('30_CASHFLOW'!$B$6:D$6))-SUM('31_P&L'!$B$10:D$10)) -> 1183546 | E14: =MAX(0,ABS(SUM('30_CASHFLOW'!$B$6:E$6))-SUM('31_P&L'!$B$10:E$10)) -> 1183546 | F14: =MAX(0,ABS(SUM('30_CASHFLOW'!$B$6:F$6))-SUM('31_P&L'!$B$10:F$10)) -> 1183546 | G14: =MAX(0,ABS(SUM('30_CASHFLOW'!$B$6:G$6))-SUM('31_P&L'!$B$10:G$10)) -> 1183546 | H14: =MAX(0,ABS(SUM('30_CASHFLOW'!$B$6:H$6))-SUM('31_P&L'!$B$10:H$10)) -> 1183546 | I14: =MAX(0,ABS(SUM('30_CASHFLOW'!$B$6:I$6))-SUM('31_P&L'!$B$10:I$10)) -> 1183546 | ... BI14: =MAX(0,ABS(SUM('30_CASHFLOW'!$B$6:BI$6))-SUM('31_P&L'!$B$10:BI$10)) -> 0
A15: Existencias construcción | B15: =MAX(0,ABS(SUM('30_CASHFLOW'!$B$7:B$7))-SUM('31_P&L'!$B$11:B$11)) -> 0 | C15: =MAX(0,ABS(SUM('30_CASHFLOW'!$B$7:C$7))-SUM('31_P&L'!$B$11:C$11)) -> 0 | D15: =MAX(0,ABS(SUM('30_CASHFLOW'!$B$7:D$7))-SUM('31_P&L'!$B$11:D$11)) -> 0 | E15: =MAX(0,ABS(SUM('30_CASHFLOW'!$B$7:E$7))-SUM('31_P&L'!$B$11:E$11)) -> 0 | F15: =MAX(0,ABS(SUM('30_CASHFLOW'!$B$7:F$7))-SUM('31_P&L'!$B$11:F$11)) -> 0 | G15: =MAX(0,ABS(SUM('30_CASHFLOW'!$B$7:G$7))-SUM('31_P&L'!$B$11:G$11)) -> 0 | H15: =MAX(0,ABS(SUM('30_CASHFLOW'!$B$7:H$7))-SUM('31_P&L'!$B$11:H$11)) -> 0 | I15: =MAX(0,ABS(SUM('30_CASHFLOW'!$B$7:I$7))-SUM('31_P&L'!$B$11:I$11)) -> 0 | ... BI15: =MAX(0,ABS(SUM('30_CASHFLOW'!$B$7:BI$7))-SUM('31_P&L'!$B$11:BI$11)) -> 0
A16: Existencias intereses capitalizados | B16: =MAX(0,SUM('30_CASHFLOW'!$B$33:B$33)-SUM('31_P&L'!$B$12:B$12)) -> 0 | C16: =MAX(0,SUM('30_CASHFLOW'!$B$33:C$33)-SUM('31_P&L'!$B$12:C$12)) -> 0 | D16: =MAX(0,SUM('30_CASHFLOW'!$B$33:D$33)-SUM('31_P&L'!$B$12:D$12)) -> 0 | E16: =MAX(0,SUM('30_CASHFLOW'!$B$33:E$33)-SUM('31_P&L'!$B$12:E$12)) -> 0 | F16: =MAX(0,SUM('30_CASHFLOW'!$B$33:F$33)-SUM('31_P&L'!$B$12:F$12)) -> 0 | G16: =MAX(0,SUM('30_CASHFLOW'!$B$33:G$33)-SUM('31_P&L'!$B$12:G$12)) -> 0 | H16: =MAX(0,SUM('30_CASHFLOW'!$B$33:H$33)-SUM('31_P&L'!$B$12:H$12)) -> 0 | I16: =MAX(0,SUM('30_CASHFLOW'!$B$33:I$33)-SUM('31_P&L'!$B$12:I$12)) -> 0 | ... BI16: =MAX(0,SUM('30_CASHFLOW'!$B$33:BI$33)-SUM('31_P&L'!$B$12:BI$12)) -> 0
A17: Clientes / cuentas a cobrar | B17: =MAX(0,SUM('31_P&L'!$B$7:B$7)-SUM('30_CASHFLOW'!$B$17:B$17)) -> 0 | C17: =MAX(0,SUM('31_P&L'!$B$7:C$7)-SUM('30_CASHFLOW'!$B$17:C$17)) -> 0 | D17: =MAX(0,SUM('31_P&L'!$B$7:D$7)-SUM('30_CASHFLOW'!$B$17:D$17)) -> 0 | E17: =MAX(0,SUM('31_P&L'!$B$7:E$7)-SUM('30_CASHFLOW'!$B$17:E$17)) -> 0 | F17: =MAX(0,SUM('31_P&L'!$B$7:F$7)-SUM('30_CASHFLOW'!$B$17:F$17)) -> 0 | G17: =MAX(0,SUM('31_P&L'!$B$7:G$7)-SUM('30_CASHFLOW'!$B$17:G$17)) -> 0 | H17: =MAX(0,SUM('31_P&L'!$B$7:H$7)-SUM('30_CASHFLOW'!$B$17:H$17)) -> 0 | I17: =MAX(0,SUM('31_P&L'!$B$7:I$7)-SUM('30_CASHFLOW'!$B$17:I$17)) -> 0 | ... BI17: =MAX(0,SUM('31_P&L'!$B$7:BI$7)-SUM('30_CASHFLOW'!$B$17:BI$17)) -> 0
A18: Tesorería | B18: =MAX(0,SUM('30_CASHFLOW'!$B$39:B$39)+SUM('30_CASHFLOW'!$B$28:B$28)) -> 0 | C18: =MAX(0,SUM('30_CASHFLOW'!$B$39:C$39)+SUM('30_CASHFLOW'!$B$28:C$28)) -> 0 | D18: =MAX(0,SUM('30_CASHFLOW'!$B$39:D$39)+SUM('30_CASHFLOW'!$B$28:D$28)) -> 0 | E18: =MAX(0,SUM('30_CASHFLOW'!$B$39:E$39)+SUM('30_CASHFLOW'!$B$28:E$28)) -> 0 | F18: =MAX(0,SUM('30_CASHFLOW'!$B$39:F$39)+SUM('30_CASHFLOW'!$B$28:F$28)) -> 0 | G18: =MAX(0,SUM('30_CASHFLOW'!$B$39:G$39)+SUM('30_CASHFLOW'!$B$28:G$28)) -> 0 | H18: =MAX(0,SUM('30_CASHFLOW'!$B$39:H$39)+SUM('30_CASHFLOW'!$B$28:H$28)) -> 0 | I18: =MAX(0,SUM('30_CASHFLOW'!$B$39:I$39)+SUM('30_CASHFLOW'!$B$28:I$28)) -> 0 | ... BI18: =MAX(0,SUM('30_CASHFLOW'!$B$39:BI$39)+SUM('30_CASHFLOW'!$B$28:BI$28)) -> 2596046
A19: Total Activo Corriente | B19: =SUM(B14:B18) -> 1183546 | C19: =SUM(C14:C18) -> 1183546 | D19: =SUM(D14:D18) -> 1183546 | E19: =SUM(E14:E18) -> 1183546 | F19: =SUM(F14:F18) -> 1183546 | G19: =SUM(G14:G18) -> 1183546 | H19: =SUM(H14:H18) -> 1183546 | I19: =SUM(I14:I18) -> 1183546 | ... BI19: =SUM(BI14:BI18) -> 2596046
A21: TOTAL ACTIVO | B21: =B11+B19 -> 1183546 | C21: =C11+C19 -> 1183546 | D21: =D11+D19 -> 1183546 | E21: =E11+E19 -> 1183546 | F21: =F11+F19 -> 1183546 | G21: =G11+G19 -> 1183546 | H21: =H11+H19 -> 1183546 | I21: =I11+I19 -> 1183546 | ... BI21: =BI11+BI19 -> 2596046
A23: PASIVO + PATRIMONIO NETO
A24: Pasivo No Corriente
A25: Deuda con entidades de crédito | B25: ='30_CASHFLOW'!B40 -> 0 | C25: ='30_CASHFLOW'!C40 -> 0 | D25: ='30_CASHFLOW'!D40 -> 0 | E25: ='30_CASHFLOW'!E40 -> 0 | F25: ='30_CASHFLOW'!F40 -> 0 | G25: ='30_CASHFLOW'!G40 -> 0 | H25: ='30_CASHFLOW'!H40 -> 0 | I25: ='30_CASHFLOW'!I40 -> 0 | ... BI25: ='30_CASHFLOW'!BI40 -> 0
A26: Total Pasivo No Corriente | B26: =B25 -> 0 | C26: =C25 -> 0 | D26: =D25 -> 0 | E26: =E25 -> 0 | F26: =F25 -> 0 | G26: =G25 -> 0 | H26: =H25 -> 0 | I26: =I25 -> 0 | ... BI26: =BI25 -> 0
A27: Pasivo Corriente
A28: Anticipos de clientes | B28: =MAX(0,SUM('30_CASHFLOW'!$B$17:B$17)-SUM('31_P&L'!$B$7:B$7)) -> 0 | C28: =MAX(0,SUM('30_CASHFLOW'!$B$17:C$17)-SUM('31_P&L'!$B$7:C$7)) -> 0 | D28: =MAX(0,SUM('30_CASHFLOW'!$B$17:D$17)-SUM('31_P&L'!$B$7:D$7)) -> 0 | E28: =MAX(0,SUM('30_CASHFLOW'!$B$17:E$17)-SUM('31_P&L'!$B$7:E$7)) -> 0 | F28: =MAX(0,SUM('30_CASHFLOW'!$B$17:F$17)-SUM('31_P&L'!$B$7:F$7)) -> 0 | G28: =MAX(0,SUM('30_CASHFLOW'!$B$17:G$17)-SUM('31_P&L'!$B$7:G$7)) -> 0 | H28: =MAX(0,SUM('30_CASHFLOW'!$B$17:H$17)-SUM('31_P&L'!$B$7:H$7)) -> 0 | I28: =MAX(0,SUM('30_CASHFLOW'!$B$17:I$17)-SUM('31_P&L'!$B$7:I$7)) -> 0 | ... BI28: =MAX(0,SUM('30_CASHFLOW'!$B$17:BI$17)-SUM('31_P&L'!$B$7:BI$7)) -> 0
A29: Total Pasivo Corriente | B29: =SUM(B28:B28) -> 0 | C29: =SUM(C28:C28) -> 0 | D29: =SUM(D28:D28) -> 0 | E29: =SUM(E28:E28) -> 0 | F29: =SUM(F28:F28) -> 0 | G29: =SUM(G28:G28) -> 0 | H29: =SUM(H28:H28) -> 0 | I29: =SUM(I28:I28) -> 0 | ... BI29: =SUM(BI28:BI28) -> 0
A31: TOTAL PASIVO | B31: =B26+B29 -> 0 | C31: =C26+C29 -> 0 | D31: =D26+D29 -> 0 | E31: =E26+E29 -> 0 | F31: =F26+F29 -> 0 | G31: =G26+G29 -> 0 | H31: =H26+H29 -> 0 | I31: =I26+I29 -> 0 | ... BI31: =BI26+BI29 -> 0
A33: PATRIMONIO NETO
A34: Capital aportado (acumulado) | B34: =SUM('30_CASHFLOW'!$B$28:B$28) -> 1183546 | C34: =SUM('30_CASHFLOW'!$B$28:C$28) -> 1183546 | D34: =SUM('30_CASHFLOW'!$B$28:D$28) -> 1183546 | E34: =SUM('30_CASHFLOW'!$B$28:E$28) -> 1183546 | F34: =SUM('30_CASHFLOW'!$B$28:F$28) -> 1183546 | G34: =SUM('30_CASHFLOW'!$B$28:G$28) -> 1183546 | H34: =SUM('30_CASHFLOW'!$B$28:H$28) -> 1183546 | I34: =SUM('30_CASHFLOW'!$B$28:I$28) -> 1183546 | ... BI34: =SUM('30_CASHFLOW'!$B$28:BI$28) -> 1880760
A35: Resultados acumulados (según P&L) | B35: ='31_P&L'!B26 -> 0 | C35: ='31_P&L'!C26 -> 0 | D35: ='31_P&L'!D26 -> 0 | E35: ='31_P&L'!E26 -> 0 | F35: ='31_P&L'!F26 -> 0 | G35: ='31_P&L'!G26 -> 0 | H35: ='31_P&L'!H26 -> 0 | I35: ='31_P&L'!I26 -> 0 | ... BI35: ='31_P&L'!BI26 -> 715285.95
A36: TOTAL PATRIMONIO NETO | B36: =SUM(B34:B35) -> 1183546 | C36: =SUM(C34:C35) -> 1183546 | D36: =SUM(D34:D35) -> 1183546 | E36: =SUM(E34:E35) -> 1183546 | F36: =SUM(F34:F35) -> 1183546 | G36: =SUM(G34:G35) -> 1183546 | H36: =SUM(H34:H35) -> 1183546 | I36: =SUM(I34:I35) -> 1183546 | ... BI36: =SUM(BI34:BI35) -> 2596046
A38: TOTAL PASIVO + PN | B38: =B31+B36 -> 1183546 | C38: =C31+C36 -> 1183546 | D38: =D31+D36 -> 1183546 | E38: =E31+E36 -> 1183546 | F38: =F31+F36 -> 1183546 | G38: =G31+G36 -> 1183546 | H38: =H31+H36 -> 1183546 | I38: =I31+I36 -> 1183546 | ... BI38: =BI31+BI36 -> 2596046
A40: CHECK ACTIVO - PASIVO - PN | B40: =B21-B38 -> 0 | C40: =C21-C38 -> 0 | D40: =D21-D38 -> 0 | E40: =E21-E38 -> 0 | F40: =F21-F38 -> 0 | G40: =G21-G38 -> 0 | H40: =H21-H38 -> 0 | I40: =I21-I38 -> 0 | ... BI40: =BI21-BI38 -> 4.1909516e-09
A42: Checks operativos
A43: Deuda / Activo | B43: =IFERROR(B25/B21,0) -> 0 | C43: =IFERROR(C25/C21,0) -> 0 | D43: =IFERROR(D25/D21,0) -> 0 | E43: =IFERROR(E25/E21,0) -> 0 | F43: =IFERROR(F25/F21,0) -> 0 | G43: =IFERROR(G25/G21,0) -> 0 | H43: =IFERROR(H25/H21,0) -> 0 | I43: =IFERROR(I25/I21,0) -> 0 | ... BI43: =IFERROR(BI25/BI21,0) -> 0
A44: Caja mínima / negativa | B44: =B18 -> 0 | C44: =C18 -> 0 | D44: =D18 -> 0 | E44: =E18 -> 0 | F44: =F18 -> 0 | G44: =G18 -> 0 | H44: =H18 -> 0 | I44: =I18 -> 0 | ... BI44: =BI18 -> 2596046

Sheet 40_CASHFLOW_TRIMESTRAL
A1: CASHFLOW TRIMESTRAL
A2: Tipología: | B2: ='00_ESTRATEGIA'!B3 -> Unifamiliar seg. | D2: Escenario: | E2: ='00_ESTRATEGIA'!B4 -> Base
A3: Año | B3: Y0 | C3: Y0 | D3: Y0 | E3: Y0 | F3: Y1 | G3: Y1 | H3: Y1 | I3: Y1 | J3: Y2 | K3: Y2 | L3: Y2 | M3: Y2 | N3: Y3 | O3: Y3 | P3: Y3 | Q3: Y3 | R3: Y4 | S3: Y4 | T3: Y4 | U3: Y4
A4: Mes | B4: 2 | C4: 5 | D4: 8 | E4: 11 | F4: 14 | G4: 17 | H4: 20 | I4: 23 | J4: 26 | K4: 29 | L4: 32 | M4: 35 | N4: 38 | O4: 41 | P4: 44 | Q4: 47 | R4: 50 | S4: 53 | T4: 56 | U4: 59
A5: Periodo | B5: Q0 | C5: Q1 | D5: Q2 | E5: Q3 | F5: Q4 | G5: Q5 | H5: Q6 | I5: Q7 | J5: Q8 | K5: Q9 | L5: Q10 | M5: Q11 | N5: Q12 | O5: Q13 | P5: Q14 | Q5: Q15 | R5: Q16 | S5: Q17 | T5: Q18 | U5: Q19
A6: Suelo | B6: =SUMIFS('30_CASHFLOW'!$B6:$FZ6,'30_CASHFLOW'!$B$3:$FZ$3,">="&(B$4-2),'30_CASHFLOW'!$B$3:$FZ$3,"<="&B$4) -> -1183546 | C6: =SUMIFS('30_CASHFLOW'!$B6:$FZ6,'30_CASHFLOW'!$B$3:$FZ$3,">="&(C$4-2),'30_CASHFLOW'!$B$3:$FZ$3,"<="&C$4) -> 0 | D6: =SUMIFS('30_CASHFLOW'!$B6:$FZ6,'30_CASHFLOW'!$B$3:$FZ$3,">="&(D$4-2),'30_CASHFLOW'!$B$3:$FZ$3,"<="&D$4) -> 0 | E6: =SUMIFS('30_CASHFLOW'!$B6:$FZ6,'30_CASHFLOW'!$B$3:$FZ$3,">="&(E$4-2),'30_CASHFLOW'!$B$3:$FZ$3,"<="&E$4) -> 0 | F6: =SUMIFS('30_CASHFLOW'!$B6:$FZ6,'30_CASHFLOW'!$B$3:$FZ$3,">="&(F$4-2),'30_CASHFLOW'!$B$3:$FZ$3,"<="&F$4) -> 0 | G6: =SUMIFS('30_CASHFLOW'!$B6:$FZ6,'30_CASHFLOW'!$B$3:$FZ$3,">="&(G$4-2),'30_CASHFLOW'!$B$3:$FZ$3,"<="&G$4) -> 0 | H6: =SUMIFS('30_CASHFLOW'!$B6:$FZ6,'30_CASHFLOW'!$B$3:$FZ$3,">="&(H$4-2),'30_CASHFLOW'!$B$3:$FZ$3,"<="&H$4) -> 0 | I6: =SUMIFS('30_CASHFLOW'!$B6:$FZ6,'30_CASHFLOW'!$B$3:$FZ$3,">="&(I$4-2),'30_CASHFLOW'!$B$3:$FZ$3,"<="&I$4) -> 0 | ... U6: =SUMIFS('30_CASHFLOW'!$B6:$FZ6,'30_CASHFLOW'!$B$3:$FZ$3,">="&(U$4-2),'30_CASHFLOW'!$B$3:$FZ$3,"<="&U$4) -> 0
A7: Construcción | B7: =SUMIFS('30_CASHFLOW'!$B7:$FZ7,'30_CASHFLOW'!$B$3:$FZ$3,">="&(B$4-2),'30_CASHFLOW'!$B$3:$FZ$3,"<="&B$4) -> 0 | C7: =SUMIFS('30_CASHFLOW'!$B7:$FZ7,'30_CASHFLOW'!$B$3:$FZ$3,">="&(C$4-2),'30_CASHFLOW'!$B$3:$FZ$3,"<="&C$4) -> 0 | D7: =SUMIFS('30_CASHFLOW'!$B7:$FZ7,'30_CASHFLOW'!$B$3:$FZ$3,">="&(D$4-2),'30_CASHFLOW'!$B$3:$FZ$3,"<="&D$4) -> 0 | E7: =SUMIFS('30_CASHFLOW'!$B7:$FZ7,'30_CASHFLOW'!$B$3:$FZ$3,">="&(E$4-2),'30_CASHFLOW'!$B$3:$FZ$3,"<="&E$4) -> -269680.32 | F7: =SUMIFS('30_CASHFLOW'!$B7:$FZ7,'30_CASHFLOW'!$B$3:$FZ$3,">="&(F$4-2),'30_CASHFLOW'!$B$3:$FZ$3,"<="&F$4) -> -809040.96 | G7: =SUMIFS('30_CASHFLOW'!$B7:$FZ7,'30_CASHFLOW'!$B$3:$FZ$3,">="&(G$4-2),'30_CASHFLOW'!$B$3:$FZ$3,"<="&G$4) -> -809040.96 | H7: =SUMIFS('30_CASHFLOW'!$B7:$FZ7,'30_CASHFLOW'!$B$3:$FZ$3,">="&(H$4-2),'30_CASHFLOW'!$B$3:$FZ$3,"<="&H$4) -> -809040.96 | I7: =SUMIFS('30_CASHFLOW'!$B7:$FZ7,'30_CASHFLOW'!$B$3:$FZ$3,">="&(I$4-2),'30_CASHFLOW'!$B$3:$FZ$3,"<="&I$4) -> -809040.96 | ... U7: =SUMIFS('30_CASHFLOW'!$B7:$FZ7,'30_CASHFLOW'!$B$3:$FZ$3,">="&(U$4-2),'30_CASHFLOW'!$B$3:$FZ$3,"<="&U$4) -> 0
A8: CAPEX Total | B8: =SUMIFS('30_CASHFLOW'!$B8:$FZ8,'30_CASHFLOW'!$B$3:$FZ$3,">="&(B$4-2),'30_CASHFLOW'!$B$3:$FZ$3,"<="&B$4) -> -1183546 | C8: =SUMIFS('30_CASHFLOW'!$B8:$FZ8,'30_CASHFLOW'!$B$3:$FZ$3,">="&(C$4-2),'30_CASHFLOW'!$B$3:$FZ$3,"<="&C$4) -> 0 | D8: =SUMIFS('30_CASHFLOW'!$B8:$FZ8,'30_CASHFLOW'!$B$3:$FZ$3,">="&(D$4-2),'30_CASHFLOW'!$B$3:$FZ$3,"<="&D$4) -> 0 | E8: =SUMIFS('30_CASHFLOW'!$B8:$FZ8,'30_CASHFLOW'!$B$3:$FZ$3,">="&(E$4-2),'30_CASHFLOW'!$B$3:$FZ$3,"<="&E$4) -> -269680.32 | F8: =SUMIFS('30_CASHFLOW'!$B8:$FZ8,'30_CASHFLOW'!$B$3:$FZ$3,">="&(F$4-2),'30_CASHFLOW'!$B$3:$FZ$3,"<="&F$4) -> -809040.96 | G8: =SUMIFS('30_CASHFLOW'!$B8:$FZ8,'30_CASHFLOW'!$B$3:$FZ$3,">="&(G$4-2),'30_CASHFLOW'!$B$3:$FZ$3,"<="&G$4) -> -809040.96 | H8: =SUMIFS('30_CASHFLOW'!$B8:$FZ8,'30_CASHFLOW'!$B$3:$FZ$3,">="&(H$4-2),'30_CASHFLOW'!$B$3:$FZ$3,"<="&H$4) -> -809040.96 | I8: =SUMIFS('30_CASHFLOW'!$B8:$FZ8,'30_CASHFLOW'!$B$3:$FZ$3,">="&(I$4-2),'30_CASHFLOW'!$B$3:$FZ$3,"<="&I$4) -> -809040.96 | ... U8: =SUMIFS('30_CASHFLOW'!$B8:$FZ8,'30_CASHFLOW'!$B$3:$FZ$3,">="&(U$4-2),'30_CASHFLOW'!$B$3:$FZ$3,"<="&U$4) -> 0
A9: Ingresos Venta
A10: Unidades vendidas | B10: =SUMIFS('30_CASHFLOW'!$B10:$FZ10,'30_CASHFLOW'!$B$3:$FZ$3,">="&(B$4-2),'30_CASHFLOW'!$B$3:$FZ$3,"<="&B$4) -> 0 | C10: =SUMIFS('30_CASHFLOW'!$B10:$FZ10,'30_CASHFLOW'!$B$3:$FZ$3,">="&(C$4-2),'30_CASHFLOW'!$B$3:$FZ$3,"<="&C$4) -> 0 | D10: =SUMIFS('30_CASHFLOW'!$B10:$FZ10,'30_CASHFLOW'!$B$3:$FZ$3,">="&(D$4-2),'30_CASHFLOW'!$B$3:$FZ$3,"<="&D$4) -> 0 | E10: =SUMIFS('30_CASHFLOW'!$B10:$FZ10,'30_CASHFLOW'!$B$3:$FZ$3,">="&(E$4-2),'30_CASHFLOW'!$B$3:$FZ$3,"<="&E$4) -> 0 | F10: =SUMIFS('30_CASHFLOW'!$B10:$FZ10,'30_CASHFLOW'!$B$3:$FZ$3,">="&(F$4-2),'30_CASHFLOW'!$B$3:$FZ$3,"<="&F$4) -> 0 | G10: =SUMIFS('30_CASHFLOW'!$B10:$FZ10,'30_CASHFLOW'!$B$3:$FZ$3,">="&(G$4-2),'30_CASHFLOW'!$B$3:$FZ$3,"<="&G$4) -> 0 | H10: =SUMIFS('30_CASHFLOW'!$B10:$FZ10,'30_CASHFLOW'!$B$3:$FZ$3,">="&(H$4-2),'30_CASHFLOW'!$B$3:$FZ$3,"<="&H$4) -> 0 | I10: =SUMIFS('30_CASHFLOW'!$B10:$FZ10,'30_CASHFLOW'!$B$3:$FZ$3,">="&(I$4-2),'30_CASHFLOW'!$B$3:$FZ$3,"<="&I$4) -> 1.25 | ... U10: =SUMIFS('30_CASHFLOW'!$B10:$FZ10,'30_CASHFLOW'!$B$3:$FZ$3,">="&(U$4-2),'30_CASHFLOW'!$B$3:$FZ$3,"<="&U$4) -> 0
A11: % ventas | B11: =SUMIFS('30_CASHFLOW'!$B11:$FZ11,'30_CASHFLOW'!$B$3:$FZ$3,">="&(B$4-2),'30_CASHFLOW'!$B$3:$FZ$3,"<="&B$4) -> 0 | C11: =SUMIFS('30_CASHFLOW'!$B11:$FZ11,'30_CASHFLOW'!$B$3:$FZ$3,">="&(C$4-2),'30_CASHFLOW'!$B$3:$FZ$3,"<="&C$4) -> 0 | D11: =SUMIFS('30_CASHFLOW'!$B11:$FZ11,'30_CASHFLOW'!$B$3:$FZ$3,">="&(D$4-2),'30_CASHFLOW'!$B$3:$FZ$3,"<="&D$4) -> 0 | E11: =SUMIFS('30_CASHFLOW'!$B11:$FZ11,'30_CASHFLOW'!$B$3:$FZ$3,">="&(E$4-2),'30_CASHFLOW'!$B$3:$FZ$3,"<="&E$4) -> 0 | F11: =SUMIFS('30_CASHFLOW'!$B11:$FZ11,'30_CASHFLOW'!$B$3:$FZ$3,">="&(F$4-2),'30_CASHFLOW'!$B$3:$FZ$3,"<="&F$4) -> 0 | G11: =SUMIFS('30_CASHFLOW'!$B11:$FZ11,'30_CASHFLOW'!$B$3:$FZ$3,">="&(G$4-2),'30_CASHFLOW'!$B$3:$FZ$3,"<="&G$4) -> 0 | H11: =SUMIFS('30_CASHFLOW'!$B11:$FZ11,'30_CASHFLOW'!$B$3:$FZ$3,">="&(H$4-2),'30_CASHFLOW'!$B$3:$FZ$3,"<="&H$4) -> 0 | I11: =SUMIFS('30_CASHFLOW'!$B11:$FZ11,'30_CASHFLOW'!$B$3:$FZ$3,">="&(I$4-2),'30_CASHFLOW'!$B$3:$FZ$3,"<="&I$4) -> 0.096153846 | ... U11: =SUMIFS('30_CASHFLOW'!$B11:$FZ11,'30_CASHFLOW'!$B$3:$FZ$3,">="&(U$4-2),'30_CASHFLOW'!$B$3:$FZ$3,"<="&U$4) -> 0
A12: Cobro reserva | B12: =SUMIFS('30_CASHFLOW'!$B12:$FZ12,'30_CASHFLOW'!$B$3:$FZ$3,">="&(B$4-2),'30_CASHFLOW'!$B$3:$FZ$3,"<="&B$4) -> 0 | C12: =SUMIFS('30_CASHFLOW'!$B12:$FZ12,'30_CASHFLOW'!$B$3:$FZ$3,">="&(C$4-2),'30_CASHFLOW'!$B$3:$FZ$3,"<="&C$4) -> 0 | D12: =SUMIFS('30_CASHFLOW'!$B12:$FZ12,'30_CASHFLOW'!$B$3:$FZ$3,">="&(D$4-2),'30_CASHFLOW'!$B$3:$FZ$3,"<="&D$4) -> 0 | E12: =SUMIFS('30_CASHFLOW'!$B12:$FZ12,'30_CASHFLOW'!$B$3:$FZ$3,">="&(E$4-2),'30_CASHFLOW'!$B$3:$FZ$3,"<="&E$4) -> 0 | F12: =SUMIFS('30_CASHFLOW'!$B12:$FZ12,'30_CASHFLOW'!$B$3:$FZ$3,">="&(F$4-2),'30_CASHFLOW'!$B$3:$FZ$3,"<="&F$4) -> 0 | G12: =SUMIFS('30_CASHFLOW'!$B12:$FZ12,'30_CASHFLOW'!$B$3:$FZ$3,">="&(G$4-2),'30_CASHFLOW'!$B$3:$FZ$3,"<="&G$4) -> 0 | H12: =SUMIFS('30_CASHFLOW'!$B12:$FZ12,'30_CASHFLOW'!$B$3:$FZ$3,">="&(H$4-2),'30_CASHFLOW'!$B$3:$FZ$3,"<="&H$4) -> 0 | I12: =SUMIFS('30_CASHFLOW'!$B12:$FZ12,'30_CASHFLOW'!$B$3:$FZ$3,">="&(I$4-2),'30_CASHFLOW'!$B$3:$FZ$3,"<="&I$4) -> 44687.5 | ... U12: =SUMIFS('30_CASHFLOW'!$B12:$FZ12,'30_CASHFLOW'!$B$3:$FZ$3,">="&(U$4-2),'30_CASHFLOW'!$B$3:$FZ$3,"<="&U$4) -> 0
A13: Cobro contrato | B13: =SUMIFS('30_CASHFLOW'!$B13:$FZ13,'30_CASHFLOW'!$B$3:$FZ$3,">="&(B$4-2),'30_CASHFLOW'!$B$3:$FZ$3,"<="&B$4) -> 0 | C13: =SUMIFS('30_CASHFLOW'!$B13:$FZ13,'30_CASHFLOW'!$B$3:$FZ$3,">="&(C$4-2),'30_CASHFLOW'!$B$3:$FZ$3,"<="&C$4) -> 0 | D13: =SUMIFS('30_CASHFLOW'!$B13:$FZ13,'30_CASHFLOW'!$B$3:$FZ$3,">="&(D$4-2),'30_CASHFLOW'!$B$3:$FZ$3,"<="&D$4) -> 0 | E13: =SUMIFS('30_CASHFLOW'!$B13:$FZ13,'30_CASHFLOW'!$B$3:$FZ$3,">="&(E$4-2),'30_CASHFLOW'!$B$3:$FZ$3,"<="&E$4) -> 0 | F13: =SUMIFS('30_CASHFLOW'!$B13:$FZ13,'30_CASHFLOW'!$B$3:$FZ$3,">="&(F$4-2),'30_CASHFLOW'!$B$3:$FZ$3,"<="&F$4) -> 0 | G13: =SUMIFS('30_CASHFLOW'!$B13:$FZ13,'30_CASHFLOW'!$B$3:$FZ$3,">="&(G$4-2),'30_CASHFLOW'!$B$3:$FZ$3,"<="&G$4) -> 0 | H13: =SUMIFS('30_CASHFLOW'!$B13:$FZ13,'30_CASHFLOW'!$B$3:$FZ$3,">="&(H$4-2),'30_CASHFLOW'!$B$3:$FZ$3,"<="&H$4) -> 0 | I13: =SUMIFS('30_CASHFLOW'!$B13:$FZ13,'30_CASHFLOW'!$B$3:$FZ$3,">="&(I$4-2),'30_CASHFLOW'!$B$3:$FZ$3,"<="&I$4) -> 0 | ... U13: =SUMIFS('30_CASHFLOW'!$B13:$FZ13,'30_CASHFLOW'!$B$3:$FZ$3,">="&(U$4-2),'30_CASHFLOW'!$B$3:$FZ$3,"<="&U$4) -> 0
A14: Cobro aplazado lineal | B14: =SUMIFS('30_CASHFLOW'!$B14:$FZ14,'30_CASHFLOW'!$B$3:$FZ$3,">="&(B$4-2),'30_CASHFLOW'!$B$3:$FZ$3,"<="&B$4) -> 0 | C14: =SUMIFS('30_CASHFLOW'!$B14:$FZ14,'30_CASHFLOW'!$B$3:$FZ$3,">="&(C$4-2),'30_CASHFLOW'!$B$3:$FZ$3,"<="&C$4) -> 0 | D14: =SUMIFS('30_CASHFLOW'!$B14:$FZ14,'30_CASHFLOW'!$B$3:$FZ$3,">="&(D$4-2),'30_CASHFLOW'!$B$3:$FZ$3,"<="&D$4) -> 0 | E14: =SUMIFS('30_CASHFLOW'!$B14:$FZ14,'30_CASHFLOW'!$B$3:$FZ$3,">="&(E$4-2),'30_CASHFLOW'!$B$3:$FZ$3,"<="&E$4) -> 0 | F14: =SUMIFS('30_CASHFLOW'!$B14:$FZ14,'30_CASHFLOW'!$B$3:$FZ$3,">="&(F$4-2),'30_CASHFLOW'!$B$3:$FZ$3,"<="&F$4) -> 0 | G14: =SUMIFS('30_CASHFLOW'!$B14:$FZ14,'30_CASHFLOW'!$B$3:$FZ$3,">="&(G$4-2),'30_CASHFLOW'!$B$3:$FZ$3,"<="&G$4) -> 0 | H14: =SUMIFS('30_CASHFLOW'!$B14:$FZ14,'30_CASHFLOW'!$B$3:$FZ$3,">="&(H$4-2),'30_CASHFLOW'!$B$3:$FZ$3,"<="&H$4) -> 0 | I14: =SUMIFS('30_CASHFLOW'!$B14:$FZ14,'30_CASHFLOW'!$B$3:$FZ$3,">="&(I$4-2),'30_CASHFLOW'!$B$3:$FZ$3,"<="&I$4) -> 0 | ... U14: =SUMIFS('30_CASHFLOW'!$B14:$FZ14,'30_CASHFLOW'!$B$3:$FZ$3,">="&(U$4-2),'30_CASHFLOW'!$B$3:$FZ$3,"<="&U$4) -> 0
A15: Escritura fin de obra | B15: =SUMIFS('30_CASHFLOW'!$B15:$FZ15,'30_CASHFLOW'!$B$3:$FZ$3,">="&(B$4-2),'30_CASHFLOW'!$B$3:$FZ$3,"<="&B$4) -> 0 | C15: =SUMIFS('30_CASHFLOW'!$B15:$FZ15,'30_CASHFLOW'!$B$3:$FZ$3,">="&(C$4-2),'30_CASHFLOW'!$B$3:$FZ$3,"<="&C$4) -> 0 | D15: =SUMIFS('30_CASHFLOW'!$B15:$FZ15,'30_CASHFLOW'!$B$3:$FZ$3,">="&(D$4-2),'30_CASHFLOW'!$B$3:$FZ$3,"<="&D$4) -> 0 | E15: =SUMIFS('30_CASHFLOW'!$B15:$FZ15,'30_CASHFLOW'!$B$3:$FZ$3,">="&(E$4-2),'30_CASHFLOW'!$B$3:$FZ$3,"<="&E$4) -> 0 | F15: =SUMIFS('30_CASHFLOW'!$B15:$FZ15,'30_CASHFLOW'!$B$3:$FZ$3,">="&(F$4-2),'30_CASHFLOW'!$B$3:$FZ$3,"<="&F$4) -> 0 | G15: =SUMIFS('30_CASHFLOW'!$B15:$FZ15,'30_CASHFLOW'!$B$3:$FZ$3,">="&(G$4-2),'30_CASHFLOW'!$B$3:$FZ$3,"<="&G$4) -> 0 | H15: =SUMIFS('30_CASHFLOW'!$B15:$FZ15,'30_CASHFLOW'!$B$3:$FZ$3,">="&(H$4-2),'30_CASHFLOW'!$B$3:$FZ$3,"<="&H$4) -> 0 | I15: =SUMIFS('30_CASHFLOW'!$B15:$FZ15,'30_CASHFLOW'!$B$3:$FZ$3,">="&(I$4-2),'30_CASHFLOW'!$B$3:$FZ$3,"<="&I$4) -> 0 | ... U15: =SUMIFS('30_CASHFLOW'!$B15:$FZ15,'30_CASHFLOW'!$B$3:$FZ$3,">="&(U$4-2),'30_CASHFLOW'!$B$3:$FZ$3,"<="&U$4) -> 0
A16: Escritura post fin de obra | B16: =SUMIFS('30_CASHFLOW'!$B16:$FZ16,'30_CASHFLOW'!$B$3:$FZ$3,">="&(B$4-2),'30_CASHFLOW'!$B$3:$FZ$3,"<="&B$4) -> 0 | C16: =SUMIFS('30_CASHFLOW'!$B16:$FZ16,'30_CASHFLOW'!$B$3:$FZ$3,">="&(C$4-2),'30_CASHFLOW'!$B$3:$FZ$3,"<="&C$4) -> 0 | D16: =SUMIFS('30_CASHFLOW'!$B16:$FZ16,'30_CASHFLOW'!$B$3:$FZ$3,">="&(D$4-2),'30_CASHFLOW'!$B$3:$FZ$3,"<="&D$4) -> 0 | E16: =SUMIFS('30_CASHFLOW'!$B16:$FZ16,'30_CASHFLOW'!$B$3:$FZ$3,">="&(E$4-2),'30_CASHFLOW'!$B$3:$FZ$3,"<="&E$4) -> 0 | F16: =SUMIFS('30_CASHFLOW'!$B16:$FZ16,'30_CASHFLOW'!$B$3:$FZ$3,">="&(F$4-2),'30_CASHFLOW'!$B$3:$FZ$3,"<="&F$4) -> 0 | G16: =SUMIFS('30_CASHFLOW'!$B16:$FZ16,'30_CASHFLOW'!$B$3:$FZ$3,">="&(G$4-2),'30_CASHFLOW'!$B$3:$FZ$3,"<="&G$4) -> 0 | H16: =SUMIFS('30_CASHFLOW'!$B16:$FZ16,'30_CASHFLOW'!$B$3:$FZ$3,">="&(H$4-2),'30_CASHFLOW'!$B$3:$FZ$3,"<="&H$4) -> 0 | I16: =SUMIFS('30_CASHFLOW'!$B16:$FZ16,'30_CASHFLOW'!$B$3:$FZ$3,">="&(I$4-2),'30_CASHFLOW'!$B$3:$FZ$3,"<="&I$4) -> 0 | ... U16: =SUMIFS('30_CASHFLOW'!$B16:$FZ16,'30_CASHFLOW'!$B$3:$FZ$3,">="&(U$4-2),'30_CASHFLOW'!$B$3:$FZ$3,"<="&U$4) -> 0
A17: Total cobro ventas (bruto) | B17: =SUMIFS('30_CASHFLOW'!$B17:$FZ17,'30_CASHFLOW'!$B$3:$FZ$3,">="&(B$4-2),'30_CASHFLOW'!$B$3:$FZ$3,"<="&B$4) -> 0 | C17: =SUMIFS('30_CASHFLOW'!$B17:$FZ17,'30_CASHFLOW'!$B$3:$FZ$3,">="&(C$4-2),'30_CASHFLOW'!$B$3:$FZ$3,"<="&C$4) -> 0 | D17: =SUMIFS('30_CASHFLOW'!$B17:$FZ17,'30_CASHFLOW'!$B$3:$FZ$3,">="&(D$4-2),'30_CASHFLOW'!$B$3:$FZ$3,"<="&D$4) -> 0 | E17: =SUMIFS('30_CASHFLOW'!$B17:$FZ17,'30_CASHFLOW'!$B$3:$FZ$3,">="&(E$4-2),'30_CASHFLOW'!$B$3:$FZ$3,"<="&E$4) -> 0 | F17: =SUMIFS('30_CASHFLOW'!$B17:$FZ17,'30_CASHFLOW'!$B$3:$FZ$3,">="&(F$4-2),'30_CASHFLOW'!$B$3:$FZ$3,"<="&F$4) -> 0 | G17: =SUMIFS('30_CASHFLOW'!$B17:$FZ17,'30_CASHFLOW'!$B$3:$FZ$3,">="&(G$4-2),'30_CASHFLOW'!$B$3:$FZ$3,"<="&G$4) -> 0 | H17: =SUMIFS('30_CASHFLOW'!$B17:$FZ17,'30_CASHFLOW'!$B$3:$FZ$3,">="&(H$4-2),'30_CASHFLOW'!$B$3:$FZ$3,"<="&H$4) -> 0 | I17: =SUMIFS('30_CASHFLOW'!$B17:$FZ17,'30_CASHFLOW'!$B$3:$FZ$3,">="&(I$4-2),'30_CASHFLOW'!$B$3:$FZ$3,"<="&I$4) -> 44687.5 | ... U17: =SUMIFS('30_CASHFLOW'!$B17:$FZ17,'30_CASHFLOW'!$B$3:$FZ$3,">="&(U$4-2),'30_CASHFLOW'!$B$3:$FZ$3,"<="&U$4) -> 0
A18: Coste comercialización | B18: =SUMIFS('30_CASHFLOW'!$B18:$FZ18,'30_CASHFLOW'!$B$3:$FZ$3,">="&(B$4-2),'30_CASHFLOW'!$B$3:$FZ$3,"<="&B$4) -> 0 | C18: =SUMIFS('30_CASHFLOW'!$B18:$FZ18,'30_CASHFLOW'!$B$3:$FZ$3,">="&(C$4-2),'30_CASHFLOW'!$B$3:$FZ$3,"<="&C$4) -> 0 | D18: =SUMIFS('30_CASHFLOW'!$B18:$FZ18,'30_CASHFLOW'!$B$3:$FZ$3,">="&(D$4-2),'30_CASHFLOW'!$B$3:$FZ$3,"<="&D$4) -> 0 | E18: =SUMIFS('30_CASHFLOW'!$B18:$FZ18,'30_CASHFLOW'!$B$3:$FZ$3,">="&(E$4-2),'30_CASHFLOW'!$B$3:$FZ$3,"<="&E$4) -> 0 | F18: =SUMIFS('30_CASHFLOW'!$B18:$FZ18,'30_CASHFLOW'!$B$3:$FZ$3,">="&(F$4-2),'30_CASHFLOW'!$B$3:$FZ$3,"<="&F$4) -> 0 | G18: =SUMIFS('30_CASHFLOW'!$B18:$FZ18,'30_CASHFLOW'!$B$3:$FZ$3,">="&(G$4-2),'30_CASHFLOW'!$B$3:$FZ$3,"<="&G$4) -> 0 | H18: =SUMIFS('30_CASHFLOW'!$B18:$FZ18,'30_CASHFLOW'!$B$3:$FZ$3,">="&(H$4-2),'30_CASHFLOW'!$B$3:$FZ$3,"<="&H$4) -> 0 | I18: =SUMIFS('30_CASHFLOW'!$B18:$FZ18,'30_CASHFLOW'!$B$3:$FZ$3,">="&(I$4-2),'30_CASHFLOW'!$B$3:$FZ$3,"<="&I$4) -> 26812.5 | ... U18: =SUMIFS('30_CASHFLOW'!$B18:$FZ18,'30_CASHFLOW'!$B$3:$FZ$3,">="&(U$4-2),'30_CASHFLOW'!$B$3:$FZ$3,"<="&U$4) -> 0
A19: Ingresos netos venta | B19: =SUMIFS('30_CASHFLOW'!$B19:$FZ19,'30_CASHFLOW'!$B$3:$FZ$3,">="&(B$4-2),'30_CASHFLOW'!$B$3:$FZ$3,"<="&B$4) -> 0 | C19: =SUMIFS('30_CASHFLOW'!$B19:$FZ19,'30_CASHFLOW'!$B$3:$FZ$3,">="&(C$4-2),'30_CASHFLOW'!$B$3:$FZ$3,"<="&C$4) -> 0 | D19: =SUMIFS('30_CASHFLOW'!$B19:$FZ19,'30_CASHFLOW'!$B$3:$FZ$3,">="&(D$4-2),'30_CASHFLOW'!$B$3:$FZ$3,"<="&D$4) -> 0 | E19: =SUMIFS('30_CASHFLOW'!$B19:$FZ19,'30_CASHFLOW'!$B$3:$FZ$3,">="&(E$4-2),'30_CASHFLOW'!$B$3:$FZ$3,"<="&E$4) -> 0 | F19: =SUMIFS('30_CASHFLOW'!$B19:$FZ19,'30_CASHFLOW'!$B$3:$FZ$3,">="&(F$4-2),'30_CASHFLOW'!$B$3:$FZ$3,"<="&F$4) -> 0 | G19: =SUMIFS('30_CASHFLOW'!$B19:$FZ19,'30_CASHFLOW'!$B$3:$FZ$3,">="&(G$4-2),'30_CASHFLOW'!$B$3:$FZ$3,"<="&G$4) -> 0 | H19: =SUMIFS('30_CASHFLOW'!$B19:$FZ19,'30_CASHFLOW'!$B$3:$FZ$3,">="&(H$4-2),'30_CASHFLOW'!$B$3:$FZ$3,"<="&H$4) -> 0 | I19: =SUMIFS('30_CASHFLOW'!$B19:$FZ19,'30_CASHFLOW'!$B$3:$FZ$3,">="&(I$4-2),'30_CASHFLOW'!$B$3:$FZ$3,"<="&I$4) -> 17875 | ... U19: =SUMIFS('30_CASHFLOW'!$B19:$FZ19,'30_CASHFLOW'!$B$3:$FZ$3,">="&(U$4-2),'30_CASHFLOW'!$B$3:$FZ$3,"<="&U$4) -> 0
A20: Flujo neto venta + CAPEX | B20: =SUMIFS('30_CASHFLOW'!$B20:$FZ20,'30_CASHFLOW'!$B$3:$FZ$3,">="&(B$4-2),'30_CASHFLOW'!$B$3:$FZ$3,"<="&B$4) -> -1183546 | C20: =SUMIFS('30_CASHFLOW'!$B20:$FZ20,'30_CASHFLOW'!$B$3:$FZ$3,">="&(C$4-2),'30_CASHFLOW'!$B$3:$FZ$3,"<="&C$4) -> 0 | D20: =SUMIFS('30_CASHFLOW'!$B20:$FZ20,'30_CASHFLOW'!$B$3:$FZ$3,">="&(D$4-2),'30_CASHFLOW'!$B$3:$FZ$3,"<="&D$4) -> 0 | E20: =SUMIFS('30_CASHFLOW'!$B20:$FZ20,'30_CASHFLOW'!$B$3:$FZ$3,">="&(E$4-2),'30_CASHFLOW'!$B$3:$FZ$3,"<="&E$4) -> -269680.32 | F20: =SUMIFS('30_CASHFLOW'!$B20:$FZ20,'30_CASHFLOW'!$B$3:$FZ$3,">="&(F$4-2),'30_CASHFLOW'!$B$3:$FZ$3,"<="&F$4) -> -809040.96 | G20: =SUMIFS('30_CASHFLOW'!$B20:$FZ20,'30_CASHFLOW'!$B$3:$FZ$3,">="&(G$4-2),'30_CASHFLOW'!$B$3:$FZ$3,"<="&G$4) -> -809040.96 | H20: =SUMIFS('30_CASHFLOW'!$B20:$FZ20,'30_CASHFLOW'!$B$3:$FZ$3,">="&(H$4-2),'30_CASHFLOW'!$B$3:$FZ$3,"<="&H$4) -> -809040.96 | I20: =SUMIFS('30_CASHFLOW'!$B20:$FZ20,'30_CASHFLOW'!$B$3:$FZ$3,">="&(I$4-2),'30_CASHFLOW'!$B$3:$FZ$3,"<="&I$4) -> -791165.96 | ... U20: =SUMIFS('30_CASHFLOW'!$B20:$FZ20,'30_CASHFLOW'!$B$3:$FZ$3,">="&(U$4-2),'30_CASHFLOW'!$B$3:$FZ$3,"<="&U$4) -> 0
A21: Alquiler | B21: =SUMIFS('30_CASHFLOW'!$B21:$FZ21,'30_CASHFLOW'!$B$3:$FZ$3,">="&(B$4-2),'30_CASHFLOW'!$B$3:$FZ$3,"<="&B$4) -> 0 | C21: =SUMIFS('30_CASHFLOW'!$B21:$FZ21,'30_CASHFLOW'!$B$3:$FZ$3,">="&(C$4-2),'30_CASHFLOW'!$B$3:$FZ$3,"<="&C$4) -> 0 | D21: =SUMIFS('30_CASHFLOW'!$B21:$FZ21,'30_CASHFLOW'!$B$3:$FZ$3,">="&(D$4-2),'30_CASHFLOW'!$B$3:$FZ$3,"<="&D$4) -> 0 | E21: =SUMIFS('30_CASHFLOW'!$B21:$FZ21,'30_CASHFLOW'!$B$3:$FZ$3,">="&(E$4-2),'30_CASHFLOW'!$B$3:$FZ$3,"<="&E$4) -> 0 | F21: =SUMIFS('30_CASHFLOW'!$B21:$FZ21,'30_CASHFLOW'!$B$3:$FZ$3,">="&(F$4-2),'30_CASHFLOW'!$B$3:$FZ$3,"<="&F$4) -> 0 | G21: =SUMIFS('30_CASHFLOW'!$B21:$FZ21,'30_CASHFLOW'!$B$3:$FZ$3,">="&(G$4-2),'30_CASHFLOW'!$B$3:$FZ$3,"<="&G$4) -> 0 | H21: =SUMIFS('30_CASHFLOW'!$B21:$FZ21,'30_CASHFLOW'!$B$3:$FZ$3,">="&(H$4-2),'30_CASHFLOW'!$B$3:$FZ$3,"<="&H$4) -> 0 | I21: =SUMIFS('30_CASHFLOW'!$B21:$FZ21,'30_CASHFLOW'!$B$3:$FZ$3,">="&(I$4-2),'30_CASHFLOW'!$B$3:$FZ$3,"<="&I$4) -> 0 | ... U21: =SUMIFS('30_CASHFLOW'!$B21:$FZ21,'30_CASHFLOW'!$B$3:$FZ$3,">="&(U$4-2),'30_CASHFLOW'!$B$3:$FZ$3,"<="&U$4) -> 0
... A26: Flujo neto alquiler + CAPEX | B26: =SUMIFS('30_CASHFLOW'!$B26:$FZ26,'30_CASHFLOW'!$B$3:$FZ$3,">="&(B$4-2),'30_CASHFLOW'!$B$3:$FZ$3,"<="&B$4) -> -1183546 | C26: =SUMIFS('30_CASHFLOW'!$B26:$FZ26,'30_CASHFLOW'!$B$3:$FZ$3,">="&(C$4-2),'30_CASHFLOW'!$B$3:$FZ$3,"<="&C$4) -> 0 | D26: =SUMIFS('30_CASHFLOW'!$B26:$FZ26,'30_CASHFLOW'!$B$3:$FZ$3,">="&(D$4-2),'30_CASHFLOW'!$B$3:$FZ$3,"<="&D$4) -> 0 | E26: =SUMIFS('30_CASHFLOW'!$B26:$FZ26,'30_CASHFLOW'!$B$3:$FZ$3,">="&(E$4-2),'30_CASHFLOW'!$B$3:$FZ$3,"<="&E$4) -> -269680.32 | F26: =SUMIFS('30_CASHFLOW'!$B26:$FZ26,'30_CASHFLOW'!$B$3:$FZ$3,">="&(F$4-2),'30_CASHFLOW'!$B$3:$FZ$3,"<="&F$4) -> -809040.96 | G26: =SUMIFS('30_CASHFLOW'!$B26:$FZ26,'30_CASHFLOW'!$B$3:$FZ$3,">="&(G$4-2),'30_CASHFLOW'!$B$3:$FZ$3,"<="&G$4) -> -809040.96 | H26: =SUMIFS('30_CASHFLOW'!$B26:$FZ26,'30_CASHFLOW'!$B$3:$FZ$3,">="&(H$4-2),'30_CASHFLOW'!$B$3:$FZ$3,"<="&H$4) -> -809040.96 | I26: =SUMIFS('30_CASHFLOW'!$B26:$FZ26,'30_CASHFLOW'!$B$3:$FZ$3,">="&(I$4-2),'30_CASHFLOW'!$B$3:$FZ$3,"<="&I$4) -> -809040.96 | ... U26: =SUMIFS('30_CASHFLOW'!$B26:$FZ26,'30_CASHFLOW'!$B$3:$FZ$3,">="&(U$4-2),'30_CASHFLOW'!$B$3:$FZ$3,"<="&U$4) -> 54670.706
A27: Financiación
A28: Equity aportado | B28: =SUMIFS('30_CASHFLOW'!$B28:$FZ28,'30_CASHFLOW'!$B$3:$FZ$3,">="&(B$4-2),'30_CASHFLOW'!$B$3:$FZ$3,"<="&B$4) -> 1183546 | C28: =SUMIFS('30_CASHFLOW'!$B28:$FZ28,'30_CASHFLOW'!$B$3:$FZ$3,">="&(C$4-2),'30_CASHFLOW'!$B$3:$FZ$3,"<="&C$4) -> 0 | D28: =SUMIFS('30_CASHFLOW'!$B28:$FZ28,'30_CASHFLOW'!$B$3:$FZ$3,">="&(D$4-2),'30_CASHFLOW'!$B$3:$FZ$3,"<="&D$4) -> 0 | E28: =SUMIFS('30_CASHFLOW'!$B28:$FZ28,'30_CASHFLOW'!$B$3:$FZ$3,">="&(E$4-2),'30_CASHFLOW'!$B$3:$FZ$3,"<="&E$4) -> 33305.52 | F28: =SUMIFS('30_CASHFLOW'!$B28:$FZ28,'30_CASHFLOW'!$B$3:$FZ$3,">="&(F$4-2),'30_CASHFLOW'!$B$3:$FZ$3,"<="&F$4) -> 4584.5654 | G28: =SUMIFS('30_CASHFLOW'!$B28:$FZ28,'30_CASHFLOW'!$B$3:$FZ$3,">="&(G$4-2),'30_CASHFLOW'!$B$3:$FZ$3,"<="&G$4) -> 3573.2642 | H28: =SUMIFS('30_CASHFLOW'!$B28:$FZ28,'30_CASHFLOW'!$B$3:$FZ$3,">="&(H$4-2),'30_CASHFLOW'!$B$3:$FZ$3,"<="&H$4) -> 2561.963 | I28: =SUMIFS('30_CASHFLOW'!$B28:$FZ28,'30_CASHFLOW'!$B$3:$FZ$3,">="&(I$4-2),'30_CASHFLOW'!$B$3:$FZ$3,"<="&I$4) -> 1146.1414 | ... U28: =SUMIFS('30_CASHFLOW'!$B28:$FZ28,'30_CASHFLOW'!$B$3:$FZ$3,">="&(U$4-2),'30_CASHFLOW'!$B$3:$FZ$3,"<="&U$4) -> 0
A29: Deuda dispuesta | B29: =SUMIFS('30_CASHFLOW'!$B29:$FZ29,'30_CASHFLOW'!$B$3:$FZ$3,">="&(B$4-2),'30_CASHFLOW'!$B$3:$FZ$3,"<="&B$4) -> 0 | C29: =SUMIFS('30_CASHFLOW'!$B29:$FZ29,'30_CASHFLOW'!$B$3:$FZ$3,">="&(C$4-2),'30_CASHFLOW'!$B$3:$FZ$3,"<="&C$4) -> 0 | D29: =SUMIFS('30_CASHFLOW'!$B29:$FZ29,'30_CASHFLOW'!$B$3:$FZ$3,">="&(D$4-2),'30_CASHFLOW'!$B$3:$FZ$3,"<="&D$4) -> 0 | E29: =SUMIFS('30_CASHFLOW'!$B29:$FZ29,'30_CASHFLOW'!$B$3:$FZ$3,">="&(E$4-2),'30_CASHFLOW'!$B$3:$FZ$3,"<="&E$4) -> 269680.32 | F29: =SUMIFS('30_CASHFLOW'!$B29:$FZ29,'30_CASHFLOW'!$B$3:$FZ$3,">="&(F$4-2),'30_CASHFLOW'!$B$3:$FZ$3,"<="&F$4) -> 809040.96 | G29: =SUMIFS('30_CASHFLOW'!$B29:$FZ29,'30_CASHFLOW'!$B$3:$FZ$3,">="&(G$4-2),'30_CASHFLOW'!$B$3:$FZ$3,"<="&G$4) -> 809040.96 | H29: =SUMIFS('30_CASHFLOW'!$B29:$FZ29,'30_CASHFLOW'!$B$3:$FZ$3,">="&(H$4-2),'30_CASHFLOW'!$B$3:$FZ$3,"<="&H$4) -> 809040.96 | I29: =SUMIFS('30_CASHFLOW'!$B29:$FZ29,'30_CASHFLOW'!$B$3:$FZ$3,">="&(I$4-2),'30_CASHFLOW'!$B$3:$FZ$3,"<="&I$4) -> 809040.96 | ... U29: =SUMIFS('30_CASHFLOW'!$B29:$FZ29,'30_CASHFLOW'!$B$3:$FZ$3,">="&(U$4-2),'30_CASHFLOW'!$B$3:$FZ$3,"<="&U$4) -> 0
A30: Total entradas financiación | B30: =SUMIFS('30_CASHFLOW'!$B30:$FZ30,'30_CASHFLOW'!$B$3:$FZ$3,">="&(B$4-2),'30_CASHFLOW'!$B$3:$FZ$3,"<="&B$4) -> 1183546 | C30: =SUMIFS('30_CASHFLOW'!$B30:$FZ30,'30_CASHFLOW'!$B$3:$FZ$3,">="&(C$4-2),'30_CASHFLOW'!$B$3:$FZ$3,"<="&C$4) -> 0 | D30: =SUMIFS('30_CASHFLOW'!$B30:$FZ30,'30_CASHFLOW'!$B$3:$FZ$3,">="&(D$4-2),'30_CASHFLOW'!$B$3:$FZ$3,"<="&D$4) -> 0 | E30: =SUMIFS('30_CASHFLOW'!$B30:$FZ30,'30_CASHFLOW'!$B$3:$FZ$3,">="&(E$4-2),'30_CASHFLOW'!$B$3:$FZ$3,"<="&E$4) -> 302985.84 | F30: =SUMIFS('30_CASHFLOW'!$B30:$FZ30,'30_CASHFLOW'!$B$3:$FZ$3,">="&(F$4-2),'30_CASHFLOW'!$B$3:$FZ$3,"<="&F$4) -> 813625.53 | G30: =SUMIFS('30_CASHFLOW'!$B30:$FZ30,'30_CASHFLOW'!$B$3:$FZ$3,">="&(G$4-2),'30_CASHFLOW'!$B$3:$FZ$3,"<="&G$4) -> 812614.22 | H30: =SUMIFS('30_CASHFLOW'!$B30:$FZ30,'30_CASHFLOW'!$B$3:$FZ$3,">="&(H$4-2),'30_CASHFLOW'!$B$3:$FZ$3,"<="&H$4) -> 811602.92 | I30: =SUMIFS('30_CASHFLOW'!$B30:$FZ30,'30_CASHFLOW'!$B$3:$FZ$3,">="&(I$4-2),'30_CASHFLOW'!$B$3:$FZ$3,"<="&I$4) -> 810187.1 | ... U30: =SUMIFS('30_CASHFLOW'!$B30:$FZ30,'30_CASHFLOW'!$B$3:$FZ$3,">="&(U$4-2),'30_CASHFLOW'!$B$3:$FZ$3,"<="&U$4) -> 0
A31: Servicio de la deuda
A32: Intereses devengados | B32: =SUMIFS('30_CASHFLOW'!$B32:$FZ32,'30_CASHFLOW'!$B$3:$FZ$3,">="&(B$4-2),'30_CASHFLOW'!$B$3:$FZ$3,"<="&B$4) -> 0 | C32: =SUMIFS('30_CASHFLOW'!$B32:$FZ32,'30_CASHFLOW'!$B$3:$FZ$3,">="&(C$4-2),'30_CASHFLOW'!$B$3:$FZ$3,"<="&C$4) -> 0 | D32: =SUMIFS('30_CASHFLOW'!$B32:$FZ32,'30_CASHFLOW'!$B$3:$FZ$3,">="&(D$4-2),'30_CASHFLOW'!$B$3:$FZ$3,"<="&D$4) -> 0 | E32: =SUMIFS('30_CASHFLOW'!$B32:$FZ32,'30_CASHFLOW'!$B$3:$FZ$3,">="&(E$4-2),'30_CASHFLOW'!$B$3:$FZ$3,"<="&E$4) -> 618.0174 | F32: =SUMIFS('30_CASHFLOW'!$B32:$FZ32,'30_CASHFLOW'!$B$3:$FZ$3,">="&(F$4-2),'30_CASHFLOW'!$B$3:$FZ$3,"<="&F$4) -> 9309.9951 | G32: =SUMIFS('30_CASHFLOW'!$B32:$FZ32,'30_CASHFLOW'!$B$3:$FZ$3,">="&(G$4-2),'30_CASHFLOW'!$B$3:$FZ$3,"<="&G$4) -> 20613.973 | H32: =SUMIFS('30_CASHFLOW'!$B32:$FZ32,'30_CASHFLOW'!$B$3:$FZ$3,">="&(H$4-2),'30_CASHFLOW'!$B$3:$FZ$3,"<="&H$4) -> 32074.093 | I32: =SUMIFS('30_CASHFLOW'!$B32:$FZ32,'30_CASHFLOW'!$B$3:$FZ$3,">="&(I$4-2),'30_CASHFLOW'!$B$3:$FZ$3,"<="&I$4) -> 43692.514 | ... U32: =SUMIFS('30_CASHFLOW'!$B32:$FZ32,'30_CASHFLOW'!$B$3:$FZ$3,">="&(U$4-2),'30_CASHFLOW'!$B$3:$FZ$3,"<="&U$4) -> 0
A33: Intereses capitalizados (no cash) | B33: =SUMIFS('30_CASHFLOW'!$B33:$FZ33,'30_CASHFLOW'!$B$3:$FZ$3,">="&(B$4-2),'30_CASHFLOW'!$B$3:$FZ$3,"<="&B$4) -> 0 | C33: =SUMIFS('30_CASHFLOW'!$B33:$FZ33,'30_CASHFLOW'!$B$3:$FZ$3,">="&(C$4-2),'30_CASHFLOW'!$B$3:$FZ$3,"<="&C$4) -> 0 | D33: =SUMIFS('30_CASHFLOW'!$B33:$FZ33,'30_CASHFLOW'!$B$3:$FZ$3,">="&(D$4-2),'30_CASHFLOW'!$B$3:$FZ$3,"<="&D$4) -> 0 | E33: =SUMIFS('30_CASHFLOW'!$B33:$FZ33,'30_CASHFLOW'!$B$3:$FZ$3,">="&(E$4-2),'30_CASHFLOW'!$B$3:$FZ$3,"<="&E$4) -> 618.0174 | F33: =SUMIFS('30_CASHFLOW'!$B33:$FZ33,'30_CASHFLOW'!$B$3:$FZ$3,">="&(F$4-2),'30_CASHFLOW'!$B$3:$FZ$3,"<="&F$4) -> 9309.9951 | G33: =SUMIFS('30_CASHFLOW'!$B33:$FZ33,'30_CASHFLOW'!$B$3:$FZ$3,">="&(G$4-2),'30_CASHFLOW'!$B$3:$FZ$3,"<="&G$4) -> 20613.973 | H33: =SUMIFS('30_CASHFLOW'!$B33:$FZ33,'30_CASHFLOW'!$B$3:$FZ$3,">="&(H$4-2),'30_CASHFLOW'!$B$3:$FZ$3,"<="&H$4) -> 32074.093 | I33: =SUMIFS('30_CASHFLOW'!$B33:$FZ33,'30_CASHFLOW'!$B$3:$FZ$3,">="&(I$4-2),'30_CASHFLOW'!$B$3:$FZ$3,"<="&I$4) -> 43692.514 | ... U33: =SUMIFS('30_CASHFLOW'!$B33:$FZ33,'30_CASHFLOW'!$B$3:$FZ$3,">="&(U$4-2),'30_CASHFLOW'!$B$3:$FZ$3,"<="&U$4) -> 0
A34: Intereses pagados (cash) | B34: =SUMIFS('30_CASHFLOW'!$B34:$FZ34,'30_CASHFLOW'!$B$3:$FZ$3,">="&(B$4-2),'30_CASHFLOW'!$B$3:$FZ$3,"<="&B$4) -> 0 | C34: =SUMIFS('30_CASHFLOW'!$B34:$FZ34,'30_CASHFLOW'!$B$3:$FZ$3,">="&(C$4-2),'30_CASHFLOW'!$B$3:$FZ$3,"<="&C$4) -> 0 | D34: =SUMIFS('30_CASHFLOW'!$B34:$FZ34,'30_CASHFLOW'!$B$3:$FZ$3,">="&(D$4-2),'30_CASHFLOW'!$B$3:$FZ$3,"<="&D$4) -> 0 | E34: =SUMIFS('30_CASHFLOW'!$B34:$FZ34,'30_CASHFLOW'!$B$3:$FZ$3,">="&(E$4-2),'30_CASHFLOW'!$B$3:$FZ$3,"<="&E$4) -> 0 | F34: =SUMIFS('30_CASHFLOW'!$B34:$FZ34,'30_CASHFLOW'!$B$3:$FZ$3,">="&(F$4-2),'30_CASHFLOW'!$B$3:$FZ$3,"<="&F$4) -> 0 | G34: =SUMIFS('30_CASHFLOW'!$B34:$FZ34,'30_CASHFLOW'!$B$3:$FZ$3,">="&(G$4-2),'30_CASHFLOW'!$B$3:$FZ$3,"<="&G$4) -> 0 | H34: =SUMIFS('30_CASHFLOW'!$B34:$FZ34,'30_CASHFLOW'!$B$3:$FZ$3,">="&(H$4-2),'30_CASHFLOW'!$B$3:$FZ$3,"<="&H$4) -> 0 | I34: =SUMIFS('30_CASHFLOW'!$B34:$FZ34,'30_CASHFLOW'!$B$3:$FZ$3,">="&(I$4-2),'30_CASHFLOW'!$B$3:$FZ$3,"<="&I$4) -> 0 | ... U34: =SUMIFS('30_CASHFLOW'!$B34:$FZ34,'30_CASHFLOW'!$B$3:$FZ$3,">="&(U$4-2),'30_CASHFLOW'!$B$3:$FZ$3,"<="&U$4) -> 0
A35: Amortización por ventas | B35: =SUMIFS('30_CASHFLOW'!$B35:$FZ35,'30_CASHFLOW'!$B$3:$FZ$3,">="&(B$4-2),'30_CASHFLOW'!$B$3:$FZ$3,"<="&B$4) -> 0 | C35: =SUMIFS('30_CASHFLOW'!$B35:$FZ35,'30_CASHFLOW'!$B$3:$FZ$3,">="&(C$4-2),'30_CASHFLOW'!$B$3:$FZ$3,"<="&C$4) -> 0 | D35: =SUMIFS('30_CASHFLOW'!$B35:$FZ35,'30_CASHFLOW'!$B$3:$FZ$3,">="&(D$4-2),'30_CASHFLOW'!$B$3:$FZ$3,"<="&D$4) -> 0 | E35: =SUMIFS('30_CASHFLOW'!$B35:$FZ35,'30_CASHFLOW'!$B$3:$FZ$3,">="&(E$4-2),'30_CASHFLOW'!$B$3:$FZ$3,"<="&E$4) -> 0 | F35: =SUMIFS('30_CASHFLOW'!$B35:$FZ35,'30_CASHFLOW'!$B$3:$FZ$3,">="&(F$4-2),'30_CASHFLOW'!$B$3:$FZ$3,"<="&F$4) -> 0 | G35: =SUMIFS('30_CASHFLOW'!$B35:$FZ35,'30_CASHFLOW'!$B$3:$FZ$3,">="&(G$4-2),'30_CASHFLOW'!$B$3:$FZ$3,"<="&G$4) -> 0 | H35: =SUMIFS('30_CASHFLOW'!$B35:$FZ35,'30_CASHFLOW'!$B$3:$FZ$3,">="&(H$4-2),'30_CASHFLOW'!$B$3:$FZ$3,"<="&H$4) -> 0 | I35: =SUMIFS('30_CASHFLOW'!$B35:$FZ35,'30_CASHFLOW'!$B$3:$FZ$3,">="&(I$4-2),'30_CASHFLOW'!$B$3:$FZ$3,"<="&I$4) -> 0 | ... U35: =SUMIFS('30_CASHFLOW'!$B35:$FZ35,'30_CASHFLOW'!$B$3:$FZ$3,">="&(U$4-2),'30_CASHFLOW'!$B$3:$FZ$3,"<="&U$4) -> 0
A36: Comisiones (apertura + no disponibilidad) | B36: =SUMIFS('30_CASHFLOW'!$B36:$FZ36,'30_CASHFLOW'!$B$3:$FZ$3,">="&(B$4-2),'30_CASHFLOW'!$B$3:$FZ$3,"<="&B$4) -> 0 | C36: =SUMIFS('30_CASHFLOW'!$B36:$FZ36,'30_CASHFLOW'!$B$3:$FZ$3,">="&(C$4-2),'30_CASHFLOW'!$B$3:$FZ$3,"<="&C$4) -> 0 | D36: =SUMIFS('30_CASHFLOW'!$B36:$FZ36,'30_CASHFLOW'!$B$3:$FZ$3,">="&(D$4-2),'30_CASHFLOW'!$B$3:$FZ$3,"<="&D$4) -> 0 | E36: =SUMIFS('30_CASHFLOW'!$B36:$FZ36,'30_CASHFLOW'!$B$3:$FZ$3,">="&(E$4-2),'30_CASHFLOW'!$B$3:$FZ$3,"<="&E$4) -> -33305.52 | F36: =SUMIFS('30_CASHFLOW'!$B36:$FZ36,'30_CASHFLOW'!$B$3:$FZ$3,">="&(F$4-2),'30_CASHFLOW'!$B$3:$FZ$3,"<="&F$4) -> -4584.5654 | G36: =SUMIFS('30_CASHFLOW'!$B36:$FZ36,'30_CASHFLOW'!$B$3:$FZ$3,">="&(G$4-2),'30_CASHFLOW'!$B$3:$FZ$3,"<="&G$4) -> -3573.2642 | H36: =SUMIFS('30_CASHFLOW'!$B36:$FZ36,'30_CASHFLOW'!$B$3:$FZ$3,">="&(H$4-2),'30_CASHFLOW'!$B$3:$FZ$3,"<="&H$4) -> -2561.963 | I36: =SUMIFS('30_CASHFLOW'!$B36:$FZ36,'30_CASHFLOW'!$B$3:$FZ$3,">="&(I$4-2),'30_CASHFLOW'!$B$3:$FZ$3,"<="&I$4) -> -1550.6618 | ... U36: =SUMIFS('30_CASHFLOW'!$B36:$FZ36,'30_CASHFLOW'!$B$3:$FZ$3,">="&(U$4-2),'30_CASHFLOW'!$B$3:$FZ$3,"<="&U$4) -> 0
A37: Servicio total de la deuda (cash) | B37: =SUMIFS('30_CASHFLOW'!$B37:$FZ37,'30_CASHFLOW'!$B$3:$FZ$3,">="&(B$4-2),'30_CASHFLOW'!$B$3:$FZ$3,"<="&B$4) -> 0 | C37: =SUMIFS('30_CASHFLOW'!$B37:$FZ37,'30_CASHFLOW'!$B$3:$FZ$3,">="&(C$4-2),'30_CASHFLOW'!$B$3:$FZ$3,"<="&C$4) -> 0 | D37: =SUMIFS('30_CASHFLOW'!$B37:$FZ37,'30_CASHFLOW'!$B$3:$FZ$3,">="&(D$4-2),'30_CASHFLOW'!$B$3:$FZ$3,"<="&D$4) -> 0 | E37: =SUMIFS('30_CASHFLOW'!$B37:$FZ37,'30_CASHFLOW'!$B$3:$FZ$3,">="&(E$4-2),'30_CASHFLOW'!$B$3:$FZ$3,"<="&E$4) -> -33305.52 | F37: =SUMIFS('30_CASHFLOW'!$B37:$FZ37,'30_CASHFLOW'!$B$3:$FZ$3,">="&(F$4-2),'30_CASHFLOW'!$B$3:$FZ$3,"<="&F$4) -> -4584.5654 | G37: =SUMIFS('30_CASHFLOW'!$B37:$FZ37,'30_CASHFLOW'!$B$3:$FZ$3,">="&(G$4-2),'30_CASHFLOW'!$B$3:$FZ$3,"<="&G$4) -> -3573.2642 | H37: =SUMIFS('30_CASHFLOW'!$B37:$FZ37,'30_CASHFLOW'!$B$3:$FZ$3,">="&(H$4-2),'30_CASHFLOW'!$B$3:$FZ$3,"<="&H$4) -> -2561.963 | I37: =SUMIFS('30_CASHFLOW'!$B37:$FZ37,'30_CASHFLOW'!$B$3:$FZ$3,">="&(I$4-2),'30_CASHFLOW'!$B$3:$FZ$3,"<="&I$4) -> -1550.6618 | ... U37: =SUMIFS('30_CASHFLOW'!$B37:$FZ37,'30_CASHFLOW'!$B$3:$FZ$3,">="&(U$4-2),'30_CASHFLOW'!$B$3:$FZ$3,"<="&U$4) -> 0
A38: IS pagado (cash) | B38: =SUMIFS('30_CASHFLOW'!$B38:$FZ38,'30_CASHFLOW'!$B$3:$FZ$3,">="&(B$4-2),'30_CASHFLOW'!$B$3:$FZ$3,"<="&B$4) -> 0 | C38: =SUMIFS('30_CASHFLOW'!$B38:$FZ38,'30_CASHFLOW'!$B$3:$FZ$3,">="&(C$4-2),'30_CASHFLOW'!$B$3:$FZ$3,"<="&C$4) -> 0 | D38: =SUMIFS('30_CASHFLOW'!$B38:$FZ38,'30_CASHFLOW'!$B$3:$FZ$3,">="&(D$4-2),'30_CASHFLOW'!$B$3:$FZ$3,"<="&D$4) -> 0 | E38: =SUMIFS('30_CASHFLOW'!$B38:$FZ38,'30_CASHFLOW'!$B$3:$FZ$3,">="&(E$4-2),'30_CASHFLOW'!$B$3:$FZ$3,"<="&E$4) -> 0 | F38: =SUMIFS('30_CASHFLOW'!$B38:$FZ38,'30_CASHFLOW'!$B$3:$FZ$3,">="&(F$4-2),'30_CASHFLOW'!$B$3:$FZ$3,"<="&F$4) -> 0 | G38: =SUMIFS('30_CASHFLOW'!$B38:$FZ38,'30_CASHFLOW'!$B$3:$FZ$3,">="&(G$4-2),'30_CASHFLOW'!$B$3:$FZ$3,"<="&G$4) -> 0 | H38: =SUMIFS('30_CASHFLOW'!$B38:$FZ38,'30_CASHFLOW'!$B$3:$FZ$3,">="&(H$4-2),'30_CASHFLOW'!$B$3:$FZ$3,"<="&H$4) -> 0 | I38: =SUMIFS('30_CASHFLOW'!$B38:$FZ38,'30_CASHFLOW'!$B$3:$FZ$3,">="&(I$4-2),'30_CASHFLOW'!$B$3:$FZ$3,"<="&I$4) -> 0 | ... U38: =SUMIFS('30_CASHFLOW'!$B38:$FZ38,'30_CASHFLOW'!$B$3:$FZ$3,">="&(U$4-2),'30_CASHFLOW'!$B$3:$FZ$3,"<="&U$4) -> 0
A39: Cashflow del accionista | B39: =SUMIFS('30_CASHFLOW'!$B39:$FZ39,'30_CASHFLOW'!$B$3:$FZ$3,">="&(B$4-2),'30_CASHFLOW'!$B$3:$FZ$3,"<="&B$4) -> -1183546 | C39: =SUMIFS('30_CASHFLOW'!$B39:$FZ39,'30_CASHFLOW'!$B$3:$FZ$3,">="&(C$4-2),'30_CASHFLOW'!$B$3:$FZ$3,"<="&C$4) -> 0 | D39: =SUMIFS('30_CASHFLOW'!$B39:$FZ39,'30_CASHFLOW'!$B$3:$FZ$3,">="&(D$4-2),'30_CASHFLOW'!$B$3:$FZ$3,"<="&D$4) -> 0 | E39: =SUMIFS('30_CASHFLOW'!$B39:$FZ39,'30_CASHFLOW'!$B$3:$FZ$3,">="&(E$4-2),'30_CASHFLOW'!$B$3:$FZ$3,"<="&E$4) -> -33305.52 | F39: =SUMIFS('30_CASHFLOW'!$B39:$FZ39,'30_CASHFLOW'!$B$3:$FZ$3,">="&(F$4-2),'30_CASHFLOW'!$B$3:$FZ$3,"<="&F$4) -> -4584.5654 | G39: =SUMIFS('30_CASHFLOW'!$B39:$FZ39,'30_CASHFLOW'!$B$3:$FZ$3,">="&(G$4-2),'30_CASHFLOW'!$B$3:$FZ$3,"<="&G$4) -> -3573.2642 | H39: =SUMIFS('30_CASHFLOW'!$B39:$FZ39,'30_CASHFLOW'!$B$3:$FZ$3,">="&(H$4-2),'30_CASHFLOW'!$B$3:$FZ$3,"<="&H$4) -> -2561.963 | I39: =SUMIFS('30_CASHFLOW'!$B39:$FZ39,'30_CASHFLOW'!$B$3:$FZ$3,">="&(I$4-2),'30_CASHFLOW'!$B$3:$FZ$3,"<="&I$4) -> 16324.338 | ... U39: =SUMIFS('30_CASHFLOW'!$B39:$FZ39,'30_CASHFLOW'!$B$3:$FZ$3,">="&(U$4-2),'30_CASHFLOW'!$B$3:$FZ$3,"<="&U$4) -> 0
A40: Saldo vivo del préstamo (memoria) | B40: {=LOOKUP(2,1/('30_CASHFLOW'!$B$3:$BI$3<=B$4),'30_CASHFLOW'!$B40:$FZ40)} -> 0 | C40: {=LOOKUP(2,1/('30_CASHFLOW'!$B$3:$BI$3<=C$4),'30_CASHFLOW'!$B40:$FZ40)} -> 0 | D40: {=LOOKUP(2,1/('30_CASHFLOW'!$B$3:$BI$3<=D$4),'30_CASHFLOW'!$B40:$FZ40)} -> 0 | E40: {=LOOKUP(2,1/('30_CASHFLOW'!$B$3:$BI$3<=E$4),'30_CASHFLOW'!$B40:$FZ40)} -> 270298.34 | F40: {=LOOKUP(2,1/('30_CASHFLOW'!$B$3:$BI$3<=F$4),'30_CASHFLOW'!$B40:$FZ40)} -> 1088649.3 | G40: {=LOOKUP(2,1/('30_CASHFLOW'!$B$3:$BI$3<=G$4),'30_CASHFLOW'!$B40:$FZ40)} -> 1918304.2 | H40: {=LOOKUP(2,1/('30_CASHFLOW'!$B$3:$BI$3<=H$4),'30_CASHFLOW'!$B40:$FZ40)} -> 2759419.3 | I40: {=LOOKUP(2,1/('30_CASHFLOW'!$B$3:$BI$3<=I$4),'30_CASHFLOW'!$B40:$FZ40)} -> 3612152.8 | ... U40: {=LOOKUP(2,1/('30_CASHFLOW'!$B$3:$BI$3<=U$4),'30_CASHFLOW'!$B40:$FZ40)} -> 0
A41: FCF accionista acumulado (memoria) | B41: {=LOOKUP(2,1/('30_CASHFLOW'!$B$3:$BI$3<=B$4),'30_CASHFLOW'!$B41:$FZ41)} -> -1183546 | C41: {=LOOKUP(2,1/('30_CASHFLOW'!$B$3:$BI$3<=C$4),'30_CASHFLOW'!$B41:$FZ41)} -> -1183546 | D41: {=LOOKUP(2,1/('30_CASHFLOW'!$B$3:$BI$3<=D$4),'30_CASHFLOW'!$B41:$FZ41)} -> -1183546 | E41: {=LOOKUP(2,1/('30_CASHFLOW'!$B$3:$BI$3<=E$4),'30_CASHFLOW'!$B41:$FZ41)} -> -1216851.5 | F41: {=LOOKUP(2,1/('30_CASHFLOW'!$B$3:$BI$3<=F$4),'30_CASHFLOW'!$B41:$FZ41)} -> -1221436.1 | G41: {=LOOKUP(2,1/('30_CASHFLOW'!$B$3:$BI$3<=G$4),'30_CASHFLOW'!$B41:$FZ41)} -> -1225009.3 | H41: {=LOOKUP(2,1/('30_CASHFLOW'!$B$3:$BI$3<=H$4),'30_CASHFLOW'!$B41:$FZ41)} -> -1227571.3 | I41: {=LOOKUP(2,1/('30_CASHFLOW'!$B$3:$BI$3<=I$4),'30_CASHFLOW'!$B41:$FZ41)} -> -1211247 | ... U41: {=LOOKUP(2,1/('30_CASHFLOW'!$B$3:$BI$3<=U$4),'30_CASHFLOW'!$B41:$FZ41)} -> 715285.95

Sheet 41_P&L_TRIMESTRAL
A1: CUENTA DE RESULTADOS TRIMESTRAL
A2: Tipología: | C2: ='00_ESTRATEGIA'!B3 -> Unifamiliar seg. | E2: Escenario: | F2: ='00_ESTRATEGIA'!B4 -> Base
A4: Mes | C4: Y0 | D4: Y0 | E4: Y0 | F4: Y0 | G4: Y1 | H4: Y1 | I4: Y1 | J4: Y1 | K4: Y2 | L4: Y2 | M4: Y2 | N4: Y2 | O4: Y3 | P4: Y3 | Q4: Y3 | R4: Y3 | S4: Y4 | T4: Y4 | U4: Y4 | V4: Y4
A5: Año | C5: 2 | D5: 5 | E5: 8 | F5: 11 | G5: 14 | H5: 17 | I5: 20 | J5: 23 | K5: 26 | L5: 29 | M5: 32 | N5: 35 | O5: 38 | P5: 41 | Q5: 44 | R5: 47 | S5: 50 | T5: 53 | U5: 56 | V5: 59
A6: Periodo | C6: Q0 | D6: Q1 | E6: Q2 | F6: Q3 | G6: Q4 | H6: Q5 | I6: Q6 | J6: Q7 | K6: Q8 | L6: Q9 | M6: Q10 | N6: Q11 | O6: Q12 | P6: Q13 | Q6: Q14 | R6: Q15 | S6: Q16 | T6: Q17 | U6: Q18 | V6: Q19
A7: INGRESOS
A8: Ingresos reconocidos por escritura / entrega | C8: =SUMIFS('31_P&L'!$B$6:$BI$6,'31_P&L'!$B$3:$BI$3,">="&0,'31_P&L'!$B$3:$BI$3,"<="&2) -> 0 | D8: =SUMIFS('31_P&L'!$B$6:$BI$6,'31_P&L'!$B$3:$BI$3,">="&3,'31_P&L'!$B$3:$BI$3,"<="&5) -> 0 | E8: =SUMIFS('31_P&L'!$B$6:$BI$6,'31_P&L'!$B$3:$BI$3,">="&6,'31_P&L'!$B$3:$BI$3,"<="&8) -> 0 | F8: =SUMIFS('31_P&L'!$B$6:$BI$6,'31_P&L'!$B$3:$BI$3,">="&9,'31_P&L'!$B$3:$BI$3,"<="&11) -> 0 | G8: =SUMIFS('31_P&L'!$B$6:$BI$6,'31_P&L'!$B$3:$BI$3,">="&12,'31_P&L'!$B$3:$BI$3,"<="&14) -> 0 | H8: =SUMIFS('31_P&L'!$B$6:$BI$6,'31_P&L'!$B$3:$BI$3,">="&15,'31_P&L'!$B$3:$BI$3,"<="&17) -> 0 | I8: =SUMIFS('31_P&L'!$B$6:$BI$6,'31_P&L'!$B$3:$BI$3,">="&18,'31_P&L'!$B$3:$BI$3,"<="&20) -> 0 | J8: =SUMIFS('31_P&L'!$B$6:$BI$6,'31_P&L'!$B$3:$BI$3,">="&21,'31_P&L'!$B$3:$BI$3,"<="&23) -> 0 | K8: =SUMIFS('31_P&L'!$B$6:$BI$6,'31_P&L'!$B$3:$BI$3,">="&24,'31_P&L'!$B$3:$BI$3,"<="&26) -> 0 | L8: =SUMIFS('31_P&L'!$B$6:$BI$6,'31_P&L'!$B$3:$BI$3,">="&27,'31_P&L'!$B$3:$BI$3,"<="&29) -> 0 | M8: =SUMIFS('31_P&L'!$B$6:$BI$6,'31_P&L'!$B$3:$BI$3,">="&30,'31_P&L'!$B$3:$BI$3,"<="&32) -> 0 | N8: =SUMIFS('31_P&L'!$B$6:$BI$6,'31_P&L'!$B$3:$BI$3,">="&33,'31_P&L'!$B$3:$BI$3,"<="&35) -> 9295000 | O8: =SUMIFS('31_P&L'!$B$6:$BI$6,'31_P&L'!$B$3:$BI$3,">="&36,'31_P&L'!$B$3:$BI$3,"<="&38) -> 0 | P8: =SUMIFS('31_P&L'!$B$6:$BI$6,'31_P&L'!$B$3:$BI$3,">="&39,'31_P&L'!$B$3:$BI$3,"<="&41) -> 0 | Q8: =SUMIFS('31_P&L'!$B$6:$BI$6,'31_P&L'!$B$3:$BI$3,">="&42,'31_P&L'!$B$3:$BI$3,"<="&44) -> 0 | R8: =SUMIFS('31_P&L'!$B$6:$BI$6,'31_P&L'!$B$3:$BI$3,">="&45,'31_P&L'!$B$3:$BI$3,"<="&47) -> 0 | S8: =SUMIFS('31_P&L'!$B$6:$BI$6,'31_P&L'!$B$3:$BI$3,">="&48,'31_P&L'!$B$3:$BI$3,"<="&50) -> 0 | T8: =SUMIFS('31_P&L'!$B$6:$BI$6,'31_P&L'!$B$3:$BI$3,">="&51,'31_P&L'!$B$3:$BI$3,"<="&53) -> 0 | U8: =SUMIFS('31_P&L'!$B$6:$BI$6,'31_P&L'!$B$3:$BI$3,">="&54,'31_P&L'!$B$3:$BI$3,"<="&56) -> 0 | V8: =SUMIFS('31_P&L'!$B$6:$BI$6,'31_P&L'!$B$3:$BI$3,">="&57,'31_P&L'!$B$3:$BI$3,"<="&59) -> 0
A9: TOTAL INGRESOS | C9: =SUMIFS('31_P&L'!$B$7:$BI$7,'31_P&L'!$B$3:$BI$3,">="&0,'31_P&L'!$B$3:$BI$3,"<="&2) -> 0 | D9: =SUMIFS('31_P&L'!$B$7:$BI$7,'31_P&L'!$B$3:$BI$3,">="&3,'31_P&L'!$B$3:$BI$3,"<="&5) -> 0 | E9: =SUMIFS('31_P&L'!$B$7:$BI$7,'31_P&L'!$B$3:$BI$3,">="&6,'31_P&L'!$B$3:$BI$3,"<="&8) -> 0 | F9: =SUMIFS('31_P&L'!$B$7:$BI$7,'31_P&L'!$B$3:$BI$3,">="&9,'31_P&L'!$B$3:$BI$3,"<="&11) -> 0 | G9: =SUMIFS('31_P&L'!$B$7:$BI$7,'31_P&L'!$B$3:$BI$3,">="&12,'31_P&L'!$B$3:$BI$3,"<="&14) -> 0 | H9: =SUMIFS('31_P&L'!$B$7:$BI$7,'31_P&L'!$B$3:$BI$3,">="&15,'31_P&L'!$B$3:$BI$3,"<="&17) -> 0 | I9: =SUMIFS('31_P&L'!$B$7:$BI$7,'31_P&L'!$B$3:$BI$3,">="&18,'31_P&L'!$B$3:$BI$3,"<="&20) -> 0 | J9: =SUMIFS('31_P&L'!$B$7:$BI$7,'31_P&L'!$B$3:$BI$3,">="&21,'31_P&L'!$B$3:$BI$3,"<="&23) -> 0 | K9: =SUMIFS('31_P&L'!$B$7:$BI$7,'31_P&L'!$B$3:$BI$3,">="&24,'31_P&L'!$B$3:$BI$3,"<="&26) -> 0 | L9: =SUMIFS('31_P&L'!$B$7:$BI$7,'31_P&L'!$B$3:$BI$3,">="&27,'31_P&L'!$B$3:$BI$3,"<="&29) -> 0 | M9: =SUMIFS('31_P&L'!$B$7:$BI$7,'31_P&L'!$B$3:$BI$3,">="&30,'31_P&L'!$B$3:$BI$3,"<="&32) -> 0 | N9: =SUMIFS('31_P&L'!$B$7:$BI$7,'31_P&L'!$B$3:$BI$3,">="&33,'31_P&L'!$B$3:$BI$3,"<="&35) -> 9295000 | O9: =SUMIFS('31_P&L'!$B$7:$BI$7,'31_P&L'!$B$3:$BI$3,">="&36,'31_P&L'!$B$3:$BI$3,"<="&38) -> 0 | P9: =SUMIFS('31_P&L'!$B$7:$BI$7,'31_P&L'!$B$3:$BI$3,">="&39,'31_P&L'!$B$3:$BI$3,"<="&41) -> 0 | Q9: =SUMIFS('31_P&L'!$B$7:$BI$7,'31_P&L'!$B$3:$BI$3,">="&42,'31_P&L'!$B$3:$BI$3,"<="&44) -> 0 | R9: =SUMIFS('31_P&L'!$B$7:$BI$7,'31_P&L'!$B$3:$BI$3,">="&45,'31_P&L'!$B$3:$BI$3,"<="&47) -> 0 | S9: =SUMIFS('31_P&L'!$B$7:$BI$7,'31_P&L'!$B$3:$BI$3,">="&48,'31_P&L'!$B$3:$BI$3,"<="&50) -> 0 | T9: =SUMIFS('31_P&L'!$B$7:$BI$7,'31_P&L'!$B$3:$BI$3,">="&51,'31_P&L'!$B$3:$BI$3,"<="&53) -> 0 | U9: =SUMIFS('31_P&L'!$B$7:$BI$7,'31_P&L'!$B$3:$BI$3,">="&54,'31_P&L'!$B$3:$BI$3,"<="&56) -> 0 | V9: =SUMIFS('31_P&L'!$B$7:$BI$7,'31_P&L'!$B$3:$BI$3,">="&57,'31_P&L'!$B$3:$BI$3,"<="&59) -> 0
A11: COSTES OPERATIVOS
A12: Coste de ventas — suelo | C12: =SUMIFS('31_P&L'!$B$10:$BI$10,'31_P&L'!$B$3:$BI$3,">="&0,'31_P&L'!$B$3:$BI$3,"<="&2) -> 0 | D12: =SUMIFS('31_P&L'!$B$10:$BI$10,'31_P&L'!$B$3:$BI$3,">="&3,'31_P&L'!$B$3:$BI$3,"<="&5) -> 0 | E12: =SUMIFS('31_P&L'!$B$10:$BI$10,'31_P&L'!$B$3:$BI$3,">="&6,'31_P&L'!$B$3:$BI$3,"<="&8) -> 0 | F12: =SUMIFS('31_P&L'!$B$10:$BI$10,'31_P&L'!$B$3:$BI$3,">="&9,'31_P&L'!$B$3:$BI$3,"<="&11) -> 0 | G12: =SUMIFS('31_P&L'!$B$10:$BI$10,'31_P&L'!$B$3:$BI$3,">="&12,'31_P&L'!$B$3:$BI$3,"<="&14) -> 0 | H12: =SUMIFS('31_P&L'!$B$10:$BI$10,'31_P&L'!$B$3:$BI$3,">="&15,'31_P&L'!$B$3:$BI$3,"<="&17) -> 0 | I12: =SUMIFS('31_P&L'!$B$10:$BI$10,'31_P&L'!$B$3:$BI$3,">="&18,'31_P&L'!$B$3:$BI$3,"<="&20) -> 0 | J12: =SUMIFS('31_P&L'!$B$10:$BI$10,'31_P&L'!$B$3:$BI$3,">="&21,'31_P&L'!$B$3:$BI$3,"<="&23) -> 0 | K12: =SUMIFS('31_P&L'!$B$10:$BI$10,'31_P&L'!$B$3:$BI$3,">="&24,'31_P&L'!$B$3:$BI$3,"<="&26) -> 0 | L12: =SUMIFS('31_P&L'!$B$10:$BI$10,'31_P&L'!$B$3:$BI$3,">="&27,'31_P&L'!$B$3:$BI$3,"<="&29) -> 0 | M12: =SUMIFS('31_P&L'!$B$10:$BI$10,'31_P&L'!$B$3:$BI$3,">="&30,'31_P&L'!$B$3:$BI$3,"<="&32) -> 0 | N12: =SUMIFS('31_P&L'!$B$10:$BI$10,'31_P&L'!$B$3:$BI$3,">="&33,'31_P&L'!$B$3:$BI$3,"<="&35) -> 1183546 | O12: =SUMIFS('31_P&L'!$B$10:$BI$10,'31_P&L'!$B$3:$BI$3,">="&36,'31_P&L'!$B$3:$BI$3,"<="&38) -> 0 | P12: =SUMIFS('31_P&L'!$B$10:$BI$10,'31_P&L'!$B$3:$BI$3,">="&39,'31_P&L'!$B$3:$BI$3,"<="&41) -> 0 | Q12: =SUMIFS('31_P&L'!$B$10:$BI$10,'31_P&L'!$B$3:$BI$3,">="&42,'31_P&L'!$B$3:$BI$3,"<="&44) -> 0 | R12: =SUMIFS('31_P&L'!$B$10:$BI$10,'31_P&L'!$B$3:$BI$3,">="&45,'31_P&L'!$B$3:$BI$3,"<="&47) -> 0 | S12: =SUMIFS('31_P&L'!$B$10:$BI$10,'31_P&L'!$B$3:$BI$3,">="&48,'31_P&L'!$B$3:$BI$3,"<="&50) -> 0 | T12: =SUMIFS('31_P&L'!$B$10:$BI$10,'31_P&L'!$B$3:$BI$3,">="&51,'31_P&L'!$B$3:$BI$3,"<="&53) -> 0 | U12: =SUMIFS('31_P&L'!$B$10:$BI$10,'31_P&L'!$B$3:$BI$3,">="&54,'31_P&L'!$B$3:$BI$3,"<="&56) -> 0 | V12: =SUMIFS('31_P&L'!$B$10:$BI$10,'31_P&L'!$B$3:$BI$3,">="&57,'31_P&L'!$B$3:$BI$3,"<="&59) -> 0
A13: Coste de ventas — construcción | C13: =SUMIFS('31_P&L'!$B$11:$BI$11,'31_P&L'!$B$3:$BI$3,">="&0,'31_P&L'!$B$3:$BI$3,"<="&2) -> 0 | D13: =SUMIFS('31_P&L'!$B$11:$BI$11,'31_P&L'!$B$3:$BI$3,">="&3,'31_P&L'!$B$3:$BI$3,"<="&5) -> 0 | E13: =SUMIFS('31_P&L'!$B$11:$BI$11,'31_P&L'!$B$3:$BI$3,">="&6,'31_P&L'!$B$3:$BI$3,"<="&8) -> 0 | F13: =SUMIFS('31_P&L'!$B$11:$BI$11,'31_P&L'!$B$3:$BI$3,">="&9,'31_P&L'!$B$3:$BI$3,"<="&11) -> 0 | G13: =SUMIFS('31_P&L'!$B$11:$BI$11,'31_P&L'!$B$3:$BI$3,">="&12,'31_P&L'!$B$3:$BI$3,"<="&14) -> 0 | H13: =SUMIFS('31_P&L'!$B$11:$BI$11,'31_P&L'!$B$3:$BI$3,">="&15,'31_P&L'!$B$3:$BI$3,"<="&17) -> 0 | I13: =SUMIFS('31_P&L'!$B$11:$BI$11,'31_P&L'!$B$3:$BI$3,">="&18,'31_P&L'!$B$3:$BI$3,"<="&20) -> 0 | J13: =SUMIFS('31_P&L'!$B$11:$BI$11,'31_P&L'!$B$3:$BI$3,">="&21,'31_P&L'!$B$3:$BI$3,"<="&23) -> 0 | K13: =SUMIFS('31_P&L'!$B$11:$BI$11,'31_P&L'!$B$3:$BI$3,">="&24,'31_P&L'!$B$3:$BI$3,"<="&26) -> 0 | L13: =SUMIFS('31_P&L'!$B$11:$BI$11,'31_P&L'!$B$3:$BI$3,">="&27,'31_P&L'!$B$3:$BI$3,"<="&29) -> 0 | M13: =SUMIFS('31_P&L'!$B$11:$BI$11,'31_P&L'!$B$3:$BI$3,">="&30,'31_P&L'!$B$3:$BI$3,"<="&32) -> 0 | N13: =SUMIFS('31_P&L'!$B$11:$BI$11,'31_P&L'!$B$3:$BI$3,">="&33,'31_P&L'!$B$3:$BI$3,"<="&35) -> 6472327.7 | O13: =SUMIFS('31_P&L'!$B$11:$BI$11,'31_P&L'!$B$3:$BI$3,">="&36,'31_P&L'!$B$3:$BI$3,"<="&38) -> 0 | P13: =SUMIFS('31_P&L'!$B$11:$BI$11,'31_P&L'!$B$3:$BI$3,">="&39,'31_P&L'!$B$3:$BI$3,"<="&41) -> 0 | Q13: =SUMIFS('31_P&L'!$B$11:$BI$11,'31_P&L'!$B$3:$BI$3,">="&42,'31_P&L'!$B$3:$BI$3,"<="&44) -> 0 | R13: =SUMIFS('31_P&L'!$B$11:$BI$11,'31_P&L'!$B$3:$BI$3,">="&45,'31_P&L'!$B$3:$BI$3,"<="&47) -> 0 | S13: =SUMIFS('31_P&L'!$B$11:$BI$11,'31_P&L'!$B$3:$BI$3,">="&48,'31_P&L'!$B$3:$BI$3,"<="&50) -> 0 | T13: =SUMIFS('31_P&L'!$B$11:$BI$11,'31_P&L'!$B$3:$BI$3,">="&51,'31_P&L'!$B$3:$BI$3,"<="&53) -> 0 | U13: =SUMIFS('31_P&L'!$B$11:$BI$11,'31_P&L'!$B$3:$BI$3,">="&54,'31_P&L'!$B$3:$BI$3,"<="&56) -> 0 | V13: =SUMIFS('31_P&L'!$B$11:$BI$11,'31_P&L'!$B$3:$BI$3,">="&57,'31_P&L'!$B$3:$BI$3,"<="&59) -> 0
A14: Coste de ventas — intereses capitalizados | C14: =SUMIFS('31_P&L'!$B$12:$BI$12,'31_P&L'!$B$3:$BI$3,">="&0,'31_P&L'!$B$3:$BI$3,"<="&2) -> 0 | D14: =SUMIFS('31_P&L'!$B$12:$BI$12,'31_P&L'!$B$3:$BI$3,">="&3,'31_P&L'!$B$3:$BI$3,"<="&5) -> 0 | E14: =SUMIFS('31_P&L'!$B$12:$BI$12,'31_P&L'!$B$3:$BI$3,">="&6,'31_P&L'!$B$3:$BI$3,"<="&8) -> 0 | F14: =SUMIFS('31_P&L'!$B$12:$BI$12,'31_P&L'!$B$3:$BI$3,">="&9,'31_P&L'!$B$3:$BI$3,"<="&11) -> 0 | G14: =SUMIFS('31_P&L'!$B$12:$BI$12,'31_P&L'!$B$3:$BI$3,">="&12,'31_P&L'!$B$3:$BI$3,"<="&14) -> 0 | H14: =SUMIFS('31_P&L'!$B$12:$BI$12,'31_P&L'!$B$3:$BI$3,">="&15,'31_P&L'!$B$3:$BI$3,"<="&17) -> 0 | I14: =SUMIFS('31_P&L'!$B$12:$BI$12,'31_P&L'!$B$3:$BI$3,">="&18,'31_P&L'!$B$3:$BI$3,"<="&20) -> 0 | J14: =SUMIFS('31_P&L'!$B$12:$BI$12,'31_P&L'!$B$3:$BI$3,">="&21,'31_P&L'!$B$3:$BI$3,"<="&23) -> 0 | K14: =SUMIFS('31_P&L'!$B$12:$BI$12,'31_P&L'!$B$3:$BI$3,">="&24,'31_P&L'!$B$3:$BI$3,"<="&26) -> 0 | L14: =SUMIFS('31_P&L'!$B$12:$BI$12,'31_P&L'!$B$3:$BI$3,">="&27,'31_P&L'!$B$3:$BI$3,"<="&29) -> 0 | M14: =SUMIFS('31_P&L'!$B$12:$BI$12,'31_P&L'!$B$3:$BI$3,">="&30,'31_P&L'!$B$3:$BI$3,"<="&32) -> 0 | N14: =SUMIFS('31_P&L'!$B$12:$BI$12,'31_P&L'!$B$3:$BI$3,">="&33,'31_P&L'!$B$3:$BI$3,"<="&35) -> 324306.06 | O14: =SUMIFS('31_P&L'!$B$12:$BI$12,'31_P&L'!$B$3:$BI$3,">="&36,'31_P&L'!$B$3:$BI$3,"<="&38) -> 0 | P14: =SUMIFS('31_P&L'!$B$12:$BI$12,'31_P&L'!$B$3:$BI$3,">="&39,'31_P&L'!$B$3:$BI$3,"<="&41) -> 0 | Q14: =SUMIFS('31_P&L'!$B$12:$BI$12,'31_P&L'!$B$3:$BI$3,">="&42,'31_P&L'!$B$3:$BI$3,"<="&44) -> 0 | R14: =SUMIFS('31_P&L'!$B$12:$BI$12,'31_P&L'!$B$3:$BI$3,">="&45,'31_P&L'!$B$3:$BI$3,"<="&47) -> 0 | S14: =SUMIFS('31_P&L'!$B$12:$BI$12,'31_P&L'!$B$3:$BI$3,">="&48,'31_P&L'!$B$3:$BI$3,"<="&50) -> 0 | T14: =SUMIFS('31_P&L'!$B$12:$BI$12,'31_P&L'!$B$3:$BI$3,">="&51,'31_P&L'!$B$3:$BI$3,"<="&53) -> 0 | U14: =SUMIFS('31_P&L'!$B$12:$BI$12,'31_P&L'!$B$3:$BI$3,">="&54,'31_P&L'!$B$3:$BI$3,"<="&56) -> 0 | V14: =SUMIFS('31_P&L'!$B$12:$BI$12,'31_P&L'!$B$3:$BI$3,">="&57,'31_P&L'!$B$3:$BI$3,"<="&59) -> 0
A15: Coste comercialización | C15: =SUMIFS('31_P&L'!$B$13:$BI$13,'31_P&L'!$B$3:$BI$3,">="&0,'31_P&L'!$B$3:$BI$3,"<="&2) -> 0 | D15: =SUMIFS('31_P&L'!$B$13:$BI$13,'31_P&L'!$B$3:$BI$3,">="&3,'31_P&L'!$B$3:$BI$3,"<="&5) -> 0 | E15: =SUMIFS('31_P&L'!$B$13:$BI$13,'31_P&L'!$B$3:$BI$3,">="&6,'31_P&L'!$B$3:$BI$3,"<="&8) -> 0 | F15: =SUMIFS('31_P&L'!$B$13:$BI$13,'31_P&L'!$B$3:$BI$3,">="&9,'31_P&L'!$B$3:$BI$3,"<="&11) -> 0 | G15: =SUMIFS('31_P&L'!$B$13:$BI$13,'31_P&L'!$B$3:$BI$3,">="&12,'31_P&L'!$B$3:$BI$3,"<="&14) -> 0 | H15: =SUMIFS('31_P&L'!$B$13:$BI$13,'31_P&L'!$B$3:$BI$3,">="&15,'31_P&L'!$B$3:$BI$3,"<="&17) -> 0 | I15: =SUMIFS('31_P&L'!$B$13:$BI$13,'31_P&L'!$B$3:$BI$3,">="&18,'31_P&L'!$B$3:$BI$3,"<="&20) -> 0 | J15: =SUMIFS('31_P&L'!$B$13:$BI$13,'31_P&L'!$B$3:$BI$3,">="&21,'31_P&L'!$B$3:$BI$3,"<="&23) -> 26812.5 | K15: =SUMIFS('31_P&L'!$B$13:$BI$13,'31_P&L'!$B$3:$BI$3,">="&24,'31_P&L'!$B$3:$BI$3,"<="&26) -> 80437.5 | L15: =SUMIFS('31_P&L'!$B$13:$BI$13,'31_P&L'!$B$3:$BI$3,">="&27,'31_P&L'!$B$3:$BI$3,"<="&29) -> 80437.5 | M15: =SUMIFS('31_P&L'!$B$13:$BI$13,'31_P&L'!$B$3:$BI$3,">="&30,'31_P&L'!$B$3:$BI$3,"<="&32) -> 80437.5 | N15: =SUMIFS('31_P&L'!$B$13:$BI$13,'31_P&L'!$B$3:$BI$3,">="&33,'31_P&L'!$B$3:$BI$3,"<="&35) -> 10725 | O15: =SUMIFS('31_P&L'!$B$13:$BI$13,'31_P&L'!$B$3:$BI$3,">="&36,'31_P&L'!$B$3:$BI$3,"<="&38) -> 0 | P15: =SUMIFS('31_P&L'!$B$13:$BI$13,'31_P&L'!$B$3:$BI$3,">="&39,'31_P&L'!$B$3:$BI$3,"<="&41) -> 0 | Q15: =SUMIFS('31_P&L'!$B$13:$BI$13,'31_P&L'!$B$3:$BI$3,">="&42,'31_P&L'!$B$3:$BI$3,"<="&44) -> 0 | R15: =SUMIFS('31_P&L'!$B$13:$BI$13,'31_P&L'!$B$3:$BI$3,">="&45,'31_P&L'!$B$3:$BI$3,"<="&47) -> 0 | S15: =SUMIFS('31_P&L'!$B$13:$BI$13,'31_P&L'!$B$3:$BI$3,">="&48,'31_P&L'!$B$3:$BI$3,"<="&50) -> 0 | T15: =SUMIFS('31_P&L'!$B$13:$BI$13,'31_P&L'!$B$3:$BI$3,">="&51,'31_P&L'!$B$3:$BI$3,"<="&53) -> 0 | U15: =SUMIFS('31_P&L'!$B$13:$BI$13,'31_P&L'!$B$3:$BI$3,">="&54,'31_P&L'!$B$3:$BI$3,"<="&56) -> 0 | V15: =SUMIFS('31_P&L'!$B$13:$BI$13,'31_P&L'!$B$3:$BI$3,">="&57,'31_P&L'!$B$3:$BI$3,"<="&59) -> 0
A16: TOTAL COSTES OPERATIVOS | C16: =SUMIFS('31_P&L'!$B$14:$BI$14,'31_P&L'!$B$3:$BI$3,">="&0,'31_P&L'!$B$3:$BI$3,"<="&2) -> 0 | D16: =SUMIFS('31_P&L'!$B$14:$BI$14,'31_P&L'!$B$3:$BI$3,">="&3,'31_P&L'!$B$3:$BI$3,"<="&5) -> 0 | E16: =SUMIFS('31_P&L'!$B$14:$BI$14,'31_P&L'!$B$3:$BI$3,">="&6,'31_P&L'!$B$3:$BI$3,"<="&8) -> 0 | F16: =SUMIFS('31_P&L'!$B$14:$BI$14,'31_P&L'!$B$3:$BI$3,">="&9,'31_P&L'!$B$3:$BI$3,"<="&11) -> 0 | G16: =SUMIFS('31_P&L'!$B$14:$BI$14,'31_P&L'!$B$3:$BI$3,">="&12,'31_P&L'!$B$3:$BI$3,"<="&14) -> 0 | H16: =SUMIFS('31_P&L'!$B$14:$BI$14,'31_P&L'!$B$3:$BI$3,">="&15,'31_P&L'!$B$3:$BI$3,"<="&17) -> 0 | I16: =SUMIFS('31_P&L'!$B$14:$BI$14,'31_P&L'!$B$3:$BI$3,">="&18,'31_P&L'!$B$3:$BI$3,"<="&20) -> 0 | J16: =SUMIFS('31_P&L'!$B$14:$BI$14,'31_P&L'!$B$3:$BI$3,">="&21,'31_P&L'!$B$3:$BI$3,"<="&23) -> 26812.5 | K16: =SUMIFS('31_P&L'!$B$14:$BI$14,'31_P&L'!$B$3:$BI$3,">="&24,'31_P&L'!$B$3:$BI$3,"<="&26) -> 80437.5 | L16: =SUMIFS('31_P&L'!$B$14:$BI$14,'31_P&L'!$B$3:$BI$3,">="&27,'31_P&L'!$B$3:$BI$3,"<="&29) -> 80437.5 | M16: =SUMIFS('31_P&L'!$B$14:$BI$14,'31_P&L'!$B$3:$BI$3,">="&30,'31_P&L'!$B$3:$BI$3,"<="&32) -> 80437.5 | N16: =SUMIFS('31_P&L'!$B$14:$BI$14,'31_P&L'!$B$3:$BI$3,">="&33,'31_P&L'!$B$3:$BI$3,"<="&35) -> 7990904.7 | O16: =SUMIFS('31_P&L'!$B$14:$BI$14,'31_P&L'!$B$3:$BI$3,">="&36,'31_P&L'!$B$3:$BI$3,"<="&38) -> 0 | P16: =SUMIFS('31_P&L'!$B$14:$BI$14,'31_P&L'!$B$3:$BI$3,">="&39,'31_P&L'!$B$3:$BI$3,"<="&41) -> 0 | Q16: =SUMIFS('31_P&L'!$B$14:$BI$14,'31_P&L'!$B$3:$BI$3,">="&42,'31_P&L'!$B$3:$BI$3,"<="&44) -> 0 | R16: =SUMIFS('31_P&L'!$B$14:$BI$14,'31_P&L'!$B$3:$BI$3,">="&45,'31_P&L'!$B$3:$BI$3,"<="&47) -> 0 | S16: =SUMIFS('31_P&L'!$B$14:$BI$14,'31_P&L'!$B$3:$BI$3,">="&48,'31_P&L'!$B$3:$BI$3,"<="&50) -> 0 | T16: =SUMIFS('31_P&L'!$B$14:$BI$14,'31_P&L'!$B$3:$BI$3,">="&51,'31_P&L'!$B$3:$BI$3,"<="&53) -> 0 | U16: =SUMIFS('31_P&L'!$B$14:$BI$14,'31_P&L'!$B$3:$BI$3,">="&54,'31_P&L'!$B$3:$BI$3,"<="&56) -> 0 | V16: =SUMIFS('31_P&L'!$B$14:$BI$14,'31_P&L'!$B$3:$BI$3,">="&57,'31_P&L'!$B$3:$BI$3,"<="&59) -> 0
A18: EBITDA | C18: =SUMIFS('31_P&L'!$B$16:$BI$16,'31_P&L'!$B$3:$BI$3,">="&0,'31_P&L'!$B$3:$BI$3,"<="&2) -> 0 | D18: =SUMIFS('31_P&L'!$B$16:$BI$16,'31_P&L'!$B$3:$BI$3,">="&3,'31_P&L'!$B$3:$BI$3,"<="&5) -> 0 | E18: =SUMIFS('31_P&L'!$B$16:$BI$16,'31_P&L'!$B$3:$BI$3,">="&6,'31_P&L'!$B$3:$BI$3,"<="&8) -> 0 | F18: =SUMIFS('31_P&L'!$B$16:$BI$16,'31_P&L'!$B$3:$BI$3,">="&9,'31_P&L'!$B$3:$BI$3,"<="&11) -> 0 | G18: =SUMIFS('31_P&L'!$B$16:$BI$16,'31_P&L'!$B$3:$BI$3,">="&12,'31_P&L'!$B$3:$BI$3,"<="&14) -> 0 | H18: =SUMIFS('31_P&L'!$B$16:$BI$16,'31_P&L'!$B$3:$BI$3,">="&15,'31_P&L'!$B$3:$BI$3,"<="&17) -> 0 | I18: =SUMIFS('31_P&L'!$B$16:$BI$16,'31_P&L'!$B$3:$BI$3,">="&18,'31_P&L'!$B$3:$BI$3,"<="&20) -> 0 | J18: =SUMIFS('31_P&L'!$B$16:$BI$16,'31_P&L'!$B$3:$BI$3,">="&21,'31_P&L'!$B$3:$BI$3,"<="&23) -> -26812.5 | K18: =SUMIFS('31_P&L'!$B$16:$BI$16,'31_P&L'!$B$3:$BI$3,">="&24,'31_P&L'!$B$3:$BI$3,"<="&26) -> -80437.5 | L18: =SUMIFS('31_P&L'!$B$16:$BI$16,'31_P&L'!$B$3:$BI$3,">="&27,'31_P&L'!$B$3:$BI$3,"<="&29) -> -80437.5 | M18: =SUMIFS('31_P&L'!$B$16:$BI$16,'31_P&L'!$B$3:$BI$3,">="&30,'31_P&L'!$B$3:$BI$3,"<="&32) -> -80437.5 | N18: =SUMIFS('31_P&L'!$B$16:$BI$16,'31_P&L'!$B$3:$BI$3,">="&33,'31_P&L'!$B$3:$BI$3,"<="&35) -> 1304095.3 | O18: =SUMIFS('31_P&L'!$B$16:$BI$16,'31_P&L'!$B$3:$BI$3,">="&36,'31_P&L'!$B$3:$BI$3,"<="&38) -> 0 | P18: =SUMIFS('31_P&L'!$B$16:$BI$16,'31_P&L'!$B$3:$BI$3,">="&39,'31_P&L'!$B$3:$BI$3,"<="&41) -> 0 | Q18: =SUMIFS('31_P&L'!$B$16:$BI$16,'31_P&L'!$B$3:$BI$3,">="&42,'31_P&L'!$B$3:$BI$3,"<="&44) -> 0 | R18: =SUMIFS('31_P&L'!$B$16:$BI$16,'31_P&L'!$B$3:$BI$3,">="&45,'31_P&L'!$B$3:$BI$3,"<="&47) -> 0 | S18: =SUMIFS('31_P&L'!$B$16:$BI$16,'31_P&L'!$B$3:$BI$3,">="&48,'31_P&L'!$B$3:$BI$3,"<="&50) -> 0 | T18: =SUMIFS('31_P&L'!$B$16:$BI$16,'31_P&L'!$B$3:$BI$3,">="&51,'31_P&L'!$B$3:$BI$3,"<="&53) -> 0 | U18: =SUMIFS('31_P&L'!$B$16:$BI$16,'31_P&L'!$B$3:$BI$3,">="&54,'31_P&L'!$B$3:$BI$3,"<="&56) -> 0 | V18: =SUMIFS('31_P&L'!$B$16:$BI$16,'31_P&L'!$B$3:$BI$3,">="&57,'31_P&L'!$B$3:$BI$3,"<="&59) -> 0
A20: RESULTADO FINANCIERO
A21: Intereses no capitalizados / pagados | C21: =SUMIFS('31_P&L'!$B$19:$BI$19,'31_P&L'!$B$3:$BI$3,">="&0,'31_P&L'!$B$3:$BI$3,"<="&2) -> 0 | D21: =SUMIFS('31_P&L'!$B$19:$BI$19,'31_P&L'!$B$3:$BI$3,">="&3,'31_P&L'!$B$3:$BI$3,"<="&5) -> 0 | E21: =SUMIFS('31_P&L'!$B$19:$BI$19,'31_P&L'!$B$3:$BI$3,">="&6,'31_P&L'!$B$3:$BI$3,"<="&8) -> 0 | F21: =SUMIFS('31_P&L'!$B$19:$BI$19,'31_P&L'!$B$3:$BI$3,">="&9,'31_P&L'!$B$3:$BI$3,"<="&11) -> 0 | G21: =SUMIFS('31_P&L'!$B$19:$BI$19,'31_P&L'!$B$3:$BI$3,">="&12,'31_P&L'!$B$3:$BI$3,"<="&14) -> 0 | H21: =SUMIFS('31_P&L'!$B$19:$BI$19,'31_P&L'!$B$3:$BI$3,">="&15,'31_P&L'!$B$3:$BI$3,"<="&17) -> 0 | I21: =SUMIFS('31_P&L'!$B$19:$BI$19,'31_P&L'!$B$3:$BI$3,">="&18,'31_P&L'!$B$3:$BI$3,"<="&20) -> 0 | J21: =SUMIFS('31_P&L'!$B$19:$BI$19,'31_P&L'!$B$3:$BI$3,">="&21,'31_P&L'!$B$3:$BI$3,"<="&23) -> 0 | K21: =SUMIFS('31_P&L'!$B$19:$BI$19,'31_P&L'!$B$3:$BI$3,">="&24,'31_P&L'!$B$3:$BI$3,"<="&26) -> 0 | L21: =SUMIFS('31_P&L'!$B$19:$BI$19,'31_P&L'!$B$3:$BI$3,">="&27,'31_P&L'!$B$3:$BI$3,"<="&29) -> 0 | M21: =SUMIFS('31_P&L'!$B$19:$BI$19,'31_P&L'!$B$3:$BI$3,">="&30,'31_P&L'!$B$3:$BI$3,"<="&32) -> 0 | N21: =SUMIFS('31_P&L'!$B$19:$BI$19,'31_P&L'!$B$3:$BI$3,">="&33,'31_P&L'!$B$3:$BI$3,"<="&35) -> 20768.546 | O21: =SUMIFS('31_P&L'!$B$19:$BI$19,'31_P&L'!$B$3:$BI$3,">="&36,'31_P&L'!$B$3:$BI$3,"<="&38) -> 0 | P21: =SUMIFS('31_P&L'!$B$19:$BI$19,'31_P&L'!$B$3:$BI$3,">="&39,'31_P&L'!$B$3:$BI$3,"<="&41) -> 0 | Q21: =SUMIFS('31_P&L'!$B$19:$BI$19,'31_P&L'!$B$3:$BI$3,">="&42,'31_P&L'!$B$3:$BI$3,"<="&44) -> 0 | R21: =SUMIFS('31_P&L'!$B$19:$BI$19,'31_P&L'!$B$3:$BI$3,">="&45,'31_P&L'!$B$3:$BI$3,"<="&47) -> 0 | S21: =SUMIFS('31_P&L'!$B$19:$BI$19,'31_P&L'!$B$3:$BI$3,">="&48,'31_P&L'!$B$3:$BI$3,"<="&50) -> 0 | T21: =SUMIFS('31_P&L'!$B$19:$BI$19,'31_P&L'!$B$3:$BI$3,">="&51,'31_P&L'!$B$3:$BI$3,"<="&53) -> 0 | U21: =SUMIFS('31_P&L'!$B$19:$BI$19,'31_P&L'!$B$3:$BI$3,">="&54,'31_P&L'!$B$3:$BI$3,"<="&56) -> 0 | V21: =SUMIFS('31_P&L'!$B$19:$BI$19,'31_P&L'!$B$3:$BI$3,">="&57,'31_P&L'!$B$3:$BI$3,"<="&59) -> 0
A22: Comisiones financieras | C22: =SUMIFS('31_P&L'!$B$20:$BI$20,'31_P&L'!$B$3:$BI$3,">="&0,'31_P&L'!$B$3:$BI$3,"<="&2) -> 0 | D22: =SUMIFS('31_P&L'!$B$20:$BI$20,'31_P&L'!$B$3:$BI$3,">="&3,'31_P&L'!$B$3:$BI$3,"<="&5) -> 0 | E22: =SUMIFS('31_P&L'!$B$20:$BI$20,'31_P&L'!$B$3:$BI$3,">="&6,'31_P&L'!$B$3:$BI$3,"<="&8) -> 0 | F22: =SUMIFS('31_P&L'!$B$20:$BI$20,'31_P&L'!$B$3:$BI$3,">="&9,'31_P&L'!$B$3:$BI$3,"<="&11) -> 33305.52 | G22: =SUMIFS('31_P&L'!$B$20:$BI$20,'31_P&L'!$B$3:$BI$3,">="&12,'31_P&L'!$B$3:$BI$3,"<="&14) -> 4584.5654 | H22: =SUMIFS('31_P&L'!$B$20:$BI$20,'31_P&L'!$B$3:$BI$3,">="&15,'31_P&L'!$B$3:$BI$3,"<="&17) -> 3573.2642 | I22: =SUMIFS('31_P&L'!$B$20:$BI$20,'31_P&L'!$B$3:$BI$3,">="&18,'31_P&L'!$B$3:$BI$3,"<="&20) -> 2561.963 | J22: =SUMIFS('31_P&L'!$B$20:$BI$20,'31_P&L'!$B$3:$BI$3,">="&21,'31_P&L'!$B$3:$BI$3,"<="&23) -> 1550.6618 | K22: =SUMIFS('31_P&L'!$B$20:$BI$20,'31_P&L'!$B$3:$BI$3,">="&24,'31_P&L'!$B$3:$BI$3,"<="&26) -> 539.36064 | L22: =SUMIFS('31_P&L'!$B$20:$BI$20,'31_P&L'!$B$3:$BI$3,">="&27,'31_P&L'!$B$3:$BI$3,"<="&29) -> 0 | M22: =SUMIFS('31_P&L'!$B$20:$BI$20,'31_P&L'!$B$3:$BI$3,">="&30,'31_P&L'!$B$3:$BI$3,"<="&32) -> 0 | N22: =SUMIFS('31_P&L'!$B$20:$BI$20,'31_P&L'!$B$3:$BI$3,">="&33,'31_P&L'!$B$3:$BI$3,"<="&35) -> 0 | O22: =SUMIFS('31_P&L'!$B$20:$BI$20,'31_P&L'!$B$3:$BI$3,">="&36,'31_P&L'!$B$3:$BI$3,"<="&38) -> 0 | P22: =SUMIFS('31_P&L'!$B$20:$BI$20,'31_P&L'!$B$3:$BI$3,">="&39,'31_P&L'!$B$3:$BI$3,"<="&41) -> 0 | Q22: =SUMIFS('31_P&L'!$B$20:$BI$20,'31_P&L'!$B$3:$BI$3,">="&42,'31_P&L'!$B$3:$BI$3,"<="&44) -> 0 | R22: =SUMIFS('31_P&L'!$B$20:$BI$20,'31_P&L'!$B$3:$BI$3,">="&45,'31_P&L'!$B$3:$BI$3,"<="&47) -> 0 | S22: =SUMIFS('31_P&L'!$B$20:$BI$20,'31_P&L'!$B$3:$BI$3,">="&48,'31_P&L'!$B$3:$BI$3,"<="&50) -> 0 | T22: =SUMIFS('31_P&L'!$B$20:$BI$20,'31_P&L'!$B$3:$BI$3,">="&51,'31_P&L'!$B$3:$BI$3,"<="&53) -> 0 | U22: =SUMIFS('31_P&L'!$B$20:$BI$20,'31_P&L'!$B$3:$BI$3,">="&54,'31_P&L'!$B$3:$BI$3,"<="&56) -> 0 | V22: =SUMIFS('31_P&L'!$B$20:$BI$20,'31_P&L'!$B$3:$BI$3,">="&57,'31_P&L'!$B$3:$BI$3,"<="&59) -> 0
A23: TOTAL GASTO FINANCIERO | C23: =SUMIFS('31_P&L'!$B$21:$BI$21,'31_P&L'!$B$3:$BI$3,">="&0,'31_P&L'!$B$3:$BI$3,"<="&2) -> 0 | D23: =SUMIFS('31_P&L'!$B$21:$BI$21,'31_P&L'!$B$3:$BI$3,">="&3,'31_P&L'!$B$3:$BI$3,"<="&5) -> 0 | E23: =SUMIFS('31_P&L'!$B$21:$BI$21,'31_P&L'!$B$3:$BI$3,">="&6,'31_P&L'!$B$3:$BI$3,"<="&8) -> 0 | F23: =SUMIFS('31_P&L'!$B$21:$BI$21,'31_P&L'!$B$3:$BI$3,">="&9,'31_P&L'!$B$3:$BI$3,"<="&11) -> 33305.52 | G23: =SUMIFS('31_P&L'!$B$21:$BI$21,'31_P&L'!$B$3:$BI$3,">="&12,'31_P&L'!$B$3:$BI$3,"<="&14) -> 4584.5654 | H23: =SUMIFS('31_P&L'!$B$21:$BI$21,'31_P&L'!$B$3:$BI$3,">="&15,'31_P&L'!$B$3:$BI$3,"<="&17) -> 3573.2642 | I23: =SUMIFS('31_P&L'!$B$21:$BI$21,'31_P&L'!$B$3:$BI$3,">="&18,'31_P&L'!$B$3:$BI$3,"<="&20) -> 2561.963 | J23: =SUMIFS('31_P&L'!$B$21:$BI$21,'31_P&L'!$B$3:$BI$3,">="&21,'31_P&L'!$B$3:$BI$3,"<="&23) -> 1550.6618 | K23: =SUMIFS('31_P&L'!$B$21:$BI$21,'31_P&L'!$B$3:$BI$3,">="&24,'31_P&L'!$B$3:$BI$3,"<="&26) -> 539.36064 | L23: =SUMIFS('31_P&L'!$B$21:$BI$21,'31_P&L'!$B$3:$BI$3,">="&27,'31_P&L'!$B$3:$BI$3,"<="&29) -> 0 | M23: =SUMIFS('31_P&L'!$B$21:$BI$21,'31_P&L'!$B$3:$BI$3,">="&30,'31_P&L'!$B$3:$BI$3,"<="&32) -> 0 | N23: =SUMIFS('31_P&L'!$B$21:$BI$21,'31_P&L'!$B$3:$BI$3,">="&33,'31_P&L'!$B$3:$BI$3,"<="&35) -> 20768.546 | O23: =SUMIFS('31_P&L'!$B$21:$BI$21,'31_P&L'!$B$3:$BI$3,">="&36,'31_P&L'!$B$3:$BI$3,"<="&38) -> 0 | P23: =SUMIFS('31_P&L'!$B$21:$BI$21,'31_P&L'!$B$3:$BI$3,">="&39,'31_P&L'!$B$3:$BI$3,"<="&41) -> 0 | Q23: =SUMIFS('31_P&L'!$B$21:$BI$21,'31_P&L'!$B$3:$BI$3,">="&42,'31_P&L'!$B$3:$BI$3,"<="&44) -> 0 | R23: =SUMIFS('31_P&L'!$B$21:$BI$21,'31_P&L'!$B$3:$BI$3,">="&45,'31_P&L'!$B$3:$BI$3,"<="&47) -> 0 | S23: =SUMIFS('31_P&L'!$B$21:$BI$21,'31_P&L'!$B$3:$BI$3,">="&48,'31_P&L'!$B$3:$BI$3,"<="&50) -> 0 | T23: =SUMIFS('31_P&L'!$B$21:$BI$21,'31_P&L'!$B$3:$BI$3,">="&51,'31_P&L'!$B$3:$BI$3,"<="&53) -> 0 | U23: =SUMIFS('31_P&L'!$B$21:$BI$21,'31_P&L'!$B$3:$BI$3,">="&54,'31_P&L'!$B$3:$BI$3,"<="&56) -> 0 | V23: =SUMIFS('31_P&L'!$B$21:$BI$21,'31_P&L'!$B$3:$BI$3,">="&57,'31_P&L'!$B$3:$BI$3,"<="&59) -> 0
A25: RESULTADO ANTES DE IMPUESTOS | C25: =SUMIFS('31_P&L'!$B$23:$BI$23,'31_P&L'!$B$3:$BI$3,">="&0,'31_P&L'!$B$3:$BI$3,"<="&2) -> 0 | D25: =SUMIFS('31_P&L'!$B$23:$BI$23,'31_P&L'!$B$3:$BI$3,">="&3,'31_P&L'!$B$3:$BI$3,"<="&5) -> 0 | E25: =SUMIFS('31_P&L'!$B$23:$BI$23,'31_P&L'!$B$3:$BI$3,">="&6,'31_P&L'!$B$3:$BI$3,"<="&8) -> 0 | F25: =SUMIFS('31_P&L'!$B$23:$BI$23,'31_P&L'!$B$3:$BI$3,">="&9,'31_P&L'!$B$3:$BI$3,"<="&11) -> -33305.52 | G25: =SUMIFS('31_P&L'!$B$23:$BI$23,'31_P&L'!$B$3:$BI$3,">="&12,'31_P&L'!$B$3:$BI$3,"<="&14) -> -4584.5654 | H25: =SUMIFS('31_P&L'!$B$23:$BI$23,'31_P&L'!$B$3:$BI$3,">="&15,'31_P&L'!$B$3:$BI$3,"<="&17) -> -3573.2642 | I25: =SUMIFS('31_P&L'!$B$23:$BI$23,'31_P&L'!$B$3:$BI$3,">="&18,'31_P&L'!$B$3:$BI$3,"<="&20) -> -2561.963 | J25: =SUMIFS('31_P&L'!$B$23:$BI$23,'31_P&L'!$B$3:$BI$3,">="&21,'31_P&L'!$B$3:$BI$3,"<="&23) -> -28363.162 | K25: =SUMIFS('31_P&L'!$B$23:$BI$23,'31_P&L'!$B$3:$BI$3,">="&24,'31_P&L'!$B$3:$BI$3,"<="&26) -> -80976.861 | L25: =SUMIFS('31_P&L'!$B$23:$BI$23,'31_P&L'!$B$3:$BI$3,">="&27,'31_P&L'!$B$3:$BI$3,"<="&29) -> -80437.5 | M25: =SUMIFS('31_P&L'!$B$23:$BI$23,'31_P&L'!$B$3:$BI$3,">="&30,'31_P&L'!$B$3:$BI$3,"<="&32) -> -80437.5 | N25: =SUMIFS('31_P&L'!$B$23:$BI$23,'31_P&L'!$B$3:$BI$3,">="&33,'31_P&L'!$B$3:$BI$3,"<="&35) -> 1283326.7 | O25: =SUMIFS('31_P&L'!$B$23:$BI$23,'31_P&L'!$B$3:$BI$3,">="&36,'31_P&L'!$B$3:$BI$3,"<="&38) -> 0 | P25: =SUMIFS('31_P&L'!$B$23:$BI$23,'31_P&L'!$B$3:$BI$3,">="&39,'31_P&L'!$B$3:$BI$3,"<="&41) -> 0 | Q25: =SUMIFS('31_P&L'!$B$23:$BI$23,'31_P&L'!$B$3:$BI$3,">="&42,'31_P&L'!$B$3:$BI$3,"<="&44) -> 0 | R25: =SUMIFS('31_P&L'!$B$23:$BI$23,'31_P&L'!$B$3:$BI$3,">="&45,'31_P&L'!$B$3:$BI$3,"<="&47) -> 0 | S25: =SUMIFS('31_P&L'!$B$23:$BI$23,'31_P&L'!$B$3:$BI$3,">="&48,'31_P&L'!$B$3:$BI$3,"<="&50) -> 0 | T25: =SUMIFS('31_P&L'!$B$23:$BI$23,'31_P&L'!$B$3:$BI$3,">="&51,'31_P&L'!$B$3:$BI$3,"<="&53) -> 0 | U25: =SUMIFS('31_P&L'!$B$23:$BI$23,'31_P&L'!$B$3:$BI$3,">="&54,'31_P&L'!$B$3:$BI$3,"<="&56) -> 0 | V25: =SUMIFS('31_P&L'!$B$23:$BI$23,'31_P&L'!$B$3:$BI$3,">="&57,'31_P&L'!$B$3:$BI$3,"<="&59) -> 0
A26: Impuesto sobre sociedades | C26: =SUMIFS('31_P&L'!$B$24:$BI$24,'31_P&L'!$B$3:$BI$3,">="&0,'31_P&L'!$B$3:$BI$3,"<="&2) -> 0 | D26: =SUMIFS('31_P&L'!$B$24:$BI$24,'31_P&L'!$B$3:$BI$3,">="&3,'31_P&L'!$B$3:$BI$3,"<="&5) -> 0 | E26: =SUMIFS('31_P&L'!$B$24:$BI$24,'31_P&L'!$B$3:$BI$3,">="&6,'31_P&L'!$B$3:$BI$3,"<="&8) -> 0 | F26: =SUMIFS('31_P&L'!$B$24:$BI$24,'31_P&L'!$B$3:$BI$3,">="&9,'31_P&L'!$B$3:$BI$3,"<="&11) -> 0 | G26: =SUMIFS('31_P&L'!$B$24:$BI$24,'31_P&L'!$B$3:$BI$3,">="&12,'31_P&L'!$B$3:$BI$3,"<="&14) -> 0 | H26: =SUMIFS('31_P&L'!$B$24:$BI$24,'31_P&L'!$B$3:$BI$3,">="&15,'31_P&L'!$B$3:$BI$3,"<="&17) -> 0 | I26: =SUMIFS('31_P&L'!$B$24:$BI$24,'31_P&L'!$B$3:$BI$3,">="&18,'31_P&L'!$B$3:$BI$3,"<="&20) -> 0 | J26: =SUMIFS('31_P&L'!$B$24:$BI$24,'31_P&L'!$B$3:$BI$3,">="&21,'31_P&L'!$B$3:$BI$3,"<="&23) -> 0 | K26: =SUMIFS('31_P&L'!$B$24:$BI$24,'31_P&L'!$B$3:$BI$3,">="&24,'31_P&L'!$B$3:$BI$3,"<="&26) -> 0 | L26: =SUMIFS('31_P&L'!$B$24:$BI$24,'31_P&L'!$B$3:$BI$3,">="&27,'31_P&L'!$B$3:$BI$3,"<="&29) -> 0 | M26: =SUMIFS('31_P&L'!$B$24:$BI$24,'31_P&L'!$B$3:$BI$3,">="&30,'31_P&L'!$B$3:$BI$3,"<="&32) -> 0 | N26: =SUMIFS('31_P&L'!$B$24:$BI$24,'31_P&L'!$B$3:$BI$3,">="&33,'31_P&L'!$B$3:$BI$3,"<="&35) -> 253800.43 | O26: =SUMIFS('31_P&L'!$B$24:$BI$24,'31_P&L'!$B$3:$BI$3,">="&36,'31_P&L'!$B$3:$BI$3,"<="&38) -> 0 | P26: =SUMIFS('31_P&L'!$B$24:$BI$24,'31_P&L'!$B$3:$BI$3,">="&39,'31_P&L'!$B$3:$BI$3,"<="&41) -> 0 | Q26: =SUMIFS('31_P&L'!$B$24:$BI$24,'31_P&L'!$B$3:$BI$3,">="&42,'31_P&L'!$B$3:$BI$3,"<="&44) -> 0 | R26: =SUMIFS('31_P&L'!$B$24:$BI$24,'31_P&L'!$B$3:$BI$3,">="&45,'31_P&L'!$B$3:$BI$3,"<="&47) -> 0 | S26: =SUMIFS('31_P&L'!$B$24:$BI$24,'31_P&L'!$B$3:$BI$3,">="&48,'31_P&L'!$B$3:$BI$3,"<="&50) -> 0 | T26: =SUMIFS('31_P&L'!$B$24:$BI$24,'31_P&L'!$B$3:$BI$3,">="&51,'31_P&L'!$B$3:$BI$3,"<="&53) -> 0 | U26: =SUMIFS('31_P&L'!$B$24:$BI$24,'31_P&L'!$B$3:$BI$3,">="&54,'31_P&L'!$B$3:$BI$3,"<="&56) -> 0 | V26: =SUMIFS('31_P&L'!$B$24:$BI$24,'31_P&L'!$B$3:$BI$3,">="&57,'31_P&L'!$B$3:$BI$3,"<="&59) -> 0
A27: RESULTADO NETO | C27: =SUMIFS('31_P&L'!$B$25:$BI$25,'31_P&L'!$B$3:$BI$3,">="&0,'31_P&L'!$B$3:$BI$3,"<="&2) -> 0 | D27: =SUMIFS('31_P&L'!$B$25:$BI$25,'31_P&L'!$B$3:$BI$3,">="&3,'31_P&L'!$B$3:$BI$3,"<="&5) -> 0 | E27: =SUMIFS('31_P&L'!$B$25:$BI$25,'31_P&L'!$B$3:$BI$3,">="&6,'31_P&L'!$B$3:$BI$3,"<="&8) -> 0 | F27: =SUMIFS('31_P&L'!$B$25:$BI$25,'31_P&L'!$B$3:$BI$3,">="&9,'31_P&L'!$B$3:$BI$3,"<="&11) -> -33305.52 | G27: =SUMIFS('31_P&L'!$B$25:$BI$25,'31_P&L'!$B$3:$BI$3,">="&12,'31_P&L'!$B$3:$BI$3,"<="&14) -> -4584.5654 | H27: =SUMIFS('31_P&L'!$B$25:$BI$25,'31_P&L'!$B$3:$BI$3,">="&15,'31_P&L'!$B$3:$BI$3,"<="&17) -> -3573.2642 | I27: =SUMIFS('31_P&L'!$B$25:$BI$25,'31_P&L'!$B$3:$BI$3,">="&18,'31_P&L'!$B$3:$BI$3,"<="&20) -> -2561.963 | J27: =SUMIFS('31_P&L'!$B$25:$BI$25,'31_P&L'!$B$3:$BI$3,">="&21,'31_P&L'!$B$3:$BI$3,"<="&23) -> -28363.162 | K27: =SUMIFS('31_P&L'!$B$25:$BI$25,'31_P&L'!$B$3:$BI$3,">="&24,'31_P&L'!$B$3:$BI$3,"<="&26) -> -80976.861 | L27: =SUMIFS('31_P&L'!$B$25:$BI$25,'31_P&L'!$B$3:$BI$3,">="&27,'31_P&L'!$B$3:$BI$3,"<="&29) -> -80437.5 | M27: =SUMIFS('31_P&L'!$B$25:$BI$25,'31_P&L'!$B$3:$BI$3,">="&30,'31_P&L'!$B$3:$BI$3,"<="&32) -> -80437.5 | N27: =SUMIFS('31_P&L'!$B$25:$BI$25,'31_P&L'!$B$3:$BI$3,">="&33,'31_P&L'!$B$3:$BI$3,"<="&35) -> 1029526.3 | O27: =SUMIFS('31_P&L'!$B$25:$BI$25,'31_P&L'!$B$3:$BI$3,">="&36,'31_P&L'!$B$3:$BI$3,"<="&38) -> 0 | P27: =SUMIFS('31_P&L'!$B$25:$BI$25,'31_P&L'!$B$3:$BI$3,">="&39,'31_P&L'!$B$3:$BI$3,"<="&41) -> 0 | Q27: =SUMIFS('31_P&L'!$B$25:$BI$25,'31_P&L'!$B$3:$BI$3,">="&42,'31_P&L'!$B$3:$BI$3,"<="&44) -> 0 | R27: =SUMIFS('31_P&L'!$B$25:$BI$25,'31_P&L'!$B$3:$BI$3,">="&45,'31_P&L'!$B$3:$BI$3,"<="&47) -> 0 | S27: =SUMIFS('31_P&L'!$B$25:$BI$25,'31_P&L'!$B$3:$BI$3,">="&48,'31_P&L'!$B$3:$BI$3,"<="&50) -> 0 | T27: =SUMIFS('31_P&L'!$B$25:$BI$25,'31_P&L'!$B$3:$BI$3,">="&51,'31_P&L'!$B$3:$BI$3,"<="&53) -> 0 | U27: =SUMIFS('31_P&L'!$B$25:$BI$25,'31_P&L'!$B$3:$BI$3,">="&54,'31_P&L'!$B$3:$BI$3,"<="&56) -> 0 | V27: =SUMIFS('31_P&L'!$B$25:$BI$25,'31_P&L'!$B$3:$BI$3,">="&57,'31_P&L'!$B$3:$BI$3,"<="&59) -> 0
A28: RESULTADO NETO ACUMULADO | C28: {=LOOKUP(2,1/('31_P&L'!$B$3:$BI$3<=2),'31_P&L'!$B$26:$BI$26)} -> 0 | D28: {=LOOKUP(2,1/('31_P&L'!$B$3:$BI$3<=5),'31_P&L'!$B$26:$BI$26)} -> 0 | E28: {=LOOKUP(2,1/('31_P&L'!$B$3:$BI$3<=8),'31_P&L'!$B$26:$BI$26)} -> 0 | F28: {=LOOKUP(2,1/('31_P&L'!$B$3:$BI$3<=11),'31_P&L'!$B$26:$BI$26)} -> -33305.52 | G28: {=LOOKUP(2,1/('31_P&L'!$B$3:$BI$3<=14),'31_P&L'!$B$26:$BI$26)} -> -37890.085 | H28: {=LOOKUP(2,1/('31_P&L'!$B$3:$BI$3<=17),'31_P&L'!$B$26:$BI$26)} -> -41463.349 | I28: {=LOOKUP(2,1/('31_P&L'!$B$3:$BI$3<=20),'31_P&L'!$B$26:$BI$26)} -> -44025.312 | J28: {=LOOKUP(2,1/('31_P&L'!$B$3:$BI$3<=23),'31_P&L'!$B$26:$BI$26)} -> -72388.474 | K28: {=LOOKUP(2,1/('31_P&L'!$B$3:$BI$3<=26),'31_P&L'!$B$26:$BI$26)} -> -153365.33 | L28: {=LOOKUP(2,1/('31_P&L'!$B$3:$BI$3<=29),'31_P&L'!$B$26:$BI$26)} -> -233802.83 | M28: {=LOOKUP(2,1/('31_P&L'!$B$3:$BI$3<=32),'31_P&L'!$B$26:$BI$26)} -> -314240.33 | N28: {=LOOKUP(2,1/('31_P&L'!$B$3:$BI$3<=35),'31_P&L'!$B$26:$BI$26)} -> 715285.95 | O28: {=LOOKUP(2,1/('31_P&L'!$B$3:$BI$3<=38),'31_P&L'!$B$26:$BI$26)} -> 715285.95 | P28: {=LOOKUP(2,1/('31_P&L'!$B$3:$BI$3<=41),'31_P&L'!$B$26:$BI$26)} -> 715285.95 | Q28: {=LOOKUP(2,1/('31_P&L'!$B$3:$BI$3<=44),'31_P&L'!$B$26:$BI$26)} -> 715285.95 | R28: {=LOOKUP(2,1/('31_P&L'!$B$3:$BI$3<=47),'31_P&L'!$B$26:$BI$26)} -> 715285.95 | S28: {=LOOKUP(2,1/('31_P&L'!$B$3:$BI$3<=50),'31_P&L'!$B$26:$BI$26)} -> 715285.95 | T28: {=LOOKUP(2,1/('31_P&L'!$B$3:$BI$3<=53),'31_P&L'!$B$26:$BI$26)} -> 715285.95 | U28: {=LOOKUP(2,1/('31_P&L'!$B$3:$BI$3<=56),'31_P&L'!$B$26:$BI$26)} -> 715285.95 | V28: {=LOOKUP(2,1/('31_P&L'!$B$3:$BI$3<=59),'31_P&L'!$B$26:$BI$26)} -> 715285.95
A30: Checks
A31: Margen EBITDA | C31: =IFERROR(C18/C9,0) -> 0 | D31: =IFERROR(D18/D9,0) -> 0 | E31: =IFERROR(E18/E9,0) -> 0 | F31: =IFERROR(F18/F9,0) -> 0 | G31: =IFERROR(G18/G9,0) -> 0 | H31: =IFERROR(H18/H9,0) -> 0 | I31: =IFERROR(I18/I9,0) -> 0 | J31: =IFERROR(J18/J9,0) -> 0 | ... V31: =IFERROR(V18/V9,0) -> 0
A32: Margen neto | C32: =IFERROR(C27/C9,0) -> 0 | D32: =IFERROR(D27/D9,0) -> 0 | E32: =IFERROR(E27/E9,0) -> 0 | F32: =IFERROR(F27/F9,0) -> 0 | G32: =IFERROR(G27/G9,0) -> 0 | H32: =IFERROR(H27/H9,0) -> 0 | I32: =IFERROR(I27/I9,0) -> 0 | J32: =IFERROR(J27/J9,0) -> 0 | ... V32: =IFERROR(V27/V9,0) -> 0
A33: Control: flujo venta + CAPEX | C33: =SUMIFS('31_P&L'!$B$31:$BI$31,'31_P&L'!$B$3:$BI$3,">="&0,'31_P&L'!$B$3:$BI$3,"<="&2) -> -1183546 | D33: =SUMIFS('31_P&L'!$B$31:$BI$31,'31_P&L'!$B$3:$BI$3,">="&3,'31_P&L'!$B$3:$BI$3,"<="&5) -> 0 | E33: =SUMIFS('31_P&L'!$B$31:$BI$31,'31_P&L'!$B$3:$BI$3,">="&6,'31_P&L'!$B$3:$BI$3,"<="&8) -> 0 | F33: =SUMIFS('31_P&L'!$B$31:$BI$31,'31_P&L'!$B$3:$BI$3,">="&9,'31_P&L'!$B$3:$BI$3,"<="&11) -> -269680.32 | G33: =SUMIFS('31_P&L'!$B$31:$BI$31,'31_P&L'!$B$3:$BI$3,">="&12,'31_P&L'!$B$3:$BI$3,"<="&14) -> -809040.96 | H33: =SUMIFS('31_P&L'!$B$31:$BI$31,'31_P&L'!$B$3:$BI$3,">="&15,'31_P&L'!$B$3:$BI$3,"<="&17) -> -809040.96 | I33: =SUMIFS('31_P&L'!$B$31:$BI$31,'31_P&L'!$B$3:$BI$3,">="&18,'31_P&L'!$B$3:$BI$3,"<="&20) -> -809040.96 | J33: =SUMIFS('31_P&L'!$B$31:$BI$31,'31_P&L'!$B$3:$BI$3,">="&21,'31_P&L'!$B$3:$BI$3,"<="&23) -> -791165.96 | K33: =SUMIFS('31_P&L'!$B$31:$BI$31,'31_P&L'!$B$3:$BI$3,">="&24,'31_P&L'!$B$3:$BI$3,"<="&26) -> -407665.96 | L33: =SUMIFS('31_P&L'!$B$31:$BI$31,'31_P&L'!$B$3:$BI$3,">="&27,'31_P&L'!$B$3:$BI$3,"<="&29) -> -233790.96 | M33: =SUMIFS('31_P&L'!$B$31:$BI$31,'31_P&L'!$B$3:$BI$3,">="&30,'31_P&L'!$B$3:$BI$3,"<="&32) -> -233790.96 | N33: =SUMIFS('31_P&L'!$B$31:$BI$31,'31_P&L'!$B$3:$BI$3,">="&33,'31_P&L'!$B$3:$BI$3,"<="&35) -> 6907039.4 | O33: =SUMIFS('31_P&L'!$B$31:$BI$31,'31_P&L'!$B$3:$BI$3,">="&36,'31_P&L'!$B$3:$BI$3,"<="&38) -> 0 | P33: =SUMIFS('31_P&L'!$B$31:$BI$31,'31_P&L'!$B$3:$BI$3,">="&39,'31_P&L'!$B$3:$BI$3,"<="&41) -> 0 | Q33: =SUMIFS('31_P&L'!$B$31:$BI$31,'31_P&L'!$B$3:$BI$3,">="&42,'31_P&L'!$B$3:$BI$3,"<="&44) -> 0 | R33: =SUMIFS('31_P&L'!$B$31:$BI$31,'31_P&L'!$B$3:$BI$3,">="&45,'31_P&L'!$B$3:$BI$3,"<="&47) -> 0 | S33: =SUMIFS('31_P&L'!$B$31:$BI$31,'31_P&L'!$B$3:$BI$3,">="&48,'31_P&L'!$B$3:$BI$3,"<="&50) -> 0 | T33: =SUMIFS('31_P&L'!$B$31:$BI$31,'31_P&L'!$B$3:$BI$3,">="&51,'31_P&L'!$B$3:$BI$3,"<="&53) -> 0 | U33: =SUMIFS('31_P&L'!$B$31:$BI$31,'31_P&L'!$B$3:$BI$3,">="&54,'31_P&L'!$B$3:$BI$3,"<="&56) -> 0 | V33: =SUMIFS('31_P&L'!$B$31:$BI$31,'31_P&L'!$B$3:$BI$3,">="&57,'31_P&L'!$B$3:$BI$3,"<="&59) -> 0
A34: Control: CAPEX total mensual | C34: =SUMIFS('31_P&L'!$B$32:$BI$32,'31_P&L'!$B$3:$BI$3,">="&0,'31_P&L'!$B$3:$BI$3,"<="&2) -> 1183546 | D34: =SUMIFS('31_P&L'!$B$32:$BI$32,'31_P&L'!$B$3:$BI$3,">="&3,'31_P&L'!$B$3:$BI$3,"<="&5) -> 0 | E34: =SUMIFS('31_P&L'!$B$32:$BI$32,'31_P&L'!$B$3:$BI$3,">="&6,'31_P&L'!$B$3:$BI$3,"<="&8) -> 0 | F34: =SUMIFS('31_P&L'!$B$32:$BI$32,'31_P&L'!$B$3:$BI$3,">="&9,'31_P&L'!$B$3:$BI$3,"<="&11) -> 269680.32 | G34: =SUMIFS('31_P&L'!$B$32:$BI$32,'31_P&L'!$B$3:$BI$3,">="&12,'31_P&L'!$B$3:$BI$3,"<="&14) -> 809040.96 | H34: =SUMIFS('31_P&L'!$B$32:$BI$32,'31_P&L'!$B$3:$BI$3,">="&15,'31_P&L'!$B$3:$BI$3,"<="&17) -> 809040.96 | I34: =SUMIFS('31_P&L'!$B$32:$BI$32,'31_P&L'!$B$3:$BI$3,">="&18,'31_P&L'!$B$3:$BI$3,"<="&20) -> 809040.96 | J34: =SUMIFS('31_P&L'!$B$32:$BI$32,'31_P&L'!$B$3:$BI$3,">="&21,'31_P&L'!$B$3:$BI$3,"<="&23) -> 809040.96 | K34: =SUMIFS('31_P&L'!$B$32:$BI$32,'31_P&L'!$B$3:$BI$3,">="&24,'31_P&L'!$B$3:$BI$3,"<="&26) -> 809040.96 | L34: =SUMIFS('31_P&L'!$B$32:$BI$32,'31_P&L'!$B$3:$BI$3,">="&27,'31_P&L'!$B$3:$BI$3,"<="&29) -> 809040.96 | M34: =SUMIFS('31_P&L'!$B$32:$BI$32,'31_P&L'!$B$3:$BI$3,">="&30,'31_P&L'!$B$3:$BI$3,"<="&32) -> 809040.96 | N34: =SUMIFS('31_P&L'!$B$32:$BI$32,'31_P&L'!$B$3:$BI$3,">="&33,'31_P&L'!$B$3:$BI$3,"<="&35) -> 539360.64 | O34: =SUMIFS('31_P&L'!$B$32:$BI$32,'31_P&L'!$B$3:$BI$3,">="&36,'31_P&L'!$B$3:$BI$3,"<="&38) -> 0 | P34: =SUMIFS('31_P&L'!$B$32:$BI$32,'31_P&L'!$B$3:$BI$3,">="&39,'31_P&L'!$B$3:$BI$3,"<="&41) -> 0 | Q34: =SUMIFS('31_P&L'!$B$32:$BI$32,'31_P&L'!$B$3:$BI$3,">="&42,'31_P&L'!$B$3:$BI$3,"<="&44) -> 0 | R34: =SUMIFS('31_P&L'!$B$32:$BI$32,'31_P&L'!$B$3:$BI$3,">="&45,'31_P&L'!$B$3:$BI$3,"<="&47) -> 0 | S34: =SUMIFS('31_P&L'!$B$32:$BI$32,'31_P&L'!$B$3:$BI$3,">="&48,'31_P&L'!$B$3:$BI$3,"<="&50) -> 0 | T34: =SUMIFS('31_P&L'!$B$32:$BI$32,'31_P&L'!$B$3:$BI$3,">="&51,'31_P&L'!$B$3:$BI$3,"<="&53) -> 0 | U34: =SUMIFS('31_P&L'!$B$32:$BI$32,'31_P&L'!$B$3:$BI$3,">="&54,'31_P&L'!$B$3:$BI$3,"<="&56) -> 0 | V34: =SUMIFS('31_P&L'!$B$32:$BI$32,'31_P&L'!$B$3:$BI$3,">="&57,'31_P&L'!$B$3:$BI$3,"<="&59) -> 0

Sheet 42_BALANCE_TRIMESTRAL
A1: BALANCE TRIMESTRAL
A2: Tipología: | B2: ='00_ESTRATEGIA'!B3 -> Unifamiliar seg. | D2: Escenario: | E2: ='00_ESTRATEGIA'!B4 -> Base
A4: Mes | B4: Y0 | C4: Y0 | D4: Y0 | E4: Y0 | F4: Y1 | G4: Y1 | H4: Y1 | I4: Y1 | J4: Y2 | K4: Y2 | L4: Y2 | M4: Y2 | N4: Y3 | O4: Y3 | P4: Y3 | Q4: Y3 | R4: Y4 | S4: Y4 | T4: Y4 | U4: Y4
A5: Año | B5: 2 | C5: 5 | D5: 8 | E5: 11 | F5: 14 | G5: 17 | H5: 20 | I5: 23 | J5: 26 | K5: 29 | L5: 32 | M5: 35 | N5: 38 | O5: 41 | P5: 44 | Q5: 47 | R5: 50 | S5: 53 | T5: 56 | U5: 59
A6: Periodo | B6: Q0 | C6: Q1 | D6: Q2 | E6: Q3 | F6: Q4 | G6: Q5 | H6: Q6 | I6: Q7 | J6: Q8 | K6: Q9 | L6: Q10 | M6: Q11 | N6: Q12 | O6: Q13 | P6: Q14 | Q6: Q15 | R6: Q16 | S6: Q17 | T6: Q18 | U6: Q19
A8: ACTIVO
A9: Activo No Corriente
A10: Inmovilizado / Inversiones LP | B10: {=LOOKUP(2,1/('32_BALANCE'!$B$4:$BI$4<=B$5),'32_BALANCE'!$B$10:$BI$10)} -> 0 | C10: {=LOOKUP(2,1/('32_BALANCE'!$B$4:$BI$4<=C$5),'32_BALANCE'!$B$10:$BI$10)} -> 0 | D10: {=LOOKUP(2,1/('32_BALANCE'!$B$4:$BI$4<=D$5),'32_BALANCE'!$B$10:$BI$10)} -> 0 | E10: {=LOOKUP(2,1/('32_BALANCE'!$B$4:$BI$4<=E$5),'32_BALANCE'!$B$10:$BI$10)} -> 0 | F10: {=LOOKUP(2,1/('32_BALANCE'!$B$4:$BI$4<=F$5),'32_BALANCE'!$B$10:$BI$10)} -> 0 | G10: {=LOOKUP(2,1/('32_BALANCE'!$B$4:$BI$4<=G$5),'32_BALANCE'!$B$10:$BI$10)} -> 0 | H10: {=LOOKUP(2,1/('32_BALANCE'!$B$4:$BI$4<=H$5),'32_BALANCE'!$B$10:$BI$10)} -> 0 | I10: {=LOOKUP(2,1/('32_BALANCE'!$B$4:$BI$4<=I$5),'32_BALANCE'!$B$10:$BI$10)} -> 0 | ... U10: {=LOOKUP(2,1/('32_BALANCE'!$B$4:$BI$4<=U$5),'32_BALANCE'!$B$10:$BI$10)} -> 0
A11: Total Activo No Corriente | B11: {=LOOKUP(2,1/('32_BALANCE'!$B$4:$BI$4<=B$5),'32_BALANCE'!$B$11:$BI$11)} -> 0 | C11: {=LOOKUP(2,1/('32_BALANCE'!$B$4:$BI$4<=C$5),'32_BALANCE'!$B$11:$BI$11)} -> 0 | D11: {=LOOKUP(2,1/('32_BALANCE'!$B$4:$BI$4<=D$5),'32_BALANCE'!$B$11:$BI$11)} -> 0 | E11: {=LOOKUP(2,1/('32_BALANCE'!$B$4:$BI$4<=E$5),'32_BALANCE'!$B$11:$BI$11)} -> 0 | F11: {=LOOKUP(2,1/('32_BALANCE'!$B$4:$BI$4<=F$5),'32_BALANCE'!$B$11:$BI$11)} -> 0 | G11: {=LOOKUP(2,1/('32_BALANCE'!$B$4:$BI$4<=G$5),'32_BALANCE'!$B$11:$BI$11)} -> 0 | H11: {=LOOKUP(2,1/('32_BALANCE'!$B$4:$BI$4<=H$5),'32_BALANCE'!$B$11:$BI$11)} -> 0 | I11: {=LOOKUP(2,1/('32_BALANCE'!$B$4:$BI$4<=I$5),'32_BALANCE'!$B$11:$BI$11)} -> 0 | ... U11: {=LOOKUP(2,1/('32_BALANCE'!$B$4:$BI$4<=U$5),'32_BALANCE'!$B$11:$BI$11)} -> 0
A13: Activo Corriente
A14: Existencias suelo | B14: {=LOOKUP(2,1/('32_BALANCE'!$B$4:$BI$4<=B$5),'32_BALANCE'!$B$14:$BI$14)} -> 1183546 | C14: {=LOOKUP(2,1/('32_BALANCE'!$B$4:$BI$4<=C$5),'32_BALANCE'!$B$14:$BI$14)} -> 1183546 | D14: {=LOOKUP(2,1/('32_BALANCE'!$B$4:$BI$4<=D$5),'32_BALANCE'!$B$14:$BI$14)} -> 1183546 | E14: {=LOOKUP(2,1/('32_BALANCE'!$B$4:$BI$4<=E$5),'32_BALANCE'!$B$14:$BI$14)} -> 1183546 | F14: {=LOOKUP(2,1/('32_BALANCE'!$B$4:$BI$4<=F$5),'32_BALANCE'!$B$14:$BI$14)} -> 1183546 | G14: {=LOOKUP(2,1/('32_BALANCE'!$B$4:$BI$4<=G$5),'32_BALANCE'!$B$14:$BI$14)} -> 1183546 | H14: {=LOOKUP(2,1/('32_BALANCE'!$B$4:$BI$4<=H$5),'32_BALANCE'!$B$14:$BI$14)} -> 1183546 | I14: {=LOOKUP(2,1/('32_BALANCE'!$B$4:$BI$4<=I$5),'32_BALANCE'!$B$14:$BI$14)} -> 1183546 | ... U14: {=LOOKUP(2,1/('32_BALANCE'!$B$4:$BI$4<=U$5),'32_BALANCE'!$B$14:$BI$14)} -> 0
A15: Existencias construcción | B15: {=LOOKUP(2,1/('32_BALANCE'!$B$4:$BI$4<=B$5),'32_BALANCE'!$B$15:$BI$15)} -> 0 | C15: {=LOOKUP(2,1/('32_BALANCE'!$B$4:$BI$4<=C$5),'32_BALANCE'!$B$15:$BI$15)} -> 0 | D15: {=LOOKUP(2,1/('32_BALANCE'!$B$4:$BI$4<=D$5),'32_BALANCE'!$B$15:$BI$15)} -> 0 | E15: {=LOOKUP(2,1/('32_BALANCE'!$B$4:$BI$4<=E$5),'32_BALANCE'!$B$15:$BI$15)} -> 269680.32 | F15: {=LOOKUP(2,1/('32_BALANCE'!$B$4:$BI$4<=F$5),'32_BALANCE'!$B$15:$BI$15)} -> 1078721.3 | G15: {=LOOKUP(2,1/('32_BALANCE'!$B$4:$BI$4<=G$5),'32_BALANCE'!$B$15:$BI$15)} -> 1887762.2 | H15: {=LOOKUP(2,1/('32_BALANCE'!$B$4:$BI$4<=H$5),'32_BALANCE'!$B$15:$BI$15)} -> 2696803.2 | I15: {=LOOKUP(2,1/('32_BALANCE'!$B$4:$BI$4<=I$5),'32_BALANCE'!$B$15:$BI$15)} -> 3505844.2 | ... U15: {=LOOKUP(2,1/('32_BALANCE'!$B$4:$BI$4<=U$5),'32_BALANCE'!$B$15:$BI$15)} -> 0
A16: Existencias intereses capitalizados | B16: {=LOOKUP(2,1/('32_BALANCE'!$B$4:$BI$4<=B$5),'32_BALANCE'!$B$16:$BI$16)} -> 0 | C16: {=LOOKUP(2,1/('32_BALANCE'!$B$4:$BI$4<=C$5),'32_BALANCE'!$B$16:$BI$16)} -> 0 | D16: {=LOOKUP(2,1/('32_BALANCE'!$B$4:$BI$4<=D$5),'32_BALANCE'!$B$16:$BI$16)} -> 0 | E16: {=LOOKUP(2,1/('32_BALANCE'!$B$4:$BI$4<=E$5),'32_BALANCE'!$B$16:$BI$16)} -> 618.0174 | F16: {=LOOKUP(2,1/('32_BALANCE'!$B$4:$BI$4<=F$5),'32_BALANCE'!$B$16:$BI$16)} -> 9928.0125 | G16: {=LOOKUP(2,1/('32_BALANCE'!$B$4:$BI$4<=G$5),'32_BALANCE'!$B$16:$BI$16)} -> 30541.985 | H16: {=LOOKUP(2,1/('32_BALANCE'!$B$4:$BI$4<=H$5),'32_BALANCE'!$B$16:$BI$16)} -> 62616.079 | I16: {=LOOKUP(2,1/('32_BALANCE'!$B$4:$BI$4<=I$5),'32_BALANCE'!$B$16:$BI$16)} -> 106308.59 | ... U16: {=LOOKUP(2,1/('32_BALANCE'!$B$4:$BI$4<=U$5),'32_BALANCE'!$B$16:$BI$16)} -> 0
A17: Clientes / cuentas a cobrar | B17: {=LOOKUP(2,1/('32_BALANCE'!$B$4:$BI$4<=B$5),'32_BALANCE'!$B$17:$BI$17)} -> 0 | C17: {=LOOKUP(2,1/('32_BALANCE'!$B$4:$BI$4<=C$5),'32_BALANCE'!$B$17:$BI$17)} -> 0 | D17: {=LOOKUP(2,1/('32_BALANCE'!$B$4:$BI$4<=D$5),'32_BALANCE'!$B$17:$BI$17)} -> 0 | E17: {=LOOKUP(2,1/('32_BALANCE'!$B$4:$BI$4<=E$5),'32_BALANCE'!$B$17:$BI$17)} -> 0 | F17: {=LOOKUP(2,1/('32_BALANCE'!$B$4:$BI$4<=F$5),'32_BALANCE'!$B$17:$BI$17)} -> 0 | G17: {=LOOKUP(2,1/('32_BALANCE'!$B$4:$BI$4<=G$5),'32_BALANCE'!$B$17:$BI$17)} -> 0 | H17: {=LOOKUP(2,1/('32_BALANCE'!$B$4:$BI$4<=H$5),'32_BALANCE'!$B$17:$BI$17)} -> 0 | I17: {=LOOKUP(2,1/('32_BALANCE'!$B$4:$BI$4<=I$5),'32_BALANCE'!$B$17:$BI$17)} -> 0 | ... U17: {=LOOKUP(2,1/('32_BALANCE'!$B$4:$BI$4<=U$5),'32_BALANCE'!$B$17:$BI$17)} -> 0
A18: Tesorería | B18: {=LOOKUP(2,1/('32_BALANCE'!$B$4:$BI$4<=B$5),'32_BALANCE'!$B$18:$BI$18)} -> 0 | C18: {=LOOKUP(2,1/('32_BALANCE'!$B$4:$BI$4<=C$5),'32_BALANCE'!$B$18:$BI$18)} -> 0 | D18: {=LOOKUP(2,1/('32_BALANCE'!$B$4:$BI$4<=D$5),'32_BALANCE'!$B$18:$BI$18)} -> 0 | E18: {=LOOKUP(2,1/('32_BALANCE'!$B$4:$BI$4<=E$5),'32_BALANCE'!$B$18:$BI$18)} -> 0 | F18: {=LOOKUP(2,1/('32_BALANCE'!$B$4:$BI$4<=F$5),'32_BALANCE'!$B$18:$BI$18)} -> 0 | G18: {=LOOKUP(2,1/('32_BALANCE'!$B$4:$BI$4<=G$5),'32_BALANCE'!$B$18:$BI$18)} -> 0 | H18: {=LOOKUP(2,1/('32_BALANCE'!$B$4:$BI$4<=H$5),'32_BALANCE'!$B$18:$BI$18)} -> 0 | I18: {=LOOKUP(2,1/('32_BALANCE'!$B$4:$BI$4<=I$5),'32_BALANCE'!$B$18:$BI$18)} -> 17470.48 | ... U18: {=LOOKUP(2,1/('32_BALANCE'!$B$4:$BI$4<=U$5),'32_BALANCE'!$B$18:$BI$18)} -> 2596046
A19: Total Activo Corriente | B19: {=LOOKUP(2,1/('32_BALANCE'!$B$4:$BI$4<=B$5),'32_BALANCE'!$B$19:$BI$19)} -> 1183546 | C19: {=LOOKUP(2,1/('32_BALANCE'!$B$4:$BI$4<=C$5),'32_BALANCE'!$B$19:$BI$19)} -> 1183546 | D19: {=LOOKUP(2,1/('32_BALANCE'!$B$4:$BI$4<=D$5),'32_BALANCE'!$B$19:$BI$19)} -> 1183546 | E19: {=LOOKUP(2,1/('32_BALANCE'!$B$4:$BI$4<=E$5),'32_BALANCE'!$B$19:$BI$19)} -> 1453844.3 | F19: {=LOOKUP(2,1/('32_BALANCE'!$B$4:$BI$4<=F$5),'32_BALANCE'!$B$19:$BI$19)} -> 2272195.3 | G19: {=LOOKUP(2,1/('32_BALANCE'!$B$4:$BI$4<=G$5),'32_BALANCE'!$B$19:$BI$19)} -> 3101850.2 | H19: {=LOOKUP(2,1/('32_BALANCE'!$B$4:$BI$4<=H$5),'32_BALANCE'!$B$19:$BI$19)} -> 3942965.3 | I19: {=LOOKUP(2,1/('32_BALANCE'!$B$4:$BI$4<=I$5),'32_BALANCE'!$B$19:$BI$19)} -> 4813169.2 | ... U19: {=LOOKUP(2,1/('32_BALANCE'!$B$4:$BI$4<=U$5),'32_BALANCE'!$B$19:$BI$19)} -> 2596046
A21: TOTAL ACTIVO | B21: {=LOOKUP(2,1/('32_BALANCE'!$B$4:$BI$4<=B$5),'32_BALANCE'!$B$21:$BI$21)} -> 1183546 | C21: {=LOOKUP(2,1/('32_BALANCE'!$B$4:$BI$4<=C$5),'32_BALANCE'!$B$21:$BI$21)} -> 1183546 | D21: {=LOOKUP(2,1/('32_BALANCE'!$B$4:$BI$4<=D$5),'32_BALANCE'!$B$21:$BI$21)} -> 1183546 | E21: {=LOOKUP(2,1/('32_BALANCE'!$B$4:$BI$4<=E$5),'32_BALANCE'!$B$21:$BI$21)} -> 1453844.3 | F21: {=LOOKUP(2,1/('32_BALANCE'!$B$4:$BI$4<=F$5),'32_BALANCE'!$B$21:$BI$21)} -> 2272195.3 | G21: {=LOOKUP(2,1/('32_BALANCE'!$B$4:$BI$4<=G$5),'32_BALANCE'!$B$21:$BI$21)} -> 3101850.2 | H21: {=LOOKUP(2,1/('32_BALANCE'!$B$4:$BI$4<=H$5),'32_BALANCE'!$B$21:$BI$21)} -> 3942965.3 | I21: {=LOOKUP(2,1/('32_BALANCE'!$B$4:$BI$4<=I$5),'32_BALANCE'!$B$21:$BI$21)} -> 4813169.2 | ... U21: {=LOOKUP(2,1/('32_BALANCE'!$B$4:$BI$4<=U$5),'32_BALANCE'!$B$21:$BI$21)} -> 2596046
A23: PASIVO
A24: Pasivo No Corriente
A25: Deuda con entidades de crédito | B25: {=LOOKUP(2,1/('32_BALANCE'!$B$4:$BI$4<=B$5),'32_BALANCE'!$B$25:$BI$25)} -> 0 | C25: {=LOOKUP(2,1/('32_BALANCE'!$B$4:$BI$4<=C$5),'32_BALANCE'!$B$25:$BI$25)} -> 0 | D25: {=LOOKUP(2,1/('32_BALANCE'!$B$4:$BI$4<=D$5),'32_BALANCE'!$B$25:$BI$25)} -> 0 | E25: {=LOOKUP(2,1/('32_BALANCE'!$B$4:$BI$4<=E$5),'32_BALANCE'!$B$25:$BI$25)} -> 270298.34 | F25: {=LOOKUP(2,1/('32_BALANCE'!$B$4:$BI$4<=F$5),'32_BALANCE'!$B$25:$BI$25)} -> 1088649.3 | G25: {=LOOKUP(2,1/('32_BALANCE'!$B$4:$BI$4<=G$5),'32_BALANCE'!$B$25:$BI$25)} -> 1918304.2 | H25: {=LOOKUP(2,1/('32_BALANCE'!$B$4:$BI$4<=H$5),'32_BALANCE'!$B$25:$BI$25)} -> 2759419.3 | I25: {=LOOKUP(2,1/('32_BALANCE'!$B$4:$BI$4<=I$5),'32_BALANCE'!$B$25:$BI$25)} -> 3612152.8 | ... U25: {=LOOKUP(2,1/('32_BALANCE'!$B$4:$BI$4<=U$5),'32_BALANCE'!$B$25:$BI$25)} -> 0
A26: Total Pasivo No Corriente | B26: {=LOOKUP(2,1/('32_BALANCE'!$B$4:$BI$4<=B$5),'32_BALANCE'!$B$26:$BI$26)} -> 0 | C26: {=LOOKUP(2,1/('32_BALANCE'!$B$4:$BI$4<=C$5),'32_BALANCE'!$B$26:$BI$26)} -> 0 | D26: {=LOOKUP(2,1/('32_BALANCE'!$B$4:$BI$4<=D$5),'32_BALANCE'!$B$26:$BI$26)} -> 0 | E26: {=LOOKUP(2,1/('32_BALANCE'!$B$4:$BI$4<=E$5),'32_BALANCE'!$B$26:$BI$26)} -> 270298.34 | F26: {=LOOKUP(2,1/('32_BALANCE'!$B$4:$BI$4<=F$5),'32_BALANCE'!$B$26:$BI$26)} -> 1088649.3 | G26: {=LOOKUP(2,1/('32_BALANCE'!$B$4:$BI$4<=G$5),'32_BALANCE'!$B$26:$BI$26)} -> 1918304.2 | H26: {=LOOKUP(2,1/('32_BALANCE'!$B$4:$BI$4<=H$5),'32_BALANCE'!$B$26:$BI$26)} -> 2759419.3 | I26: {=LOOKUP(2,1/('32_BALANCE'!$B$4:$BI$4<=I$5),'32_BALANCE'!$B$26:$BI$26)} -> 3612152.8 | ... U26: {=LOOKUP(2,1/('32_BALANCE'!$B$4:$BI$4<=U$5),'32_BALANCE'!$B$26:$BI$26)} -> 0
A27: Pasivo Corriente
A28: Anticipos de clientes | B28: {=LOOKUP(2,1/('32_BALANCE'!$B$4:$BI$4<=B$5),'32_BALANCE'!$B$28:$BI$28)} -> 0 | C28: {=LOOKUP(2,1/('32_BALANCE'!$B$4:$BI$4<=C$5),'32_BALANCE'!$B$28:$BI$28)} -> 0 | D28: {=LOOKUP(2,1/('32_BALANCE'!$B$4:$BI$4<=D$5),'32_BALANCE'!$B$28:$BI$28)} -> 0 | E28: {=LOOKUP(2,1/('32_BALANCE'!$B$4:$BI$4<=E$5),'32_BALANCE'!$B$28:$BI$28)} -> 0 | F28: {=LOOKUP(2,1/('32_BALANCE'!$B$4:$BI$4<=F$5),'32_BALANCE'!$B$28:$BI$28)} -> 0 | G28: {=LOOKUP(2,1/('32_BALANCE'!$B$4:$BI$4<=G$5),'32_BALANCE'!$B$28:$BI$28)} -> 0 | H28: {=LOOKUP(2,1/('32_BALANCE'!$B$4:$BI$4<=H$5),'32_BALANCE'!$B$28:$BI$28)} -> 0 | I28: {=LOOKUP(2,1/('32_BALANCE'!$B$4:$BI$4<=I$5),'32_BALANCE'!$B$28:$BI$28)} -> 44687.5 | ... U28: {=LOOKUP(2,1/('32_BALANCE'!$B$4:$BI$4<=U$5),'32_BALANCE'!$B$28:$BI$28)} -> 0
A29: Total Pasivo Corriente | B29: {=LOOKUP(2,1/('32_BALANCE'!$B$4:$BI$4<=B$5),'32_BALANCE'!$B$29:$BI$29)} -> 0 | C29: {=LOOKUP(2,1/('32_BALANCE'!$B$4:$BI$4<=C$5),'32_BALANCE'!$B$29:$BI$29)} -> 0 | D29: {=LOOKUP(2,1/('32_BALANCE'!$B$4:$BI$4<=D$5),'32_BALANCE'!$B$29:$BI$29)} -> 0 | E29: {=LOOKUP(2,1/('32_BALANCE'!$B$4:$BI$4<=E$5),'32_BALANCE'!$B$29:$BI$29)} -> 0 | F29: {=LOOKUP(2,1/('32_BALANCE'!$B$4:$BI$4<=F$5),'32_BALANCE'!$B$29:$BI$29)} -> 0 | G29: {=LOOKUP(2,1/('32_BALANCE'!$B$4:$BI$4<=G$5),'32_BALANCE'!$B$29:$BI$29)} -> 0 | H29: {=LOOKUP(2,1/('32_BALANCE'!$B$4:$BI$4<=H$5),'32_BALANCE'!$B$29:$BI$29)} -> 0 | I29: {=LOOKUP(2,1/('32_BALANCE'!$B$4:$BI$4<=I$5),'32_BALANCE'!$B$29:$BI$29)} -> 44687.5 | ... U29: {=LOOKUP(2,1/('32_BALANCE'!$B$4:$BI$4<=U$5),'32_BALANCE'!$B$29:$BI$29)} -> 0
A31: TOTAL PASIVO | B31: {=LOOKUP(2,1/('32_BALANCE'!$B$4:$BI$4<=B$5),'32_BALANCE'!$B$31:$BI$31)} -> 0 | C31: {=LOOKUP(2,1/('32_BALANCE'!$B$4:$BI$4<=C$5),'32_BALANCE'!$B$31:$BI$31)} -> 0 | D31: {=LOOKUP(2,1/('32_BALANCE'!$B$4:$BI$4<=D$5),'32_BALANCE'!$B$31:$BI$31)} -> 0 | E31: {=LOOKUP(2,1/('32_BALANCE'!$B$4:$BI$4<=E$5),'32_BALANCE'!$B$31:$BI$31)} -> 270298.34 | F31: {=LOOKUP(2,1/('32_BALANCE'!$B$4:$BI$4<=F$5),'32_BALANCE'!$B$31:$BI$31)} -> 1088649.3 | G31: {=LOOKUP(2,1/('32_BALANCE'!$B$4:$BI$4<=G$5),'32_BALANCE'!$B$31:$BI$31)} -> 1918304.2 | H31: {=LOOKUP(2,1/('32_BALANCE'!$B$4:$BI$4<=H$5),'32_BALANCE'!$B$31:$BI$31)} -> 2759419.3 | I31: {=LOOKUP(2,1/('32_BALANCE'!$B$4:$BI$4<=I$5),'32_BALANCE'!$B$31:$BI$31)} -> 3656840.3 | ... U31: {=LOOKUP(2,1/('32_BALANCE'!$B$4:$BI$4<=U$5),'32_BALANCE'!$B$31:$BI$31)} -> 0
A33: PATRIMONIO NETO
A34: Capital aportado (acumulado) | B34: {=LOOKUP(2,1/('32_BALANCE'!$B$4:$BI$4<=B$5),'32_BALANCE'!$B$34:$BI$34)} -> 1183546 | C34: {=LOOKUP(2,1/('32_BALANCE'!$B$4:$BI$4<=C$5),'32_BALANCE'!$B$34:$BI$34)} -> 1183546 | D34: {=LOOKUP(2,1/('32_BALANCE'!$B$4:$BI$4<=D$5),'32_BALANCE'!$B$34:$BI$34)} -> 1183546 | E34: {=LOOKUP(2,1/('32_BALANCE'!$B$4:$BI$4<=E$5),'32_BALANCE'!$B$34:$BI$34)} -> 1216851.5 | F34: {=LOOKUP(2,1/('32_BALANCE'!$B$4:$BI$4<=F$5),'32_BALANCE'!$B$34:$BI$34)} -> 1221436.1 | G34: {=LOOKUP(2,1/('32_BALANCE'!$B$4:$BI$4<=G$5),'32_BALANCE'!$B$34:$BI$34)} -> 1225009.3 | H34: {=LOOKUP(2,1/('32_BALANCE'!$B$4:$BI$4<=H$5),'32_BALANCE'!$B$34:$BI$34)} -> 1227571.3 | I34: {=LOOKUP(2,1/('32_BALANCE'!$B$4:$BI$4<=I$5),'32_BALANCE'!$B$34:$BI$34)} -> 1228717.5 | ... U34: {=LOOKUP(2,1/('32_BALANCE'!$B$4:$BI$4<=U$5),'32_BALANCE'!$B$34:$BI$34)} -> 1880760
A35: Resultados acumulados (según P&L) | B35: {=LOOKUP(2,1/('32_BALANCE'!$B$4:$BI$4<=B$5),'32_BALANCE'!$B$35:$BI$35)} -> 0 | C35: {=LOOKUP(2,1/('32_BALANCE'!$B$4:$BI$4<=C$5),'32_BALANCE'!$B$35:$BI$35)} -> 0 | D35: {=LOOKUP(2,1/('32_BALANCE'!$B$4:$BI$4<=D$5),'32_BALANCE'!$B$35:$BI$35)} -> 0 | E35: {=LOOKUP(2,1/('32_BALANCE'!$B$4:$BI$4<=E$5),'32_BALANCE'!$B$35:$BI$35)} -> -33305.52 | F35: {=LOOKUP(2,1/('32_BALANCE'!$B$4:$BI$4<=F$5),'32_BALANCE'!$B$35:$BI$35)} -> -37890.085 | G35: {=LOOKUP(2,1/('32_BALANCE'!$B$4:$BI$4<=G$5),'32_BALANCE'!$B$35:$BI$35)} -> -41463.349 | H35: {=LOOKUP(2,1/('32_BALANCE'!$B$4:$BI$4<=H$5),'32_BALANCE'!$B$35:$BI$35)} -> -44025.312 | I35: {=LOOKUP(2,1/('32_BALANCE'!$B$4:$BI$4<=I$5),'32_BALANCE'!$B$35:$BI$35)} -> -72388.474 | ... U35: {=LOOKUP(2,1/('32_BALANCE'!$B$4:$BI$4<=U$5),'32_BALANCE'!$B$35:$BI$35)} -> 715285.95
A36: TOTAL PATRIMONIO NETO | B36: {=LOOKUP(2,1/('32_BALANCE'!$B$4:$BI$4<=B$5),'32_BALANCE'!$B$36:$BI$36)} -> 1183546 | C36: {=LOOKUP(2,1/('32_BALANCE'!$B$4:$BI$4<=C$5),'32_BALANCE'!$B$36:$BI$36)} -> 1183546 | D36: {=LOOKUP(2,1/('32_BALANCE'!$B$4:$BI$4<=D$5),'32_BALANCE'!$B$36:$BI$36)} -> 1183546 | E36: {=LOOKUP(2,1/('32_BALANCE'!$B$4:$BI$4<=E$5),'32_BALANCE'!$B$36:$BI$36)} -> 1183546 | F36: {=LOOKUP(2,1/('32_BALANCE'!$B$4:$BI$4<=F$5),'32_BALANCE'!$B$36:$BI$36)} -> 1183546 | G36: {=LOOKUP(2,1/('32_BALANCE'!$B$4:$BI$4<=G$5),'32_BALANCE'!$B$36:$BI$36)} -> 1183546 | H36: {=LOOKUP(2,1/('32_BALANCE'!$B$4:$BI$4<=H$5),'32_BALANCE'!$B$36:$BI$36)} -> 1183546 | I36: {=LOOKUP(2,1/('32_BALANCE'!$B$4:$BI$4<=I$5),'32_BALANCE'!$B$36:$BI$36)} -> 1156329 | ... U36: {=LOOKUP(2,1/('32_BALANCE'!$B$4:$BI$4<=U$5),'32_BALANCE'!$B$36:$BI$36)} -> 2596046
A38: TOTAL PASIVO + PN | B38: {=LOOKUP(2,1/('32_BALANCE'!$B$4:$BI$4<=B$5),'32_BALANCE'!$B$38:$BI$38)} -> 1183546 | C38: {=LOOKUP(2,1/('32_BALANCE'!$B$4:$BI$4<=C$5),'32_BALANCE'!$B$38:$BI$38)} -> 1183546 | D38: {=LOOKUP(2,1/('32_BALANCE'!$B$4:$BI$4<=D$5),'32_BALANCE'!$B$38:$BI$38)} -> 1183546 | E38: {=LOOKUP(2,1/('32_BALANCE'!$B$4:$BI$4<=E$5),'32_BALANCE'!$B$38:$BI$38)} -> 1453844.3 | F38: {=LOOKUP(2,1/('32_BALANCE'!$B$4:$BI$4<=F$5),'32_BALANCE'!$B$38:$BI$38)} -> 2272195.3 | G38: {=LOOKUP(2,1/('32_BALANCE'!$B$4:$BI$4<=G$5),'32_BALANCE'!$B$38:$BI$38)} -> 3101850.2 | H38: {=LOOKUP(2,1/('32_BALANCE'!$B$4:$BI$4<=H$5),'32_BALANCE'!$B$38:$BI$38)} -> 3942965.3 | I38: {=LOOKUP(2,1/('32_BALANCE'!$B$4:$BI$4<=I$5),'32_BALANCE'!$B$38:$BI$38)} -> 4813169.2 | ... U38: {=LOOKUP(2,1/('32_BALANCE'!$B$4:$BI$4<=U$5),'32_BALANCE'!$B$38:$BI$38)} -> 2596046
A40: CHECK ACTIVO - PASIVO - PN | B40: =LOOKUP(2,1/('32_BALANCE'!$B$5:$BI$5=B$4),'32_BALANCE'!$B$40:$BI$40) -> 0 | C40: =LOOKUP(2,1/('32_BALANCE'!$B$5:$BI$5=C$4),'32_BALANCE'!$B$40:$BI$40) -> 0 | D40: =LOOKUP(2,1/('32_BALANCE'!$B$5:$BI$5=D$4),'32_BALANCE'!$B$40:$BI$40) -> 0 | E40: =LOOKUP(2,1/('32_BALANCE'!$B$5:$BI$5=E$4),'32_BALANCE'!$B$40:$BI$40) -> 0 | F40: =LOOKUP(2,1/('32_BALANCE'!$B$5:$BI$5=F$4),'32_BALANCE'!$B$40:$BI$40) -> 0
